Workbook
Name Slicer_Account_Manager: #N/A
Name Slicer_Region: #N/A

Sheet Summary
B2: RECEIVABLE SUMMARY(In $)
B3: Sum of USD AMOUNT | C3: Column Labels
B4: Row Labels | C4: 0-30 days | D4: 31-60 days | E4: 61-90 days | F4: Over 90+ days | G4: Grand Total
B5: EU/UK | C5: 36034.993 | D5: 4096.0347 | E5: 4162.1359 | F5: 4250.9684 | G5: 48544.132
B6: APAC | C6: 304837.31 | D6: 40947.48 | E6: 65412.636 | F6: 51245.138 | G6: 462442.56
B7: Shared Center | C7: 35014.798 | D7: 23869.362 | E7: 8504.5 | F7: 78993.5 | G7: 146382.16
B8: Americas | C8: 201735.55 | D8: 21503.113 | E8: 168.33774 | F8: 18888.387 | G8: 242295.38
B9: MEA | C9: 61256.36 | D9: 8122.75 | E9: 7766.25 | F9: 12745.24 | G9: 89890.6
B10: Grand Total | C10: 638879.01 | D10: 98538.739 | E10: 86013.86 | F10: 166123.23 | G10: 989554.84
B13: Regional Outstanding (In $)
B14: Region | C14: 0-30 days | D14: 31-60 days | E14: 61-90 days | F14: Over 90+ days | G14: Grand Total | H14: Region-wise contribution(%)
B15: EU/UK | C15: =GETPIVOTDATA("USD AMOUNT",$B$3,"Region","EU/UK","Ageing Tier","0-30 days") -> 36034.993 | D15: =GETPIVOTDATA("USD AMOUNT",$B$3,"Region","EU/UK","Ageing Tier","31-60 days") -> 4096.0347 | E15: =GETPIVOTDATA("USD AMOUNT",$B$3,"Region","EU/UK","Ageing Tier","61-90 days") -> 4162.1359 | F15: =GETPIVOTDATA("USD AMOUNT",$B$3,"Region","EU/UK","Ageing Tier","Over 90+ days") -> 4250.9684 | G15: =SUM(C15:F15) -> 48544.132 | H15: =G15/G20 -> 0.049056535
B16: Americas | C16: =GETPIVOTDATA("USD AMOUNT",$B$3,"Region","Americas","Ageing Tier","0-30 days") -> 201735.55 | D16: =GETPIVOTDATA("USD AMOUNT",$B$3,"Region","Americas","Ageing Tier","31-60 days") -> 21503.113 | E16: =GETPIVOTDATA("USD AMOUNT",$B$3,"Region","Americas","Ageing Tier","61-90 days") -> 168.33774 | F16: =GETPIVOTDATA("USD AMOUNT",$B$3,"Region","Americas","Ageing Tier","Over 90+ days") -> 18888.387 | G16: =SUM(C16:F16) -> 242295.38 | H16: =G16/G20 -> 0.24485291
B17: MEA | C17: =GETPIVOTDATA("USD AMOUNT",$B$3,"Region","MEA","Ageing Tier","0-30 days") -> 61256.36 | D17: =GETPIVOTDATA("USD AMOUNT",$B$3,"Region","MEA","Ageing Tier","31-60 days") -> 8122.75 | E17: =GETPIVOTDATA("USD AMOUNT",$B$3,"Region","MEA","Ageing Tier","61-90 days") -> 7766.25 | F17: =GETPIVOTDATA("USD AMOUNT",$B$3,"Region","MEA","Ageing Tier","Over 90+ days") -> 12745.24 | G17: =SUM(C17:F17) -> 89890.6 | H17: =G17/G20 -> 0.090839432
B18: APAC | C18: =GETPIVOTDATA("USD AMOUNT",$B$3,"Region","APAC","Ageing Tier","0-30 days") -> 304837.31 | D18: =GETPIVOTDATA("USD AMOUNT",$B$3,"Region","APAC","Ageing Tier","31-60 days") -> 40947.48 | E18: =GETPIVOTDATA("USD AMOUNT",$B$3,"Region","APAC","Ageing Tier","61-90 days") -> 65412.636 | F18: =GETPIVOTDATA("USD AMOUNT",$B$3,"Region","APAC","Ageing Tier","Over 90+ days") -> 51245.138 | G18: =SUM(C18:F18) -> 462442.56 | H18: =G18/G20 -> 0.46732384
B19: Shared Centre | C19: =GETPIVOTDATA("USD AMOUNT",$B$3,"Region","Shared Center","Ageing Tier","0-30 days") -> 35014.798 | D19: =GETPIVOTDATA("USD AMOUNT",$B$3,"Region","Shared Center","Ageing Tier","31-60 days") -> 23869.362 | E19: =GETPIVOTDATA("USD AMOUNT",$B$3,"Region","Shared Center","Ageing Tier","61-90 days") -> 8504.5 | F19: =GETPIVOTDATA("USD AMOUNT",$B$3,"Region","Shared Center","Ageing Tier","Over 90+ days") -> 78993.5 | G19: =SUM(C19:F19) -> 146382.16 | H19: =G19/G20 -> 0.14792728
B20: Grand Total | C20: =SUM(C15:C19) -> 638879.01 | D20: =SUM(D15:D19) -> 98538.739 | E20: =SUM(E15:E19) -> 86013.86 | F20: =SUM(F15:F19) -> 166123.23 | G20: =SUM(C20:F20) -> 989554.84 | H20: 1
B21: Ageing-wise contribution(%) | C21: =C20/G20 -> 0.64562264 | D21: =D20/G20 -> 0.099578856 | E21: =E20/G20 -> 0.086921772 | F21: =F20/G20 -> 0.16787673 | G21: 1
B23: Customer Label | C23: Account Manager | D23: BD | E23: Amount($)
B24: Al Muzaini Exchange | C24: Jerome Coelho | D24: Ashraf Omran | E24: -48
B25: Aspire FT Pte Ltd | C25: Shi Yin | D25: Gitesh Athavale | E25: -1826.2714
B26: Loadpass LTDA | C26: Eduardo Avallone | D26: Christina Hutchinson | E26: -152.91
B27: borderless llc | C27: Lia Susin | D27: NA | E27: -3310.7
B28: Grand Total | E28: -5337.8814
B33: Client Name | C33: AM/BD | D33: Amount ($)
B34: Al Muzaini Exchange | C34: Ashraf Omran | D34: -48
B35: Loadpass LTDA | C35: Eduardo Avallone | D35: -152.91
B36: Aspire FT Pte Ltd | C36: Shi Yin | D36: -1826.2714
B37: borderless llc | C37: Lia Susin | D37: -3310.7
C38: Total | D38: =SUM(D34:D37) -> -5337.8814

Sheet Governance
A3: Sum of USD AMOUNT | J3: Month
A4: Client Name | B4: Region | C4: Platform | D4: Settlement Type | E4: Client Status | F4: AR's Comments | G4: Account Manager | H4: BD | I4: Year | J4: Jan | K4: Feb | L4: Mar | M4: Apr | N4: Sep | O4: Oct | P4: Nov | Q4: Dec | R4: Jul | S4: Aug | T4: Grand Total
A5: Loadpass LTDA | B5: USA | C5: N1 | D5: Bank Transfer | E5: Active | F5: AM is chasing the client to clear all o/s invoices | G5: Lia Susin | H5: Christina Hutchinson | I5: 2025 | N5: 3487.5 | O5: 2602.25 | P5: 1786.14 | Q5: 1659.62 | R5: 3495.5 | S5: 3485 | T5: 16516.01
A6: Loadpass LTDA | B6: USA | C6: N1 | D6: Bank Transfer | E6: Active | F6: AM is chasing the client to clear all o/s invoices | G6: Lia Susin | H6: Christina Hutchinson | I6: 2026 | K6: 608.97 | T6: 608.97
A7: KOHO Financial Inc.-Verify | B7: USA | C7: N1 | D7: Bank Transfer | E7: Active | F7: No response from the client post reminder sent | G7: Tanu Arora | H7: Vinoth M | I7: 2026 | M7: 312 | T7: 312
A8: MyBeacon Services Inc. | B8: USA | C8: N1 | D8: Bank Transfer | E8: Active | F8: No response from the client post reminder sent | G8: Tanu Arora | H8: Michael Bermingham | I8: 2026 | J8: 265.36476 | K8: 1020.4297 | L8: 5219.9482 | M8: 39.566801 | T8: 6545.3094
A9: MyBeacon Services Inc.-Verify | B9: USA | C9: N1 | D9: Bank Transfer | E9: Active | F9: No response from the client post reminder sent | G9: Tanu Arora | H9: Michael Bermingham | I9: 2026 | J9: 36.32 | K9: 43.5 | L9: 7.5 | T9: 87.32
A10: KOHO Financial Inc. | B10: USA | C10: N1 | D10: Bank Transfer | E10: Active | F10: No response from the client post reminder sent | G10: Tanu Arora | H10: Vinoth M | I10: 2026 | M10: 1412.24 | T10: 1412.24
A11: BEXS BANCO DE CAMBIO S.A. | B11: USA | C11: Masspay | D11: Bank Transfer | E11: Active | F11: No response from the client post reminder sent | G11: Eduardo Avallone | H11: Christina Hutchinson | I11: 2026 | M11: 500 | T11: 500
A12: Poaster Technologies Inc. DBA Warp | B12: USA | C12: N1 | D12: Bank Transfer | E12: Active | F12: No response from the client post reminder sent | G12: Tulio Lima | H12: NA | I12: 2026 | L12: 250 | M12: 130 | T12: 380
A13: Grand Total | J13: 301.68476 | K13: 1672.8997 | L13: 5477.4482 | M13: 2393.8068 | N13: 3487.5 | O13: 2602.25 | P13: 1786.14 | Q13: 1659.62 | R13: 3495.5 | S13: 3485 | T13: 26361.849

Sheet Sheet1
A1: Region | B1: APAC/ME
A2: Account Manager | B2: Hui Ting Hoe
A4: Sum of USD AMOUNT | B4: Column Labels
A5: Row Labels | B5: 0-30 days | C5: 31-60 days | D5: 61-90 days | E5: Over 90+ days | F5: Grand Total
A6: Hong Leong Finance Limited | B6: 8074.9534 | D6: 4652.5833 | F6: 12727.537
A7: iFast Financial Pte Ltd | B7: 3452.8545 | F7: 3452.8545
A8: Transwap Private Limited | B8: 4406.6802 | C8: 3236.5106 | D8: 3389.1551 | E8: 23791.203 | F8: 34823.549
A9: Grand Total | B9: 15934.488 | C9: 3236.5106 | D9: 8041.7385 | E9: 23791.203 | F9: 51003.94

Sheet Invoices
A1: Platform | B1: Customer Label | C1: Region | D1: Account Manager | E1: BD | F1: Client Status | G1: Year | H1: Settlement Type | I1: Currency | J1: USD AMOUNT | K1: Invoice Amount | L1: Billing Period | M1: Month | N1: Days | O1: Ageing Tier | P1: Fee Type | Q1: Invoice Date | R1: Due Date | S1: Invoice Status | T1: Invoice Number | U1: Reminder Sent | V1: LOD | W1: AR's Comments | X1: AM's Comments | Y1: =TODAY() -> 46232
A2: N1 | B2: SWiM Pay Pty Ltd | C2: =VLOOKUP(B2,Validation!A:B,2,0) -> Shared Center | D2: =VLOOKUP(B2,Validation!A:D,4,0) -> Simrn | E2: =VLOOKUP(B2,Validation!A:E,5,0) -> Vinoth M | F2: Active | G2: =YEAR(L2) -> 2024 | H2: Bank Transfer | I2: USD | J2: =VLOOKUP(I2,'XE rates'!A:D,4,0)*K2 -> 5500 | K2: 5500 | L2: 45597 | M2: =TEXT(L2,"mmm") -> Nov | N2: =$Y$1-R2 -> 595 | O2: =IF(N2<=30, "0-30 days", IF(N2<=60, "31-60 days", IF(N2<=90, "61-90 days", "Over 90+ days"))) -> Over 90+ days | P2: Monthly Billing | Q2: 45597 | R2: 45637 | S2: Outstanding | T2: INV-041224105640 | U2: Yes | V2: Yes | W2: A Letter of Demand (LOD) has been issued, and the account has been suspended. BD has asked client to make partial payment of $25k, awaiting further update. | Y2: =VLOOKUP(T2,'[1]Query result'!$J:$K,2,0) -> 45637 | Z2: =VLOOKUP(T2,'[1]Query result'!$J:$W,14,0) -> 0 | AA2: =K2-Z2 -> 5500
A3: N1 | B3: SWiM Pay Pty Ltd | C3: =VLOOKUP(B3,Validation!A:B,2,0) -> Shared Center | D3: =VLOOKUP(B3,Validation!A:D,4,0) -> Simrn | E3: =VLOOKUP(B3,Validation!A:E,5,0) -> Vinoth M | F3: Active | G3: =YEAR(L3) -> 2025 | H3: Bank Transfer | I3: USD | J3: =VLOOKUP(I3,'XE rates'!A:D,4,0)*K3 -> 9930 | K3: 9930 | L3: 45658 | M3: =TEXT(L3,"mmm") -> Jan | N3: =$Y$1-R3 -> 532 | O3: =IF(N3<=30, "0-30 days", IF(N3<=60, "31-60 days", IF(N3<=90, "61-90 days", "Over 90+ days"))) -> Over 90+ days | P3: Monthly Billing | Q3: 45693 | R3: 45700 | S3: Outstanding | T3: INV-050225183406 | U3: Yes | V3: Yes | W3: A Letter of Demand (LOD) has been issued, and the account has been suspended. BD has asked client to make partial payment of $25k, awaiting further update. | Y3: =VLOOKUP(T3,'[1]Query result'!$J:$K,2,0) -> 45700 | Z3: =VLOOKUP(T3,'[1]Query result'!$J:$W,14,0) -> 0 | AA3: =K3-Z3 -> 9930
A4: N1 | B4: SWiM Pay Pty Ltd | C4: =VLOOKUP(B4,Validation!A:B,2,0) -> Shared Center | D4: =VLOOKUP(B4,Validation!A:D,4,0) -> Simrn | E4: =VLOOKUP(B4,Validation!A:E,5,0) -> Vinoth M | F4: Active | G4: =YEAR(L4) -> 2025 | H4: Bank Transfer | I4: USD | J4: =VLOOKUP(I4,'XE rates'!A:D,4,0)*K4 -> 10000 | K4: 10000 | L4: 45689 | M4: =TEXT(L4,"mmm") -> Feb | N4: =$Y$1-R4 -> 504 | O4: =IF(N4<=30, "0-30 days", IF(N4<=60, "31-60 days", IF(N4<=90, "61-90 days", "Over 90+ days"))) -> Over 90+ days | P4: Monthly Billing | Q4: 45721 | R4: 45728 | S4: Outstanding | T4: INV-050325103203 | U4: Yes | V4: Yes | W4: A Letter of Demand (LOD) has been issued, and the account has been suspended. BD has asked client to make partial payment of $25k, awaiting further update. | Y4: =VLOOKUP(T4,'[1]Query result'!$J:$K,2,0) -> 45728 | Z4: =VLOOKUP(T4,'[1]Query result'!$J:$W,14,0) -> 0 | AA4: =K4-Z4 -> 10000
A5: N1 | B5: SWiM Pay Pty Ltd | C5: =VLOOKUP(B5,Validation!A:B,2,0) -> Shared Center | D5: =VLOOKUP(B5,Validation!A:D,4,0) -> Simrn | E5: =VLOOKUP(B5,Validation!A:E,5,0) -> Vinoth M | F5: Active | G5: =YEAR(L5) -> 2025 | H5: Bank Transfer | I5: USD | J5: =VLOOKUP(I5,'XE rates'!A:D,4,0)*K5 -> 10000 | K5: 10000 | L5: 45717 | M5: =TEXT(L5,"mmm") -> Mar | N5: =$Y$1-R5 -> 476 | O5: =IF(N5<=30, "0-30 days", IF(N5<=60, "31-60 days", IF(N5<=90, "61-90 days", "Over 90+ days"))) -> Over 90+ days | P5: Monthly Billing | Q5: 45749 | R5: 45756 | S5: Outstanding | T5: INV-020425174717 | U5: Yes | V5: Yes | W5: A Letter of Demand (LOD) has been issued, and the account has been suspended. BD has asked client to make partial payment of $25k, awaiting further update. | Y5: =VLOOKUP(T5,'[1]Query result'!$J:$K,2,0) -> 45756 | Z5: =VLOOKUP(T5,'[1]Query result'!$J:$W,14,0) -> 0 | AA5: =K5-Z5 -> 10000
A6: N1 | B6: SWiM Pay Pty Ltd | C6: =VLOOKUP(B6,Validation!A:B,2,0) -> Shared Center | D6: =VLOOKUP(B6,Validation!A:D,4,0) -> Simrn | E6: =VLOOKUP(B6,Validation!A:E,5,0) -> Vinoth M | F6: Active | G6: =YEAR(L6) -> 2025 | H6: Bank Transfer | I6: USD | J6: =VLOOKUP(I6,'XE rates'!A:D,4,0)*K6 -> 10000 | K6: 10000 | L6: 45748 | M6: =TEXT(L6,"mmm") -> Apr | N6: =$Y$1-R6 -> 443 | O6: =IF(N6<=30, "0-30 days", IF(N6<=60, "31-60 days", IF(N6<=90, "61-90 days", "Over 90+ days"))) -> Over 90+ days | P6: Monthly Billing | Q6: 45782 | R6: 45789 | S6: Outstanding | T6: INV-050525114818 | U6: Yes | V6: Yes | W6: A Letter of Demand (LOD) has been issued, and the account has been suspended. BD has asked client to make partial payment of $25k, awaiting further update. | Y6: =VLOOKUP(T6,'[1]Query result'!$J:$K,2,0) -> 45789 | Z6: =VLOOKUP(T6,'[1]Query result'!$J:$W,14,0) -> 0 | AA6: =K6-Z6 -> 10000
A7: N1 | B7: SWiM Pay Pty Ltd | C7: =VLOOKUP(B7,Validation!A:B,2,0) -> Shared Center | D7: =VLOOKUP(B7,Validation!A:D,4,0) -> Simrn | E7: =VLOOKUP(B7,Validation!A:E,5,0) -> Vinoth M | F7: Active | G7: =YEAR(L7) -> 2025 | H7: Bank Transfer | I7: USD | J7: =VLOOKUP(I7,'XE rates'!A:D,4,0)*K7 -> 10000 | K7: 10000 | L7: 45778 | M7: =TEXT(L7,"mmm") -> May | N7: =$Y$1-R7 -> 413 | O7: =IF(N7<=30, "0-30 days", IF(N7<=60, "31-60 days", IF(N7<=90, "61-90 days", "Over 90+ days"))) -> Over 90+ days | P7: Monthly Billing | Q7: 45812 | R7: 45819 | S7: Outstanding | T7: INV-040625165635 | U7: Yes | V7: Yes | W7: A Letter of Demand (LOD) has been issued, and the account has been suspended. BD has asked client to make partial payment of $25k, awaiting further update. | Y7: =VLOOKUP(T7,'[1]Query result'!$J:$K,2,0) -> 45819 | Z7: =VLOOKUP(T7,'[1]Query result'!$J:$W,14,0) -> 0 | AA7: =K7-Z7 -> 10000
A8: N1 | B8: Loadpass LTDA | C8: =VLOOKUP(B8,Validation!A:B,2,0) -> Americas | D8: =VLOOKUP(B8,Validation!A:D,4,0) -> Lia Susin | E8: =VLOOKUP(B8,Validation!A:E,5,0) -> Christina Hutchinson | F8: Active | G8: =YEAR(L8) -> 2025 | H8: Bank Transfer | I8: USD | J8: =VLOOKUP(I8,'XE rates'!A:D,4,0)*K8 -> 3495.5 | K8: 3495.5 | L8: 45839 | M8: =TEXT(L8,"mmm") -> Jul | N8: =$Y$1-R8 -> 351 | O8: =IF(N8<=30, "0-30 days", IF(N8<=60, "31-60 days", IF(N8<=90, "61-90 days", "Over 90+ days"))) -> Over 90+ days | P8: Monthly Billing | Q8: 45874 | R8: 45881 | S8: Outstanding | T8: INV-050825115818 | U8: Yes | V8: No | W8: AM is currently revisiting commercials in place hence this will may take some more time to settle the invoices. | Y8: =VLOOKUP(T8,'[1]Query result'!$J:$K,2,0) -> 45881 | Z8: =VLOOKUP(T8,'[1]Query result'!$J:$W,14,0) -> 0 | AA8: =K8-Z8 -> 3495.5
A9: N1 | B9: Loadpass LTDA | C9: =VLOOKUP(B9,Validation!A:B,2,0) -> Americas | D9: =VLOOKUP(B9,Validation!A:D,4,0) -> Lia Susin | E9: =VLOOKUP(B9,Validation!A:E,5,0) -> Christina Hutchinson | F9: Active | G9: =YEAR(L9) -> 2025 | H9: Bank Transfer | I9: USD | J9: =VLOOKUP(I9,'XE rates'!A:D,4,0)*K9 -> 3485 | K9: 3485 | L9: 45870 | M9: =TEXT(L9,"mmm") -> Aug | N9: =$Y$1-R9 -> 323 | O9: =IF(N9<=30, "0-30 days", IF(N9<=60, "31-60 days", IF(N9<=90, "61-90 days", "Over 90+ days"))) -> Over 90+ days | P9: Monthly Billing | Q9: 45902 | R9: 45909 | S9: Outstanding | T9: INV-020925171323 | U9: Yes | V9: No | W9: AM is currently revisiting commercials in place hence this will may take some more time to settle the invoices. | Y9: =VLOOKUP(T9,'[1]Query result'!$J:$K,2,0) -> 45909 | Z9: =VLOOKUP(T9,'[1]Query result'!$J:$W,14,0) -> 0 | AA9: =K9-Z9 -> 3485
A10: Masspay | B10: FTB HUB S.A.C | C10: =VLOOKUP(B10,Validation!A:B,2,0) -> Shared Center | D10: =VLOOKUP(B10,Validation!A:D,4,0) -> Bhavani | E10: =VLOOKUP(B10,Validation!A:E,5,0) -> NA | F10: Active | G10: =YEAR(L10) -> 2025 | H10: Wallet Debit | I10: USD | J10: =VLOOKUP(I10,'XE rates'!A:D,4,0)*K10 -> 1020 | K10: 1020 | L10: 45901 | M10: =TEXT(L10,"mmm") -> Sep | N10: =$Y$1-R10 -> 295 | O10: =IF(N10<=30, "0-30 days", IF(N10<=60, "31-60 days", IF(N10<=90, "61-90 days", "Over 90+ days"))) -> Over 90+ days | P10: Monthly Billing | Q10: 45931 | R10: 45937 | S10: Force Settlement | T10: SG-FTBHUB-09/2025 | U10: Yes | V10: No | W10: wallet debited, insufficient funds | Y10: =VLOOKUP(T10,'[1]Query result'!$J:$K,2,0) -> 45937 | Z10: =VLOOKUP(T10,'[1]Query result'!$J:$W,14,0) -> 0 | AA10: =K10-Z10 -> 1020
A11: N1 | B11: Loadpass LTDA | C11: =VLOOKUP(B11,Validation!A:B,2,0) -> Americas | D11: =VLOOKUP(B11,Validation!A:D,4,0) -> Lia Susin | E11: =VLOOKUP(B11,Validation!A:E,5,0) -> Christina Hutchinson | F11: Active | G11: =YEAR(L11) -> 2025 | H11: Bank Transfer | I11: USD | J11: =VLOOKUP(I11,'XE rates'!A:D,4,0)*K11 -> 3487.5 | K11: 3487.5 | L11: 45901 | M11: =TEXT(L11,"mmm") -> Sep | N11: =$Y$1-R11 -> 293 | O11: =IF(N11<=30, "0-30 days", IF(N11<=60, "31-60 days", IF(N11<=90, "61-90 days", "Over 90+ days"))) -> Over 90+ days | P11: Monthly Billing | Q11: 45932 | R11: 45939 | S11: Outstanding | T11: INV-021025184847 | U11: Yes | V11: No | W11: AM is currently revisiting commercials in place hence this will may take some more time to settle the invoices. | Y11: =VLOOKUP(T11,'[1]Query result'!$J:$K,2,0) -> 45939 | Z11: =VLOOKUP(T11,'[1]Query result'!$J:$W,14,0) -> 0 | AA11: =K11-Z11 -> 3487.5
A12: Masspay | B12: FTB HUB S.A.C | C12: =VLOOKUP(B12,Validation!A:B,2,0) -> Shared Center | D12: =VLOOKUP(B12,Validation!A:D,4,0) -> Bhavani | E12: =VLOOKUP(B12,Validation!A:E,5,0) -> NA | F12: Active | G12: =YEAR(L12) -> 2025 | H12: Wallet Debit | I12: USD | J12: =VLOOKUP(I12,'XE rates'!A:D,4,0)*K12 -> 1000 | K12: 1000 | L12: 45931 | M12: =TEXT(L12,"mmm") -> Oct | N12: =$Y$1-R12 -> 264 | O12: =IF(N12<=30, "0-30 days", IF(N12<=60, "31-60 days", IF(N12<=90, "61-90 days", "Over 90+ days"))) -> Over 90+ days | P12: Monthly Billing | Q12: 45962 | R12: 45968 | S12: Force Settlement | T12: SG-FTBHUB-10/2025 | U12: Yes | V12: No | W12: wallet debited, insufficient funds | Y12: =VLOOKUP(T12,'[1]Query result'!$J:$K,2,0) -> 45968 | Z12: =VLOOKUP(T12,'[1]Query result'!$J:$W,14,0) -> 0 | AA12: =K12-Z12 -> 1000
A13: N1 | B13: Budgetly Pty Ltd | C13: =VLOOKUP(B13,Validation!A:B,2,0) -> APAC | D13: =VLOOKUP(B13,Validation!A:D,4,0) -> Hao Nguyen | E13: =VLOOKUP(B13,Validation!A:E,5,0) -> Vinoth M | F13: Active | G13: =YEAR(L13) -> 2025 | H13: Bank Transfer | I13: AUD | J13: =VLOOKUP(I13,'XE rates'!A:D,4,0)*K13 -> 962.06719 | K13: 1372.9 | L13: 45901 | M13: =TEXT(L13,"mmm") -> Sep | N13: =$Y$1-R13 -> 243 | O13: =IF(N13<=30, "0-30 days", IF(N13<=60, "31-60 days", IF(N13<=90, "61-90 days", "Over 90+ days"))) -> Over 90+ days | P13: Card Printing and Delivery | Q13: 45958 | R13: 45989 | S13: Partially Paid | T13: INV-281025170000 | U13: Yes | V13: No | W13: Client has raised concerns regarding card deactivation & not willing to pay MMC. AM will send summary to the client including all invoices & share goodwill amount. | Y13: =VLOOKUP(T13,'[1]Query result'!$J:$K,2,0) -> 45989 | Z13: =VLOOKUP(T13,'[1]Query result'!$J:$W,14,0) -> 0 | AA13: =K13-Z13 -> 1372.9
... A21: N1 | B21: Loadpass LTDA | C21: =VLOOKUP(B21,Validation!A:B,2,0) -> Americas | D21: =VLOOKUP(B21,Validation!A:D,4,0) -> Lia Susin | E21: =VLOOKUP(B21,Validation!A:E,5,0) -> Christina Hutchinson | F21: Active | G21: =YEAR(L21) -> 2025 | H21: Bank Transfer | I21: USD | J21: =VLOOKUP(I21,'XE rates'!A:D,4,0)*K21 -> 1786.14 | K21: 1786.14 | L21: 45962 | M21: =TEXT(L21,"mmm") -> Nov | N21: =$Y$1-R21 -> 232 | O21: =IF(N21<=30, "0-30 days", IF(N21<=60, "31-60 days", IF(N21<=90, "61-90 days", "Over 90+ days"))) -> Over 90+ days | P21: Monthly Billing | Q21: 45993 | R21: 46000 | S21: Outstanding | T21: INV-021225201549 | U21: Yes | V21: No | W21: AM is currently revisiting commercials in place hence this will may take some more time to settle the invoices. | Y21: =VLOOKUP(T21,'[1]Query result'!$J:$K,2,0) -> 46000 | Z21: =VLOOKUP(T21,'[1]Query result'!$J:$W,14,0) -> 0 | AA21: =K21-Z21 -> 1786.14
A22: Masspay | B22: GLOBAL ROOTS INC | C22: =VLOOKUP(B22,Validation!A:B,2,0) -> Shared Center | D22: =VLOOKUP(B22,Validation!A:D,4,0) -> Bhavani | E22: =VLOOKUP(B22,Validation!A:E,5,0) -> NA | F22: Active | G22: =YEAR(L22) -> 2025 | H22: Bank Transfer | I22: USD | J22: =VLOOKUP(I22,'XE rates'!A:D,4,0)*K22 -> 2217.6 | K22: 2217.6 | L22: 45992 | M22: =TEXT(L22,"mmm") -> Dec | N22: =$Y$1-R22 -> 193 | O22: =IF(N22<=30, "0-30 days", IF(N22<=60, "31-60 days", IF(N22<=90, "61-90 days", "Over 90+ days"))) -> Over 90+ days | P22: Monthly Billing | Q22: 46024 | R22: 46039 | S22: Overdue | T22: US-GLOBAL ROOTS INC-12/2025 | U22: Yes | V22: No | W22: AM to connect with the client regarding settlement of the 2 invoices, where actuals were billed. | Y22: =VLOOKUP(T22,'[1]Query result'!$J:$K,2,0) -> 46039
A23: N1 | B23: Budgetly Pty Ltd | C23: =VLOOKUP(B23,Validation!A:B,2,0) -> APAC | D23: =VLOOKUP(B23,Validation!A:D,4,0) -> Hao Nguyen | E23: =VLOOKUP(B23,Validation!A:E,5,0) -> Vinoth M | F23: Active | G23: =YEAR(L23) -> 2025 | H23: Bank Transfer | I23: AUD | J23: =VLOOKUP(I23,'XE rates'!A:D,4,0)*K23 -> 832.15974 | K23: 1187.518 | L23: 45992 | M23: =TEXT(L23,"mmm") -> Dec | N23: =$Y$1-R23 -> 174 | O23: =IF(N23<=30, "0-30 days", IF(N23<=60, "31-60 days", IF(N23<=90, "61-90 days", "Over 90+ days"))) -> Over 90+ days | P23: Monthly Billing | Q23: 46028 | R23: 46058 | S23: Outstanding | T23: INV-060126122618 | U23: Yes | V23: No | W23: Client has raised concerns regarding card deactivation & not willing to pay MMC. AM will send summary to the client including all invoices & share goodwill amount. | Y23: =VLOOKUP(T23,'[1]Query result'!$J:$K,2,0) -> 46058 | Z23: =VLOOKUP(T23,'[1]Query result'!$J:$W,14,0) -> 0 | AA23: =K23-Z23 -> 1187.518
A24: N1 | B24: FIRSTKYC PTE. LTD. | C24: =VLOOKUP(B24,Validation!A:B,2,0) -> APAC | D24: =VLOOKUP(B24,Validation!A:D,4,0) -> NA | E24: =VLOOKUP(B24,Validation!A:E,5,0) -> Denis Tan | F24: Active | G24: =YEAR(L24) -> 2025 | H24: Bank Transfer | I24: USD | J24: =VLOOKUP(I24,'XE rates'!A:D,4,0)*K24 -> 1.72 | K24: 1.72 | L24: 45992 | M24: =TEXT(L24,"mmm") -> Dec | N24: =$Y$1-R24 -> 198 | O24: =IF(N24<=30, "0-30 days", IF(N24<=60, "31-60 days", IF(N24<=90, "61-90 days", "Over 90+ days"))) -> Over 90+ days | P24: Monthly Billing | Q24: 46027 | R24: 46034 | S24: Outstanding | T24: INV-050126095427 | U24: Yes | V24: No | W24: Client will settle once lumpsum threshold achieved | Y24: =VLOOKUP(T24,'[1]Query result'!$J:$K,2,0) -> 46034 | Z24: =VLOOKUP(T24,'[1]Query result'!$J:$W,14,0) -> 0 | AA24: =K24-Z24 -> 1.72
A25: N1 | B25: Istanbul Ödeme ve Elektronik Para A.S | C25: =VLOOKUP(B25,Validation!A:B,2,0) -> MEA | D25: =VLOOKUP(B25,Validation!A:D,4,0) -> Jerome Coelho | E25: =VLOOKUP(B25,Validation!A:E,5,0) -> Ashraf Omran | F25: Active | G25: =YEAR(L25) -> 2025 | H25: Bank Transfer | I25: USD | J25: =VLOOKUP(I25,'XE rates'!A:D,4,0)*K25 -> 2500 | K25: 2500 | L25: 45992 | M25: =TEXT(L25,"mmm") -> Dec | N25: =$Y$1-R25 -> 198 | O25: =IF(N25<=30, "0-30 days", IF(N25<=60, "31-60 days", IF(N25<=90, "61-90 days", "Over 90+ days"))) -> Over 90+ days | P25: Monthly Billing | Q25: 46027 | R25: 46034 | S25: Force Settlement | T25: INV-050126150313 | U25: Yes | V25: No | W25: AM has asked to keep the invoices pending until funds are received. | Y25: =VLOOKUP(T25,'[1]Query result'!$J:$K,2,0) -> 46034 | Z25: =VLOOKUP(T25,'[1]Query result'!$J:$W,14,0) -> 0 | AA25: =K25-Z25 -> 2500
A26: N1 | B26: JPMORGAN CHASE BANK | C26: =VLOOKUP(B26,Validation!A:B,2,0) -> EU/UK | D26: =VLOOKUP(B26,Validation!A:D,4,0) -> Sachli Zare | E26: =VLOOKUP(B26,Validation!A:E,5,0) -> NA | F26: Active | G26: =YEAR(L26) -> 2025 | H26: Bank Transfer | I26: USD | J26: =VLOOKUP(I26,'XE rates'!A:D,4,0)*K26 -> 2.5 | K26: 2.5 | L26: 45992 | M26: =TEXT(L26,"mmm") -> Dec | N26: =$Y$1-R26 -> 198 | O26: =IF(N26<=30, "0-30 days", IF(N26<=60, "31-60 days", IF(N26<=90, "61-90 days", "Over 90+ days"))) -> Over 90+ days | P26: Monthly Billing | Q26: 46027 | R26: 46034 | S26: Outstanding | T26: INV-050126184308 | U26: Yes | V26: No | W26: Partially settled by the client | Y26: =VLOOKUP(T26,'[1]Query result'!$J:$K,2,0) -> 46034 | Z26: =VLOOKUP(T26,'[1]Query result'!$J:$W,14,0) -> 0 | AA26: =K26-Z26 -> 2.5
A27: N1 | B27: Loadpass LTDA | C27: =VLOOKUP(B27,Validation!A:B,2,0) -> Americas | D27: =VLOOKUP(B27,Validation!A:D,4,0) -> Lia Susin | E27: =VLOOKUP(B27,Validation!A:E,5,0) -> Christina Hutchinson | F27: Active | G27: =YEAR(L27) -> 2025 | H27: Bank Transfer | I27: USD | J27: =VLOOKUP(I27,'XE rates'!A:D,4,0)*K27 -> 1659.62 | K27: 1659.62 | L27: 45992 | M27: =TEXT(L27,"mmm") -> Dec | N27: =$Y$1-R27 -> 198 | O27: =IF(N27<=30, "0-30 days", IF(N27<=60, "31-60 days", IF(N27<=90, "61-90 days", "Over 90+ days"))) -> Over 90+ days | P27: Monthly Billing | Q27: 46027 | R27: 46034 | S27: Outstanding | T27: INV-050126153219 | U27: Yes | V27: No | W27: AM is currently revisiting commercials in place hence this will may take some more time to settle the invoices. | Y27: =VLOOKUP(T27,'[1]Query result'!$J:$K,2,0) -> 46034 | Z27: =VLOOKUP(T27,'[1]Query result'!$J:$W,14,0) -> 0 | AA27: =K27-Z27 -> 1659.62
A28: N1 | B28: Budgetly Pty Ltd | C28: =VLOOKUP(B28,Validation!A:B,2,0) -> APAC | D28: =VLOOKUP(B28,Validation!A:D,4,0) -> Hao Nguyen | E28: =VLOOKUP(B28,Validation!A:E,5,0) -> Vinoth M | F28: Active | G28: =YEAR(L28) -> 2025 | H28: Bank Transfer | I28: AUD | J28: =VLOOKUP(I28,'XE rates'!A:D,4,0)*K28 -> 1558.6694 | K28: 2224.27 | L28: 45992 | M28: =TEXT(L28,"mmm") -> Dec | N28: =$Y$1-R28 -> 156 | O28: =IF(N28<=30, "0-30 days", IF(N28<=60, "31-60 days", IF(N28<=90, "61-90 days", "Over 90+ days"))) -> Over 90+ days | P28: Card Printing and Delivery | Q28: 46045 | R28: 46076 | S28: Outstanding | T28: INV-230126170000 | U28: Yes | V28: No | W28: Client has raised concerns regarding card deactivation & not willing to pay MMC. AM will send summary to the client including all invoices & share goodwill amount.
A29: N1 | B29: Budgetly Pty Ltd | C29: =VLOOKUP(B29,Validation!A:B,2,0) -> APAC | D29: =VLOOKUP(B29,Validation!A:D,4,0) -> Hao Nguyen | E29: =VLOOKUP(B29,Validation!A:E,5,0) -> Vinoth M | F29: Active | G29: =YEAR(L29) -> 2026 | H29: Bank Transfer | I29: AUD | J29: =VLOOKUP(I29,'XE rates'!A:D,4,0)*K29 -> 3733.176 | K29: 5327.359 | L29: 46023 | M29: =TEXT(L29,"mmm") -> Jan | N29: =$Y$1-R29 -> 165 | O29: =IF(N29<=30, "0-30 days", IF(N29<=60, "31-60 days", IF(N29<=90, "61-90 days", "Over 90+ days"))) -> Over 90+ days | P29: Monthly Billing | Q29: 46060 | R29: 46067 | S29: Outstanding | T29: INV-070226133026 | U29: Yes | V29: No | W29: Client has raised concerns regarding card deactivation & not willing to pay MMC. AM will send summary to the client including all invoices & share goodwill amount.
A30: N1 | B30: FIRSTKYC PTE. LTD. | C30: =VLOOKUP(B30,Validation!A:B,2,0) -> APAC | D30: =VLOOKUP(B30,Validation!A:D,4,0) -> NA | E30: =VLOOKUP(B30,Validation!A:E,5,0) -> Denis Tan | F30: Active | G30: =YEAR(L30) -> 2026 | H30: Bank Transfer | I30: USD | J30: =VLOOKUP(I30,'XE rates'!A:D,4,0)*K30 -> 14.19 | K30: 14.19 | L30: 46023 | M30: =TEXT(L30,"mmm") -> Jan | N30: =$Y$1-R30 -> 166 | O30: =IF(N30<=30, "0-30 days", IF(N30<=60, "31-60 days", IF(N30<=90, "61-90 days", "Over 90+ days"))) -> Over 90+ days | P30: Monthly Billing | Q30: 46059 | R30: 46066 | S30: Outstanding | T30: INV-060226120820 | U30: Yes | V30: No | W30: Client will settle once lumpsum threshold achieved
A31: N1 | B31: Istanbul Ödeme ve Elektronik Para A.S | C31: =VLOOKUP(B31,Validation!A:B,2,0) -> MEA | D31: =VLOOKUP(B31,Validation!A:D,4,0) -> Jerome Coelho | E31: =VLOOKUP(B31,Validation!A:E,5,0) -> Ashraf Omran | F31: Active | G31: =YEAR(L31) -> 2026 | H31: Bank Transfer | I31: USD | J31: =VLOOKUP(I31,'XE rates'!A:D,4,0)*K31 -> 2500 | K31: 2500 | L31: 46023 | M31: =TEXT(L31,"mmm") -> Jan | N31: =$Y$1-R31 -> 170 | O31: =IF(N31<=30, "0-30 days", IF(N31<=60, "31-60 days", IF(N31<=90, "61-90 days", "Over 90+ days"))) -> Over 90+ days | P31: Monthly Billing | Q31: 46055 | R31: 46062 | S31: Force Settlement | T31: INV-020226182425 | U31: Yes | V31: No | W31: AM has asked to keep the invoices pending until funds are received.
A32: N1 | B32: MULTIPLIER TECHNOLOGIES PTE. LTD | C32: =VLOOKUP(B32,Validation!A:B,2,0) -> Shared Center | D32: =VLOOKUP(B32,Validation!A:D,4,0) -> Sanat Patakar | E32: =VLOOKUP(B32,Validation!A:E,5,0) -> Vinoth M | F32: Active | G32: =YEAR(L32) -> 2026 | H32: Bank Transfer | I32: USD | J32: =VLOOKUP(I32,'XE rates'!A:D,4,0)*K32 -> 2965 | K32: 2965 | L32: 46023 | M32: =TEXT(L32,"mmm") -> Jan | N32: =$Y$1-R32 -> 167 | O32: =IF(N32<=30, "0-30 days", IF(N32<=60, "31-60 days", IF(N32<=90, "61-90 days", "Over 90+ days"))) -> Over 90+ days | P32: Monthly Billing | Q32: 46058 | R32: 46065 | S32: Outstanding | T32: INV-050226133127 | U32: Yes | V32: Yes | W32: Payment has been received for two invoices; pending update on settlement of the remaining balance.
A33: N1 | B33: MyBeacon Services Inc.-Verify | C33: =VLOOKUP(B33,Validation!A:B,2,0) -> Americas | D33: =VLOOKUP(B33,Validation!A:D,4,0) -> Tanu Arora | E33: =VLOOKUP(B33,Validation!A:E,5,0) -> Michael Bermingham | F33: Active | G33: =YEAR(L33) -> 2026 | H33: Bank Transfer | I33: USD | J33: =VLOOKUP(I33,'XE rates'!A:D,4,0)*K33 -> 36.32 | K33: 36.32 | L33: 46023 | M33: =TEXT(L33,"mmm") -> Jan | N33: =$Y$1-R33 -> 168 | O33: =IF(N33<=30, "0-30 days", IF(N33<=60, "31-60 days", IF(N33<=90, "61-90 days", "Over 90+ days"))) -> Over 90+ days | P33: Monthly Billing | Q33: 46057 | R33: 46064 | S33: Outstanding | T33: INV-040226185603 | U33: Yes | V33: No | W33: Client does not want to bear the return charges, discussions are currently ongoing with the client and Mike to reach a resolution.
A34: N1 | B34: Budgetly Pty Ltd | C34: =VLOOKUP(B34,Validation!A:B,2,0) -> APAC | D34: =VLOOKUP(B34,Validation!A:D,4,0) -> Hao Nguyen | E34: =VLOOKUP(B34,Validation!A:E,5,0) -> Vinoth M | F34: Active | G34: =YEAR(L34) -> 2026 | H34: Bank Transfer | I34: AUD | J34: =VLOOKUP(I34,'XE rates'!A:D,4,0)*K34 -> 38.905944 | K34: 55.52 | L34: 46023 | M34: =TEXT(L34,"mmm") -> Jan | N34: =$Y$1-R34 -> 131 | O34: =IF(N34<=30, "0-30 days", IF(N34<=60, "31-60 days", IF(N34<=90, "61-90 days", "Over 90+ days"))) -> Over 90+ days | P34: Card Printing and Delivery | Q34: 46073 | R34: 46101 | S34: Outstanding | T34: INV-200226170000 | U34: Yes | V34: No | W34: Client has raised concerns regarding card deactivation & not willing to pay MMC. AM will send summary to the client including all invoices & share goodwill amount.
A35: N1 | B35: Budgetly Pty Ltd | C35: =VLOOKUP(B35,Validation!A:B,2,0) -> APAC | D35: =VLOOKUP(B35,Validation!A:D,4,0) -> Hao Nguyen | E35: =VLOOKUP(B35,Validation!A:E,5,0) -> Vinoth M | F35: Active | G35: =YEAR(L35) -> 2026 | H35: Bank Transfer | I35: AUD | J35: =VLOOKUP(I35,'XE rates'!A:D,4,0)*K35 -> 2696.4181 | K35: 3847.873 | L35: 46054 | M35: =TEXT(L35,"mmm") -> Feb | N35: =$Y$1-R35 -> 117 | O35: =IF(N35<=30, "0-30 days", IF(N35<=60, "31-60 days", IF(N35<=90, "61-90 days", "Over 90+ days"))) -> Over 90+ days | P35: Monthly Billing | Q35: 46085 | R35: 46115 | S35: Outstanding | T35: INV-040326125850 | U35: Yes | V35: No | W35: Client has raised concerns regarding card deactivation & not willing to pay MMC. AM will send summary to the client including all invoices & share goodwill amount.
A36: N1 | B36: FIRSTKYC PTE. LTD. | C36: =VLOOKUP(B36,Validation!A:B,2,0) -> APAC | D36: =VLOOKUP(B36,Validation!A:D,4,0) -> NA | E36: =VLOOKUP(B36,Validation!A:E,5,0) -> Denis Tan | F36: Active | G36: =YEAR(L36) -> 2026 | H36: Bank Transfer | I36: USD | J36: =VLOOKUP(I36,'XE rates'!A:D,4,0)*K36 -> 6.88 | K36: 6.88 | L36: 46054 | M36: =TEXT(L36,"mmm") -> Feb | N36: =$Y$1-R36 -> 140 | O36: =IF(N36<=30, "0-30 days", IF(N36<=60, "31-60 days", IF(N36<=90, "61-90 days", "Over 90+ days"))) -> Over 90+ days | P36: Monthly Billing | Q36: 46085 | R36: 46092 | S36: Outstanding | T36: INV-040326132912 | U36: Yes | V36: No | W36: Client will settle once lumpsum threshold achieved
A37: N1 | B37: Istanbul Ödeme ve Elektronik Para A.S | C37: =VLOOKUP(B37,Validation!A:B,2,0) -> MEA | D37: =VLOOKUP(B37,Validation!A:D,4,0) -> Jerome Coelho | E37: =VLOOKUP(B37,Validation!A:E,5,0) -> Ashraf Omran | F37: Active | G37: =YEAR(L37) -> 2026 | H37: Bank Transfer | I37: USD | J37: =VLOOKUP(I37,'XE rates'!A:D,4,0)*K37 -> 2500 | K37: 2500 | L37: 46054 | M37: =TEXT(L37,"mmm") -> Feb | N37: =$Y$1-R37 -> 142 | O37: =IF(N37<=30, "0-30 days", IF(N37<=60, "31-60 days", IF(N37<=90, "61-90 days", "Over 90+ days"))) -> Over 90+ days | P37: Monthly Billing | Q37: 46083 | R37: 46090 | S37: Force Settlement | T37: INV-020326191014 | U37: Yes | V37: No | W37: AM has asked to keep the invoices pending until funds are received.
A38: N1 | B38: JPMORGAN CHASE BANK | C38: =VLOOKUP(B38,Validation!A:B,2,0) -> EU/UK | D38: =VLOOKUP(B38,Validation!A:D,4,0) -> Sachli Zare | E38: =VLOOKUP(B38,Validation!A:E,5,0) -> NA | F38: Active | G38: =YEAR(L38) -> 2026 | H38: Bank Transfer | I38: USD | J38: =VLOOKUP(I38,'XE rates'!A:D,4,0)*K38 -> 89.8 | K38: 89.8 | L38: 46054 | M38: =TEXT(L38,"mmm") -> Feb | N38: =$Y$1-R38 -> 140 | O38: =IF(N38<=30, "0-30 days", IF(N38<=60, "31-60 days", IF(N38<=90, "61-90 days", "Over 90+ days"))) -> Over 90+ days | P38: Monthly Billing | Q38: 46085 | R38: 46092 | S38: Partially Paid | T38: INV-040326132449 | U38: Yes | V38: No | W38: Partially settled by the client
A39: N1 | B39: Loadpass LTDA | C39: =VLOOKUP(B39,Validation!A:B,2,0) -> Americas | D39: =VLOOKUP(B39,Validation!A:D,4,0) -> Lia Susin | E39: =VLOOKUP(B39,Validation!A:E,5,0) -> Christina Hutchinson | F39: Active | G39: =YEAR(L39) -> 2026 | H39: Bank Transfer | I39: USD | J39: =VLOOKUP(I39,'XE rates'!A:D,4,0)*K39 -> 608.97 | K39: 608.97 | L39: 46054 | M39: =TEXT(L39,"mmm") -> Feb | N39: =$Y$1-R39 -> 141 | O39: =IF(N39<=30, "0-30 days", IF(N39<=60, "31-60 days", IF(N39<=90, "61-90 days", "Over 90+ days"))) -> Over 90+ days | P39: Monthly Billing | Q39: 46084 | R39: 46091 | S39: Outstanding | T39: INV-030326144903 | U39: Yes | V39: No | W39: AM is currently revisiting commercials in place hence this will may take some more time to settle the invoices.
... A55: Masspay | B55: Qatar National Bank (Q.P.S.C.) | C55: =VLOOKUP(B55,Validation!A:B,2,0) -> MEA | D55: =VLOOKUP(B55,Validation!A:D,4,0) -> Jerome Coelho | E55: =VLOOKUP(B55,Validation!A:E,5,0) -> Rohit Bammi | F55: Active | G55: =YEAR(L55) -> 2026 | H55: Bank Transfer | I55: USD | J55: =VLOOKUP(I55,'XE rates'!A:D,4,0)*K55 -> 4029.75 | K55: 4029.75 | L55: 46113 | M55: =TEXT(L55,"mmm") -> Apr | N55: =$Y$1-R55 -> 79 | O55: =IF(N55<=30, "0-30 days", IF(N55<=60, "31-60 days", IF(N55<=90, "61-90 days", "Over 90+ days"))) -> 61-90 days | P55: Monthly Billing | Q55: 46146 | R55: 46153 | S55: Overdue | T55: SG-Qatar National Bank (Q.P.S.C.)-04/2026 | U55: Yes | V55: No | W55: No response from the client post reminder sent
A56: N1 | B56: Emirates Islamic Bank PJSC | C56: =VLOOKUP(B56,Validation!A:B,2,0) -> MEA | D56: =VLOOKUP(B56,Validation!A:D,4,0) -> Jerome Coelho | E56: =VLOOKUP(B56,Validation!A:E,5,0) -> Rohit Bammi | F56: Active | G56: =YEAR(L56) -> 2026 | H56: Bank Transfer | I56: USD | J56: =VLOOKUP(I56,'XE rates'!A:D,4,0)*K56 -> 3736.5 | K56: 3736.5 | L56: 46113 | M56: =TEXT(L56,"mmm") -> Apr | N56: =$Y$1-R56 -> 79 | O56: =IF(N56<=30, "0-30 days", IF(N56<=60, "31-60 days", IF(N56<=90, "61-90 days", "Over 90+ days"))) -> 61-90 days | P56: Monthly Billing | Q56: 46146 | R56: 46153 | S56: Outstanding | T56: INV-040526204049 | U56: Yes | V56: No
A57: N1 | B57: EVERWIN REMITTANCE AND EXCHANGE CO LIMITED | C57: =VLOOKUP(B57,Validation!A:B,2,0) -> APAC | D57: =VLOOKUP(B57,Validation!A:D,4,0) -> NA | E57: =VLOOKUP(B57,Validation!A:E,5,0) -> Lisa Sung | F57: Active | G57: =YEAR(L57) -> 2026 | H57: Bank Transfer | I57: USD | J57: =VLOOKUP(I57,'XE rates'!A:D,4,0)*K57 -> 46001.45 | K57: 46001.45 | L57: 46143 | M57: =TEXT(L57,"mmm") -> May | N57: =$Y$1-R57 -> 72 | O57: =IF(N57<=30, "0-30 days", IF(N57<=60, "31-60 days", IF(N57<=90, "61-90 days", "Over 90+ days"))) -> 61-90 days | P57: Monthly Billing | Q57: 46153 | R57: 46160 | S57: Partially Paid | T57: INV-110526145754 | U57: Yes | V57: No
A58: N1 | B58: Express Hub Services Pty Ltd | C58: =VLOOKUP(B58,Validation!A:B,2,0) -> APAC | D58: =VLOOKUP(B58,Validation!A:D,4,0) -> NA | E58: =VLOOKUP(B58,Validation!A:E,5,0) -> Wendy zhai | F58: Active | G58: =YEAR(L58) -> 2026 | H58: Bank Transfer | I58: AUD | J58: =VLOOKUP(I58,'XE rates'!A:D,4,0)*K58 -> 2804.7738 | K58: 4002.5 | L58: 46113 | M58: =TEXT(L58,"mmm") -> Apr | N58: =$Y$1-R58 -> 78 | O58: =IF(N58<=30, "0-30 days", IF(N58<=60, "31-60 days", IF(N58<=90, "61-90 days", "Over 90+ days"))) -> 61-90 days | P58: Monthly Billing | Q58: 46147 | R58: 46154 | S58: Partially Paid | T58: INV-050526150527 | U58: Yes | V58: No | W58: Debited their wallet balance
A59: N1 | B59: FIRSTKYC PTE. LTD. | C59: =VLOOKUP(B59,Validation!A:B,2,0) -> APAC | D59: =VLOOKUP(B59,Validation!A:D,4,0) -> NA | E59: =VLOOKUP(B59,Validation!A:E,5,0) -> Denis Tan | F59: Active | G59: =YEAR(L59) -> 2026 | H59: Bank Transfer | I59: USD | J59: =VLOOKUP(I59,'XE rates'!A:D,4,0)*K59 -> 37.84 | K59: 37.84 | L59: 46113 | M59: =TEXT(L59,"mmm") -> Apr | N59: =$Y$1-R59 -> 79 | O59: =IF(N59<=30, "0-30 days", IF(N59<=60, "31-60 days", IF(N59<=90, "61-90 days", "Over 90+ days"))) -> 61-90 days | P59: Monthly Billing | Q59: 46146 | R59: 46153 | S59: Outstanding | T59: INV-040526162158 | U59: Yes | V59: No | W59: Client will settle once lumpsum threshold achieved
A60: N1 | B60: JPMORGAN CHASE BANK | C60: =VLOOKUP(B60,Validation!A:B,2,0) -> EU/UK | D60: =VLOOKUP(B60,Validation!A:D,4,0) -> Sachli Zare | E60: =VLOOKUP(B60,Validation!A:E,5,0) -> NA | F60: Active | G60: =YEAR(L60) -> 2026 | H60: Bank Transfer | I60: USD | J60: =VLOOKUP(I60,'XE rates'!A:D,4,0)*K60 -> 99.6 | K60: 99.6 | L60: 46113 | M60: =TEXT(L60,"mmm") -> Apr | N60: =$Y$1-R60 -> 79 | O60: =IF(N60<=30, "0-30 days", IF(N60<=60, "31-60 days", IF(N60<=90, "61-90 days", "Over 90+ days"))) -> 61-90 days | P60: Monthly Billing | Q60: 46146 | R60: 46153 | S60: Outstanding | T60: INV-040526200003 | U60: Yes | V60: No | W60: Partially settled by the client
A61: N1 | B61: MULTIPLIER TECHNOLOGIES PTE. LTD | C61: =VLOOKUP(B61,Validation!A:B,2,0) -> Shared Center | D61: =VLOOKUP(B61,Validation!A:D,4,0) -> Sanat Patakar | E61: =VLOOKUP(B61,Validation!A:E,5,0) -> Vinoth M | F61: Active | G61: =YEAR(L61) -> 2026 | H61: Bank Transfer | I61: USD | J61: =VLOOKUP(I61,'XE rates'!A:D,4,0)*K61 -> 2954.5 | K61: 2954.5 | L61: 46113 | M61: =TEXT(L61,"mmm") -> Apr | N61: =$Y$1-R61 -> 79 | O61: =IF(N61<=30, "0-30 days", IF(N61<=60, "31-60 days", IF(N61<=90, "61-90 days", "Over 90+ days"))) -> 61-90 days | P61: Monthly Billing | Q61: 46146 | R61: 46153 | S61: Outstanding | T61: INV-040526195142 | U61: Yes | V61: Yes | W61: Payment has been received for two invoices; pending update on settlement of the remaining balance.
A62: N1 | B62: MyBeacon Services Inc. | C62: =VLOOKUP(B62,Validation!A:B,2,0) -> Americas | D62: =VLOOKUP(B62,Validation!A:D,4,0) -> Tanu Arora | E62: =VLOOKUP(B62,Validation!A:E,5,0) -> Michael Bermingham | F62: Active | G62: =YEAR(L62) -> 2026 | H62: Bank Transfer | I62: CAD | J62: =VLOOKUP(I62,'XE rates'!A:D,4,0)*K62 -> 38.337743 | K62: 54.05 | L62: 46113 | M62: =TEXT(L62,"mmm") -> Apr | N62: =$Y$1-R62 -> 78 | O62: =IF(N62<=30, "0-30 days", IF(N62<=60, "31-60 days", IF(N62<=90, "61-90 days", "Over 90+ days"))) -> 61-90 days | P62: Monthly Billing | Q62: 46147 | R62: 46154 | S62: Outstanding | T62: INV-050526163450 | U62: Yes | V62: No | W62: Client does not want to bear the return charges, discussions are currently ongoing with the client and Mike to reach a resolution.
A63: N1 | B63: Poaster Technologies Inc. DBA Warp | C63: =VLOOKUP(B63,Validation!A:B,2,0) -> Americas | D63: =VLOOKUP(B63,Validation!A:D,4,0) -> Tulio Lima | E63: =VLOOKUP(B63,Validation!A:E,5,0) -> NA | F63: Active | G63: =YEAR(L63) -> 2026 | H63: Bank Transfer | I63: USD | J63: =VLOOKUP(I63,'XE rates'!A:D,4,0)*K63 -> 130 | K63: 130 | L63: 46113 | M63: =TEXT(L63,"mmm") -> Apr | N63: =$Y$1-R63 -> 79 | O63: =IF(N63<=30, "0-30 days", IF(N63<=60, "31-60 days", IF(N63<=90, "61-90 days", "Over 90+ days"))) -> 61-90 days | P63: Monthly Billing | Q63: 46146 | R63: 46153 | S63: Outstanding | T63: INV-040526102628 | U63: Yes | V63: No | W63: No response from the client post reminder sent
A64: N1 | B64: Travel Ledger UK | C64: =VLOOKUP(B64,Validation!A:B,2,0) -> EU/UK | D64: =VLOOKUP(B64,Validation!A:D,4,0) -> Will Turner | E64: =VLOOKUP(B64,Validation!A:E,5,0) -> Danny May | F64: Active | G64: =YEAR(L64) -> 2026 | H64: Bank Transfer | I64: GBP | J64: =VLOOKUP(I64,'XE rates'!A:D,4,0)*K64 -> 4062.5359 | K64: 3038 | L64: 46113 | M64: =TEXT(L64,"mmm") -> Apr | N64: =$Y$1-R64 -> 71 | O64: =IF(N64<=30, "0-30 days", IF(N64<=60, "31-60 days", IF(N64<=90, "61-90 days", "Over 90+ days"))) -> 61-90 days | P64: Monthly Billing | Q64: 46147 | R64: 46161 | S64: Outstanding | T64: INV-050526184408 | U64: Yes | V64: No | W64: No response from the client post reminder sent
A65: N1 | B65: VPLUS GREATER BAY EXCHANGE LIMITED | C65: =VLOOKUP(B65,Validation!A:B,2,0) -> APAC | D65: =VLOOKUP(B65,Validation!A:D,4,0) -> NA | E65: =VLOOKUP(B65,Validation!A:E,5,0) -> Lisa Sung | F65: Active | G65: =YEAR(L65) -> 2026 | H65: Bank Transfer | I65: USD | J65: =VLOOKUP(I65,'XE rates'!A:D,4,0)*K65 -> 15125 | K65: 15125 | L65: 46113 | M65: =TEXT(L65,"mmm") -> Apr | N65: =$Y$1-R65 -> 77 | O65: =IF(N65<=30, "0-30 days", IF(N65<=60, "31-60 days", IF(N65<=90, "61-90 days", "Over 90+ days"))) -> 61-90 days | P65: Monthly Billing | Q65: 46148 | R65: 46155 | S65: Outstanding | T65: INV-060526134523 | U65: Yes | V65: No
A66: N1 | B66: Aspire FT Pte Ltd | C66: =VLOOKUP(B66,Validation!A:B,2,0) -> APAC | D66: =VLOOKUP(B66,Validation!A:D,4,0) -> Shi Yin | E66: =VLOOKUP(B66,Validation!A:E,5,0) -> Gitesh Athavale | F66: Active | G66: =YEAR(L66) -> 2026 | H66: Bank Transfer | I66: SGD | J66: =VLOOKUP(I66,'XE rates'!A:D,4,0)*K66 -> 107062.18 | K66: 138295.49 | L66: 46143 | M66: =TEXT(L66,"mmm") -> May | N66: =$Y$1-R66 -> 33 | O66: =IF(N66<=30, "0-30 days", IF(N66<=60, "31-60 days", IF(N66<=90, "61-90 days", "Over 90+ days"))) -> 31-60 days | P66: Quarterly Scheme Fees | Q66: 46169 | R66: 46199 | S66: Outstanding | T66: INV-270526152527 | U66: Yes | V66: No
A67: N1 | B67: Budgetly Pty Ltd | C67: =VLOOKUP(B67,Validation!A:B,2,0) -> APAC | D67: =VLOOKUP(B67,Validation!A:D,4,0) -> Hao Nguyen | E67: =VLOOKUP(B67,Validation!A:E,5,0) -> Vinoth M | F67: Active | G67: =YEAR(L67) -> 2026 | H67: Bank Transfer | I67: AUD | J67: =VLOOKUP(I67,'XE rates'!A:D,4,0)*K67 -> 22031.093 | K67: 31439.06 | L67: 46113 | M67: =TEXT(L67,"mmm") -> Apr | N67: =$Y$1-R67 -> 31 | O67: =IF(N67<=30, "0-30 days", IF(N67<=60, "31-60 days", IF(N67<=90, "61-90 days", "Over 90+ days"))) -> 31-60 days | P67: Monthly Billing | Q67: 46171 | R67: 46201 | S67: Outstanding | T67: INV-290526111409 | U67: Yes | V67: No | W67: Client has raised concerns regarding card deactivation & not willing to pay MMC. AM will send summary to the client including all invoices & share goodwill amount.
A68: Masspay | B68: Everpro Holdings Limited | C68: =VLOOKUP(B68,Validation!A:B,2,0) -> Shared Center | D68: =VLOOKUP(B68,Validation!A:D,4,0) -> Simrn | E68: =VLOOKUP(B68,Validation!A:E,5,0) -> Lisa Sung | F68: Active | G68: =YEAR(L68) -> 2026 | H68: Bank Transfer | I68: USD | J68: =VLOOKUP(I68,'XE rates'!A:D,4,0)*K68 -> 5000 | K68: 5000 | L68: 46143 | M68: =TEXT(L68,"mmm") -> May | N68: =$Y$1-R68 -> 50 | O68: =IF(N68<=30, "0-30 days", IF(N68<=60, "31-60 days", IF(N68<=90, "61-90 days", "Over 90+ days"))) -> 31-60 days | P68: Monthly Billing | Q68: 46175 | R68: 46182 | S68: Overdue | T68: HK-Everpro-05/2026 | U68: Yes | V68: No
A69: Masspay | B69: PT FLIPTECH LENTERA INSPIRASI PERTIWI | C69: =VLOOKUP(B69,Validation!A:B,2,0) -> APAC | D69: =VLOOKUP(B69,Validation!A:D,4,0) -> Hao Nguyen | E69: =VLOOKUP(B69,Validation!A:E,5,0) -> NA | F69: Active | G69: =YEAR(L69) -> 2026 | H69: Bank Transfer | I69: USD | J69: =VLOOKUP(I69,'XE rates'!A:D,4,0)*K69 -> 283.43 | K69: 283.43 | L69: 46143 | M69: =TEXT(L69,"mmm") -> May | N69: =$Y$1-R69 -> 42 | O69: =IF(N69<=30, "0-30 days", IF(N69<=60, "31-60 days", IF(N69<=90, "61-90 days", "Over 90+ days"))) -> 31-60 days | P69: Debit note - Incremental FX margin charges | Q69: 46175 | R69: 46190 | S69: Overdue | T69: ID-DN-PT FLIPTECH-05-2026 | U69: Yes | V69: No
A70: Masspay | B70: PT FLIPTECH LENTERA INSPIRASI PERTIWI | C70: =VLOOKUP(B70,Validation!A:B,2,0) -> APAC | D70: =VLOOKUP(B70,Validation!A:D,4,0) -> Hao Nguyen | E70: =VLOOKUP(B70,Validation!A:E,5,0) -> NA | F70: Active | G70: =YEAR(L70) -> 2026 | H70: Bank Transfer | I70: USD | J70: =VLOOKUP(I70,'XE rates'!A:D,4,0)*K70 -> 980.96 | K70: 980.96 | L70: 46143 | M70: =TEXT(L70,"mmm") -> May | N70: =$Y$1-R70 -> 42 | O70: =IF(N70<=30, "0-30 days", IF(N70<=60, "31-60 days", IF(N70<=90, "61-90 days", "Over 90+ days"))) -> 31-60 days | P70: Monthly Billing | Q70: 46175 | R70: 46190 | S70: Overdue | T70: ID-PT FLIPTECH-05/2026 | U70: Yes | V70: No
A71: Masspay | B71: PT Midtrans | C71: =VLOOKUP(B71,Validation!A:B,2,0) -> APAC | D71: =VLOOKUP(B71,Validation!A:D,4,0) -> Hao Nguyen | E71: =VLOOKUP(B71,Validation!A:E,5,0) -> Hari Budiman | F71: Active | G71: =YEAR(L71) -> 2026 | H71: Bank Transfer | I71: IDR | J71: =VLOOKUP(I71,'XE rates'!A:D,4,0)*K71 -> 238.97251 | K71: 4281428 | L71: 46143 | M71: =TEXT(L71,"mmm") -> May | N71: =$Y$1-R71 -> 27 | O71: =IF(N71<=30, "0-30 days", IF(N71<=60, "31-60 days", IF(N71<=90, "61-90 days", "Over 90+ days"))) -> 0-30 days | P71: Monthly Billing | Q71: 46175 | R71: 46205 | S71: Overdue | T71: ID-PT Midtrans-05/2026 | U71: Yes | V71: No
A72: Masspay | B72: Qatar National Bank (Q.P.S.C.) | C72: =VLOOKUP(B72,Validation!A:B,2,0) -> MEA | D72: =VLOOKUP(B72,Validation!A:D,4,0) -> Jerome Coelho | E72: =VLOOKUP(B72,Validation!A:E,5,0) -> Rohit Bammi | F72: Active | G72: =YEAR(L72) -> 2026 | H72: Bank Transfer | I72: USD | J72: =VLOOKUP(I72,'XE rates'!A:D,4,0)*K72 -> 4441.75 | K72: 4441.75 | L72: 46143 | M72: =TEXT(L72,"mmm") -> May | N72: =$Y$1-R72 -> 49 | O72: =IF(N72<=30, "0-30 days", IF(N72<=60, "31-60 days", IF(N72<=90, "61-90 days", "Over 90+ days"))) -> 31-60 days | P72: Monthly Billing | Q72: 46176 | R72: 46183 | S72: Overdue | T72: SG-Qatar National Bank (Q.P.S.C.)-05/2026 | U72: Yes | V72: No
A73: Masspay | B73: Stratos Payments, Inc | C73: =VLOOKUP(B73,Validation!A:B,2,0) -> Shared Center | D73: =VLOOKUP(B73,Validation!A:D,4,0) -> Mrinal | E73: =VLOOKUP(B73,Validation!A:E,5,0) -> Michael Bermingham | F73: Active | G73: =YEAR(L73) -> 2026 | H73: Wallet Debit | I73: USD | J73: =VLOOKUP(I73,'XE rates'!A:D,4,0)*K73 -> 4000 | K73: 4000 | L73: 46143 | M73: =TEXT(L73,"mmm") -> May | N73: =$Y$1-R73 -> 51 | O73: =IF(N73<=30, "0-30 days", IF(N73<=60, "31-60 days", IF(N73<=90, "61-90 days", "Over 90+ days"))) -> 31-60 days | P73: Monthly Billing | Q73: 46175 | R73: 46181 | S73: Force Settlement | T73: US-Stratos Payments, Inc-05/2026 | U73: Yes | V73: No
A74: N1 | B74: AtoB Canada Ltd. | C74: =VLOOKUP(B74,Validation!A:B,2,0) -> Americas | D74: =VLOOKUP(B74,Validation!A:D,4,0) -> Tanu Arora | E74: =VLOOKUP(B74,Validation!A:E,5,0) -> Michael Bermingham | F74: Active | G74: =YEAR(L74) -> 2026 | H74: Bank Transfer | I74: USD | J74: =VLOOKUP(I74,'XE rates'!A:D,4,0)*K74 -> 10004.1 | K74: 10004.1 | L74: 46143 | M74: =TEXT(L74,"mmm") -> May | N74: =$Y$1-R74 -> 46 | O74: =IF(N74<=30, "0-30 days", IF(N74<=60, "31-60 days", IF(N74<=90, "61-90 days", "Over 90+ days"))) -> 31-60 days | P74: Monthly Billing | Q74: 46179 | R74: 46186 | S74: Outstanding | T74: INV-060626213209 | U74: Yes | V74: No
A75: N1 | B75: Bivo Cash Inc | C75: =VLOOKUP(B75,Validation!A:B,2,0) -> Americas | D75: =VLOOKUP(B75,Validation!A:D,4,0) -> Unmanaged | E75: =VLOOKUP(B75,Validation!A:E,5,0) -> Michael Bermingham | F75: Active | G75: =YEAR(L75) -> 2026 | H75: Bank Transfer | I75: USD | J75: =VLOOKUP(I75,'XE rates'!A:D,4,0)*K75 -> 1000 | K75: 1000 | L75: 46174 | M75: =TEXT(L75,"mmm") -> Jun | N75: =$Y$1-R75 -> 44 | O75: =IF(N75<=30, "0-30 days", IF(N75<=60, "31-60 days", IF(N75<=90, "61-90 days", "Over 90+ days"))) -> 31-60 days | P75: Integration Fee | Q75: 46181 | R75: 46188 | S75: Force Settlement | T75: INV-080626181247 | U75: Yes | V75: No
A76: N1 | B76: Budgetly Pty Ltd | C76: =VLOOKUP(B76,Validation!A:B,2,0) -> APAC | D76: =VLOOKUP(B76,Validation!A:D,4,0) -> Hao Nguyen | E76: =VLOOKUP(B76,Validation!A:E,5,0) -> Vinoth M | F76: Active | G76: =YEAR(L76) -> 2026 | H76: Bank Transfer | I76: AUD | J76: =VLOOKUP(I76,'XE rates'!A:D,4,0)*K76 -> 7722.7486 | K76: 11020.604 | L76: 46143 | M76: =TEXT(L76,"mmm") -> May | N76: =$Y$1-R76 -> 26 | O76: =IF(N76<=30, "0-30 days", IF(N76<=60, "31-60 days", IF(N76<=90, "61-90 days", "Over 90+ days"))) -> 0-30 days | P76: Monthly Billing | Q76: 46176 | R76: 46206 | S76: Outstanding | T76: INV-030626161636 | U76: Yes | V76: No | W76: Client has raised concerns regarding card deactivation & not willing to pay MMC. AM will send summary to the client including all invoices & share goodwill amount.
A77: N1 | B77: CashD Pty Ltd | C77: =VLOOKUP(B77,Validation!A:B,2,0) -> Shared Center | D77: =VLOOKUP(B77,Validation!A:D,4,0) -> Bhavani | E77: =VLOOKUP(B77,Validation!A:E,5,0) -> Vinoth M | F77: Active | G77: =YEAR(L77) -> 2026 | H77: Bank Transfer | I77: AUD | J77: =VLOOKUP(I77,'XE rates'!A:D,4,0)*K77 -> 2203.876 | K77: 3145 | L77: 46143 | M77: =TEXT(L77,"mmm") -> May | N77: =$Y$1-R77 -> 50 | O77: =IF(N77<=30, "0-30 days", IF(N77<=60, "31-60 days", IF(N77<=90, "61-90 days", "Over 90+ days"))) -> 31-60 days | P77: Monthly Billing | Q77: 46175 | R77: 46182 | S77: Outstanding | T77: INV-020626161624 | U77: Yes | V77: No
A78: N1 | B78: Emirates Islamic Bank PJSC | C78: =VLOOKUP(B78,Validation!A:B,2,0) -> MEA | D78: =VLOOKUP(B78,Validation!A:D,4,0) -> Jerome Coelho | E78: =VLOOKUP(B78,Validation!A:E,5,0) -> Rohit Bammi | F78: Active | G78: =YEAR(L78) -> 2026 | H78: Bank Transfer | I78: USD | J78: =VLOOKUP(I78,'XE rates'!A:D,4,0)*K78 -> 3681 | K78: 3681 | L78: 46143 | M78: =TEXT(L78,"mmm") -> May | N78: =$Y$1-R78 -> 49 | O78: =IF(N78<=30, "0-30 days", IF(N78<=60, "31-60 days", IF(N78<=90, "61-90 days", "Over 90+ days"))) -> 31-60 days | P78: Monthly Billing | Q78: 46176 | R78: 46183 | S78: Outstanding | T78: INV-030626161519 | U78: Yes | V78: No
A79: N1 | B79: Express Hub Services Pty Ltd | C79: =VLOOKUP(B79,Validation!A:B,2,0) -> APAC | D79: =VLOOKUP(B79,Validation!A:D,4,0) -> NA | E79: =VLOOKUP(B79,Validation!A:E,5,0) -> Wendy zhai | F79: Active | G79: =YEAR(L79) -> 2026 | H79: Bank Transfer | I79: AUD | J79: =VLOOKUP(I79,'XE rates'!A:D,4,0)*K79 -> 3364.1378 | K79: 4800.73 | L79: 46143 | M79: =TEXT(L79,"mmm") -> May | N79: =$Y$1-R79 -> 50 | O79: =IF(N79<=30, "0-30 days", IF(N79<=60, "31-60 days", IF(N79<=90, "61-90 days", "Over 90+ days"))) -> 31-60 days | P79: Monthly Billing | Q79: 46175 | R79: 46182 | S79: Force Settlement | T79: INV-020626125728 | U79: Yes | V79: No | W79: Debited their wallet balance
A80: N1 | B80: Futurepay Global Limited | C80: =VLOOKUP(B80,Validation!A:B,2,0) -> Shared Center | D80: =VLOOKUP(B80,Validation!A:D,4,0) -> Sanat Patakar | E80: =VLOOKUP(B80,Validation!A:E,5,0) -> Edward Li | F80: Active | G80: =YEAR(L80) -> 2026 | H80: Bank Transfer | I80: USD | J80: =VLOOKUP(I80,'XE rates'!A:D,4,0)*K80 -> 1356.08 | K80: 1356.08 | L80: 46143 | M80: =TEXT(L80,"mmm") -> May | N80: =$Y$1-R80 -> 51 | O80: =IF(N80<=30, "0-30 days", IF(N80<=60, "31-60 days", IF(N80<=90, "61-90 days", "Over 90+ days"))) -> 31-60 days | P80: Monthly Billing | Q80: 46174 | R80: 46181 | S80: Outstanding | T80: INV-010626194231 | U80: Yes | V80: No
A81: N1 | B81: Genieum Services Pty Ltd | C81: =VLOOKUP(B81,Validation!A:B,2,0) -> Shared Center | D81: =VLOOKUP(B81,Validation!A:D,4,0) -> Sakshi Shanbhag | E81: =VLOOKUP(B81,Validation!A:E,5,0) -> Vinoth M | F81: Active | G81: =YEAR(L81) -> 2026 | H81: Bank Transfer | I81: AUD | J81: =VLOOKUP(I81,'XE rates'!A:D,4,0)*K81 -> 4878.3513 | K81: 6961.56 | L81: 46143 | M81: =TEXT(L81,"mmm") -> May | N81: =$Y$1-R81 -> 50 | O81: =IF(N81<=30, "0-30 days", IF(N81<=60, "31-60 days", IF(N81<=90, "61-90 days", "Over 90+ days"))) -> 31-60 days | P81: Monthly Billing | Q81: 46175 | R81: 46182 | S81: Outstanding | T81: INV-020626150926 | U81: Yes | V81: No
A82: N1 | B82: JPMORGAN CHASE BANK | C82: =VLOOKUP(B82,Validation!A:B,2,0) -> EU/UK | D82: =VLOOKUP(B82,Validation!A:D,4,0) -> Sachli Zare | E82: =VLOOKUP(B82,Validation!A:E,5,0) -> NA | F82: Active | G82: =YEAR(L82) -> 2026 | H82: Bank Transfer | I82: USD | J82: =VLOOKUP(I82,'XE rates'!A:D,4,0)*K82 -> 33.9 | K82: 33.9 | L82: 46143 | M82: =TEXT(L82,"mmm") -> May | N82: =$Y$1-R82 -> 48 | O82: =IF(N82<=30, "0-30 days", IF(N82<=60, "31-60 days", IF(N82<=90, "61-90 days", "Over 90+ days"))) -> 31-60 days | P82: Monthly Billing | Q82: 46177 | R82: 46184 | S82: Outstanding | T82: INV-040626125713 | U82: Yes | V82: No
A83: N1 | B83: Loadpass LTDA | C83: =VLOOKUP(B83,Validation!A:B,2,0) -> Americas | D83: =VLOOKUP(B83,Validation!A:D,4,0) -> Lia Susin | E83: =VLOOKUP(B83,Validation!A:E,5,0) -> Christina Hutchinson | F83: Active | G83: =YEAR(L83) -> 2026 | H83: Bank Transfer | I83: USD | J83: =VLOOKUP(I83,'XE rates'!A:D,4,0)*K83 -> 7821.2098 | K83: 7821.2098 | L83: 46143 | M83: =TEXT(L83,"mmm") -> May | N83: =$Y$1-R83 -> 49 | O83: =IF(N83<=30, "0-30 days", IF(N83<=60, "31-60 days", IF(N83<=90, "61-90 days", "Over 90+ days"))) -> 31-60 days | P83: Monthly Billing | Q83: 46176 | R83: 46183 | S83: Outstanding | T83: INV-030626112352 | U83: Yes | V83: No | W83: AM is currently revisiting commercials in place hence this will may take some more time to settle the invoices.
A84: N1 | B84: MULTIPLIER TECHNOLOGIES PTE. LTD | C84: =VLOOKUP(B84,Validation!A:B,2,0) -> Shared Center | D84: =VLOOKUP(B84,Validation!A:D,4,0) -> Sanat Patakar | E84: =VLOOKUP(B84,Validation!A:E,5,0) -> Vinoth M | F84: Active | G84: =YEAR(L84) -> 2026 | H84: Bank Transfer | I84: USD | J84: =VLOOKUP(I84,'XE rates'!A:D,4,0)*K84 -> 2956.5 | K84: 2956.5 | L84: 46143 | M84: =TEXT(L84,"mmm") -> May | N84: =$Y$1-R84 -> 42 | O84: =IF(N84<=30, "0-30 days", IF(N84<=60, "31-60 days", IF(N84<=90, "61-90 days", "Over 90+ days"))) -> 31-60 days | P84: Monthly Billing | Q84: 46175 | R84: 46190 | S84: Outstanding | T84: INV-020626175858 | U84: Yes | V84: No | W84: Payment has been received for two invoices; pending update on settlement of the remaining balance.
A85: N1 | B85: MyBeacon Services Inc. | C85: =VLOOKUP(B85,Validation!A:B,2,0) -> Americas | D85: =VLOOKUP(B85,Validation!A:D,4,0) -> Tanu Arora | E85: =VLOOKUP(B85,Validation!A:E,5,0) -> Michael Bermingham | F85: Active | G85: =YEAR(L85) -> 2026 | H85: Bank Transfer | I85: CAD | J85: =VLOOKUP(I85,'XE rates'!A:D,4,0)*K85 -> 2125.2627 | K85: 2996.2757 | L85: 46143 | M85: =TEXT(L85,"mmm") -> May | N85: =$Y$1-R85 -> 48 | O85: =IF(N85<=30, "0-30 days", IF(N85<=60, "31-60 days", IF(N85<=90, "61-90 days", "Over 90+ days"))) -> 31-60 days | P85: Monthly Billing | Q85: 46177 | R85: 46184 | S85: Outstanding | T85: INV-040626193129 | U85: Yes | V85: No | W85: Client does not want to bear the return charges, discussions are currently ongoing with the client and Mike to reach a resolution.
A86: N1 | B86: MyBeacon Services Inc.-Verify | C86: =VLOOKUP(B86,Validation!A:B,2,0) -> Americas | D86: =VLOOKUP(B86,Validation!A:D,4,0) -> Tanu Arora | E86: =VLOOKUP(B86,Validation!A:E,5,0) -> Michael Bermingham | F86: Active | G86: =YEAR(L86) -> 2026 | H86: Bank Transfer | I86: USD | J86: =VLOOKUP(I86,'XE rates'!A:D,4,0)*K86 -> 342.54048 | K86: 342.54048 | L86: 46143 | M86: =TEXT(L86,"mmm") -> May | N86: =$Y$1-R86 -> 50 | O86: =IF(N86<=30, "0-30 days", IF(N86<=60, "31-60 days", IF(N86<=90, "61-90 days", "Over 90+ days"))) -> 31-60 days | P86: Monthly Billing | Q86: 46175 | R86: 46182 | S86: Outstanding | T86: INV-020626113157 | U86: Yes | V86: No | W86: Client does not want to bear the return charges, discussions are currently ongoing with the client and Mike to reach a resolution.
A87: N1 | B87: Poaster Technologies Inc. DBA Warp | C87: =VLOOKUP(B87,Validation!A:B,2,0) -> Americas | D87: =VLOOKUP(B87,Validation!A:D,4,0) -> Tulio Lima | E87: =VLOOKUP(B87,Validation!A:E,5,0) -> NA | F87: Active | G87: =YEAR(L87) -> 2026 | H87: Bank Transfer | I87: USD | J87: =VLOOKUP(I87,'XE rates'!A:D,4,0)*K87 -> 210 | K87: 210 | L87: 46143 | M87: =TEXT(L87,"mmm") -> May | N87: =$Y$1-R87 -> 51 | O87: =IF(N87<=30, "0-30 days", IF(N87<=60, "31-60 days", IF(N87<=90, "61-90 days", "Over 90+ days"))) -> 31-60 days | P87: Monthly Billing | Q87: 46174 | R87: 46181 | S87: Outstanding | T87: INV-010626164441 | U87: Yes | V87: No | W87: No response from the client post reminder sent
A88: N1 | B88: Relay Financial (US), Corp-SG | C88: =VLOOKUP(B88,Validation!A:B,2,0) -> Americas | D88: =VLOOKUP(B88,Validation!A:D,4,0) -> Tulio Lima | E88: =VLOOKUP(B88,Validation!A:E,5,0) -> Michael Bermingham | F88: Active | G88: =YEAR(L88) -> 2026 | H88: Bank Transfer | I88: USD | J88: =VLOOKUP(I88,'XE rates'!A:D,4,0)*K88 -> 2500 | K88: 2500 | L88: 46174 | M88: =TEXT(L88,"mmm") -> Jun | N88: =$Y$1-R88 -> 34 | O88: =IF(N88<=30, "0-30 days", IF(N88<=60, "31-60 days", IF(N88<=90, "61-90 days", "Over 90+ days"))) -> 31-60 days | P88: Pay In Service Integration Fee | Q88: 46191 | R88: 46198 | S88: Outstanding | T88: INV-180626165925 | U88: Yes | V88: No | W88: No response from the client post reminder sent
A89: N1 | B89: SHUN TUNG CENTURY LIMITED | C89: =VLOOKUP(B89,Validation!A:B,2,0) -> APAC | D89: =VLOOKUP(B89,Validation!A:D,4,0) -> NA | E89: =VLOOKUP(B89,Validation!A:E,5,0) -> Edward Li | F89: Active | G89: =YEAR(L89) -> 2026 | H89: Bank Transfer | I89: USD | J89: =VLOOKUP(I89,'XE rates'!A:D,4,0)*K89 -> 304.5 | K89: 304.5 | L89: 46143 | M89: =TEXT(L89,"mmm") -> May | N89: =$Y$1-R89 -> 47 | O89: =IF(N89<=30, "0-30 days", IF(N89<=60, "31-60 days", IF(N89<=90, "61-90 days", "Over 90+ days"))) -> 31-60 days | P89: Monthly Billing | Q89: 46178 | R89: 46185 | S89: Outstanding | T89: INV-050626121629 | U89: Yes | V89: No | W89: No response from the client post reminder sent
A90: N1 | B90: Travel Ledger UK | C90: =VLOOKUP(B90,Validation!A:B,2,0) -> EU/UK | D90: =VLOOKUP(B90,Validation!A:D,4,0) -> Will Turner | E90: =VLOOKUP(B90,Validation!A:E,5,0) -> Danny May | F90: Active | G90: =YEAR(L90) -> 2026 | H90: Bank Transfer | I90: GBP | J90: =VLOOKUP(I90,'XE rates'!A:D,4,0)*K90 -> 4062.1347 | K90: 3037.7 | L90: 46143 | M90: =TEXT(L90,"mmm") -> May | N90: =$Y$1-R90 -> 43 | O90: =IF(N90<=30, "0-30 days", IF(N90<=60, "31-60 days", IF(N90<=90, "61-90 days", "Over 90+ days"))) -> 31-60 days | P90: Monthly Billing | Q90: 46175 | R90: 46189 | S90: Outstanding | T90: INV-020626190918 | U90: Yes | V90: No | W90: No response from the client post reminder sent
A91: N1 | B91: Tremendous, LLC | C91: =VLOOKUP(B91,Validation!A:B,2,0) -> Shared Center | D91: =VLOOKUP(B91,Validation!A:D,4,0) -> Sakshi Shanbhag | E91: =VLOOKUP(B91,Validation!A:E,5,0) -> Michael Bermingham | F91: Active | G91: =YEAR(L91) -> 2026 | H91: Bank Transfer | I91: USD | J91: =VLOOKUP(I91,'XE rates'!A:D,4,0)*K91 -> 1505.67 | K91: 1505.67 | L91: 46143 | M91: =TEXT(L91,"mmm") -> May | N91: =$Y$1-R91 -> 50 | O91: =IF(N91<=30, "0-30 days", IF(N91<=60, "31-60 days", IF(N91<=90, "61-90 days", "Over 90+ days"))) -> 31-60 days | P91: Monthly Billing | Q91: 46175 | R91: 46182 | S91: Outstanding | T91: INV-020626151734 | U91: Yes | V91: No | W91: No response from the client post reminder sent
A92: N1 | B92: Volopay Co Pte Ltd. | C92: =VLOOKUP(B92,Validation!A:B,2,0) -> APAC | D92: =VLOOKUP(B92,Validation!A:D,4,0) -> XiaoXiao | E92: =VLOOKUP(B92,Validation!A:E,5,0) -> Gitesh Athavale | F92: Active | G92: =YEAR(L92) -> 2026 | H92: Bank Transfer | I92: USD | J92: =VLOOKUP(I92,'XE rates'!A:D,4,0)*K92 -> 7924.3281 | K92: 7924.3281 | L92: 46174 | M92: =TEXT(L92,"mmm") -> Jun | N92: =$Y$1-R92 -> 41 | O92: =IF(N92<=30, "0-30 days", IF(N92<=60, "31-60 days", IF(N92<=90, "61-90 days", "Over 90+ days"))) -> 31-60 days | P92: Visa Scheme fee Revision | Q92: 46177 | R92: 46191 | S92: Outstanding | T92: INV-040626193255 | U92: Yes | V92: No | W92: No response from the client post reminder sent
A93: N1 | B93: Volopay Co Pte Ltd. | C93: =VLOOKUP(B93,Validation!A:B,2,0) -> APAC | D93: =VLOOKUP(B93,Validation!A:D,4,0) -> XiaoXiao | E93: =VLOOKUP(B93,Validation!A:E,5,0) -> Gitesh Athavale | F93: Active | G93: =YEAR(L93) -> 2026 | H93: Bank Transfer | I93: USD | J93: =VLOOKUP(I93,'XE rates'!A:D,4,0)*K93 -> 26670.124 | K93: 26670.124 | L93: 46174 | M93: =TEXT(L93,"mmm") -> Jun | N93: =$Y$1-R93 -> 41 | O93: =IF(N93<=30, "0-30 days", IF(N93<=60, "31-60 days", IF(N93<=90, "61-90 days", "Over 90+ days"))) -> 31-60 days | P93: Visa Scheme fee Revision | Q93: 46184 | R93: 46191 | S93: Outstanding | T93: INV-110626174025 | U93: Yes | V93: No | W93: No response from the client post reminder sent
A94: N1 | B94: Yorbis Inc. | C94: =VLOOKUP(B94,Validation!A:B,2,0) -> Shared Center | D94: =VLOOKUP(B94,Validation!A:D,4,0) -> Sakshi Shanbhag | E94: =VLOOKUP(B94,Validation!A:E,5,0) -> Andrew Gyenis | F94: Active | G94: =YEAR(L94) -> 2026 | H94: Bank Transfer | I94: USD | J94: =VLOOKUP(I94,'XE rates'!A:D,4,0)*K94 -> 2500.31 | K94: 2500.31 | L94: 46143 | M94: =TEXT(L94,"mmm") -> May | N94: =$Y$1-R94 -> 29 | O94: =IF(N94<=30, "0-30 days", IF(N94<=60, "31-60 days", IF(N94<=90, "61-90 days", "Over 90+ days"))) -> 0-30 days | P94: Monthly Billing | Q94: 46174 | R94: 46203 | S94: Outstanding | T94: INV-010626172437 | U94: Yes | V94: No | W94: No response from the client post reminder sent
... A148: N1 | B148: WORLDFIRST (SINGAPORE) MERCHANT SERVICES PTE. LTD. | C148: =VLOOKUP(B148,Validation!A:B,2,0) -> APAC | D148: =VLOOKUP(B148,Validation!A:D,4,0) -> NA | E148: =VLOOKUP(B148,Validation!A:E,5,0) -> Lisa Sung | F148: Active | G148: =YEAR(L148) -> 2026 | H148: Bank Transfer | I148: USD | J148: =VLOOKUP(I148,'XE rates'!A:D,4,0)*K148 -> 25667.656 | K148: 25667.656 | L148: 46174 | M148: =TEXT(L148,"mmm") -> Jun | N148: =$Y$1-R148 -> -4 | O148: =IF(N148<=30, "0-30 days", IF(N148<=60, "31-60 days", IF(N148<=90, "61-90 days", "Over 90+ days"))) -> 0-30 days | P148: Monthly Billing | Q148: 46206 | R148: 46236 | S148: Invoice Sent | T148: INV-030726124744 | U148: Yes | V148: No | W148: No response from the client post reminder sent
A149: N1 | B149: Ailingual Limited | C149: =VLOOKUP(B149,Validation!A:B,2,0) -> APAC | D149: Pat Sarisa | F149: Active | G149: =YEAR(L149) -> 2026 | H149: Bank Transfer | I149: USD | J149: =VLOOKUP(I149,'XE rates'!A:D,4,0)*K149 -> 58336.26 | K149: 58336.26 | L149: 46204 | M149: =TEXT(L149,"mmm") -> Jul | N149: =$Y$1-R149 -> -6 | O149: =IF(N149<=30, "0-30 days", IF(N149<=60, "31-60 days", IF(N149<=90, "61-90 days", "Over 90+ days"))) -> 0-30 days | P149: Visa Scheme fee Revision | Q149: 46231 | R149: 46238 | S149: Invoice Sent | T149: INV-280726113916 | U149: Yes | V149: No | W149: No response from the client post reminder sent
A150: N1 | B150: Aspire FT Pte Ltd | C150: =VLOOKUP(B150,Validation!A:B,2,0) -> APAC | D150: Shi Yin | F150: Active | G150: =YEAR(L150) -> 2026 | H150: Bank Transfer | I150: SGD | J150: =VLOOKUP(I150,'XE rates'!A:D,4,0)*K150 -> 427462.25 | K150: 552166.09 | L150: 46204 | M150: =TEXT(L150,"mmm") -> Jul | N150: =$Y$1-R150 -> 1 | O150: =IF(N150<=30, "0-30 days", IF(N150<=60, "31-60 days", IF(N150<=90, "61-90 days", "Over 90+ days"))) -> 0-30 days | P150: Visa Scheme fee Revision | Q150: 46224 | R150: 46231 | S150: Outstanding | T150: INV-210726164750 | U150: Yes | V150: No | W150: No response from the client post reminder sent
A151: N1 | B151: Budgetly Pty Ltd | C151: =VLOOKUP(B151,Validation!A:B,2,0) -> APAC | D151: Hao Nguyen | F151: Active | G151: =YEAR(L151) -> 2026 | H151: Bank Transfer | I151: AUD | J151: =VLOOKUP(I151,'XE rates'!A:D,4,0)*K151 -> 175702.71 | K151: 250733.27 | L151: 46204 | M151: =TEXT(L151,"mmm") -> Jul | N151: =$Y$1-R151 -> -6 | O151: =IF(N151<=30, "0-30 days", IF(N151<=60, "31-60 days", IF(N151<=90, "61-90 days", "Over 90+ days"))) -> 0-30 days | P151: Visa Scheme fee Revision | Q151: 46231 | R151: 46238 | S151: Invoice Sent | T151: INV-280726145400 | U151: Yes | V151: No | W151: No response from the client post reminder sent
A152: N1 | B152: iFast Financial Pte Ltd | C152: =VLOOKUP(B152,Validation!A:B,2,0) -> Shared Center | D152: Sanat Patakar | F152: Active | G152: =YEAR(L152) -> 2026 | H152: Bank Transfer | I152: SGD | J152: =VLOOKUP(I152,'XE rates'!A:D,4,0)*K152 -> 27238.806 | K152: 35185.2 | L152: 46204 | M152: =TEXT(L152,"mmm") -> Jul | N152: =$Y$1-R152 -> -6 | O152: =IF(N152<=30, "0-30 days", IF(N152<=60, "31-60 days", IF(N152<=90, "61-90 days", "Over 90+ days"))) -> 0-30 days | P152: BIN setup fee | Q152: 46231 | R152: 46238 | S152: Invoice Sent | T152: INV-270726185840 | U152: Yes | V152: No | W152: No response from the client post reminder sent
A153: N1 | B153: Unit Finance Inc. | C153: Americas | D153: NA | E153: Michael Birmingham | F153: Active | G153: =YEAR(L153) -> 2026 | H153: Bank Transfer | I153: USD | J153: =VLOOKUP(I153,'XE rates'!A:D,4,0)*K153 -> 1500 | K153: 1500 | L153: 46204 | M153: =TEXT(L153,"mmm") -> Jul | N153: =$Y$1-R153 -> -5 | O153: =IF(N153<=30, "0-30 days", IF(N153<=60, "31-60 days", IF(N153<=90, "61-90 days", "Over 90+ days"))) -> 0-30 days | P153: Pay In & Pay Out Service Integration Fee | Q153: 46230 | R153: 46237 | S153: Invoice Sent | T153: INV-270726175934 | U153: Yes | V153: No | W153: No response from the client post reminder sent
A154: N1 | B154: VOLOPAY.CO PTE. LTD. | C154: =VLOOKUP(B154,Validation!A:B,2,0) -> APAC | D154: XiaoXiao | F154: Active | G154: =YEAR(L154) -> 2026 | H154: Bank Transfer | I154: USD | J154: =VLOOKUP(I154,'XE rates'!A:D,4,0)*K154 -> -106493 | K154: -106493 | L154: 46204 | M154: =TEXT(L154,"mmm") -> Jul | N154: =$Y$1-R154 -> -1 | O154: =IF(N154<=30, "0-30 days", IF(N154<=60, "31-60 days", IF(N154<=90, "61-90 days", "Over 90+ days"))) -> 0-30 days | P154: GST Adjustment | Q154: 46226 | R154: 46233 | S154: Partially Paid | T154: CN-INV-230726161141 | U154: Yes | V154: No | W154: No response from the client post reminder sent
A155: N1 | B155: Weel New Zealand Limited | C155: =VLOOKUP(B155,Validation!A:B,2,0) -> APAC | D155: Hao Nguyen | F155: Active | G155: =YEAR(L155) -> 2026 | H155: Bank Transfer | I155: NZD | J155: =VLOOKUP(I155,'XE rates'!A:D,4,0)*K155 -> -647.30028 | K155: -1110.06 | L155: 46204 | M155: =TEXT(L155,"mmm") -> Jul | N155: =$Y$1-R155 -> 1 | O155: =IF(N155<=30, "0-30 days", IF(N155<=60, "31-60 days", IF(N155<=90, "61-90 days", "Over 90+ days"))) -> 0-30 days | P155: Credit Note-Rebate | Q155: 46224 | R155: 46231 | S155: Outstanding | T155: CN-INV-210726131820 | U155: Yes | V155: No | W155: No response from the client post reminder sent

Sheet Rebates
A1: Platform | B1: Customer Label | C1: Region | D1: Account Manager | E1: BD | F1: Client Status | G1: Year | H1: Settlement Type | I1: Currency | J1: USD AMOUNT | K1: Invoice Amount | L1: Billing Period | M1: Month | N1: Days | O1: Ageing Tier | P1: Fee Type | Q1: Invoice Date | R1: Due Date | S1: Invoice Status | T1: Invoice Number | U1: Reminder Sent | V1: LOD | W1: AR's Comments | X1: AM's Comments
A2: N1 | B2: Al Muzaini Exchange | C2: ME | D2: Jerome Coelho | E2: Ashraf Omran | F2: Active | G2: 2025 | H2: Account Settlement | I2: USD | J2: -48 | K2: -48 | L2: 45870 | M2: Aug | N2: 293 | O2: Over 90+ days | P2: Credit Note-Waive off | Q2: 45903 | R2: 45910 | S2: Partially Paid | T2: CN-INV-030925182457 | Y2: Partially Paid
A3: N1 | B3: Aspire FT Pte Ltd | C3: APAC | D3: Shi Yin | E3: Gitesh Athavale | F3: Active | G3: 2026 | H3: Account Settlement | I3: SGD | J3: -25787.318 | K3: -32883.286 | L3: 46143 | M3: May | N3: -4 | O3: 0-30 days | P3: Monthly Billing | Q3: 46177 | R3: 46207 | S3: Invoice Sent | T3: INV-040626125945 | Y3: Invoice Sent
A4: N1 | B4: Loadpass LTDA | C4: USA | D4: Lia Susin | E4: Christina Hutchinson | F4: Active | G4: 2026 | H4: Account Settlement | I4: USD | J4: -152.91 | K4: -152.91 | L4: 46023 | M4: Jan | N4: 140 | O4: Over 90+ days | P4: Monthly Billing | Q4: 46056 | R4: 46063 | S4: Outstanding | T4: INV-030226233006 | Y4: Outstanding
A5: N1 | B5: Mizzen Digital DMCC | C5: ME | D5: Jerome Coelho | E5: Rohit Bammi | F5: Active | G5: 2026 | H5: Account Settlement | I5: USD | J5: -2954.5 | K5: -2954.5 | L5: 46143 | M5: May | N5: 19 | O5: 0-30 days | P5: Credit Note-Waived Off | Q5: 46177 | R5: 46184 | S5: Outstanding | T5: CN-INV-030626132939 | Y5: Outstanding
A6: N1 | B6: Mizzen Digital DMCC | C6: ME | D6: Jerome Coelho | E6: Rohit Bammi | F6: Active | G6: 2026 | H6: Account Settlement | I6: USD | J6: -232.06 | K6: -232.06 | L6: 46143 | M6: May | N6: 19 | O6: 0-30 days | P6: Monthly Billing | Q6: 46177 | R6: 46184 | S6: Outstanding | T6: INV-030626145124 | Y6: Outstanding
A7: N1 | B7: Monex Canada Inc | C7: USA | D7: Tulio Lima | E7: Michael Bermingham | F7: Active | G7: 2026 | H7: Account Settlement | I7: USD | J7: -2132.65 | K7: -2132.65 | L7: 46174 | M7: Jun | N7: 6 | O7: 0-30 days | P7: Credit Note-Write-Off | Q7: 46190 | R7: 46197 | S7: Invoice Sent | T7: CN-INV-170626175259 | Y7: Outstanding
A8: N1 | B8: VOLOPAY.CO PTE. LTD. | C8: APAC | D8: XiaoXiao | E8: Gitesh Athavale | F8: Active | G8: 2026 | H8: Account Settlement | I8: USD | J8: -3325.1822 | K8: -3325.1822 | L8: 46143 | M8: May | N8: 19 | O8: 0-30 days | P8: Monthly Billing | Q8: 46177 | R8: 46184 | S8: Outstanding | T8: INV-040626092813 | Y8: Outstanding
J9: =SUM(J2:J8) -> -34632.62

Sheet XE rates
A1: Currency | B1: Name | C1: Units per USD | D1: USD per unit
A2: USD | B2: US Dollar | C2: 1 | D2: 1
A3: EUR | B3: Euro | C3: 0.8766387 | D3: 1.1407208
A4: GBP | B4: British Pound | C4: 0.74780878 | D4: 1.3372402
A5: INR | B5: Indian Rupee | C5: 96.290192 | D5: 0.010385274
A6: AUD | B6: Australian Dollar | C6: 1.4270313 | D6: 0.70075547
A7: CAD | B7: Canadian Dollar | C7: 1.4098378 | D7: 0.70930144
A8: SGD | B8: Singapore Dollar | C8: 1.2917306 | D8: 0.77415521
A9: CHF | B9: Swiss Franc | C9: 0.81230058 | D9: 1.2310714
A10: MYR | B10: Malaysian Ringgit | C10: 4.0888767 | D10: 0.24456594
A11: JPY | B11: Japanese Yen | C11: 163.02258 | D11: 0.0061341197
A12: CNY | B12: Chinese Yuan Renminbi | C12: 6.7707654 | D12: 0.14769379
A13: NZD | B13: New Zealand Dollar | C13: 1.7149073 | D13: 0.58312189
... A194: ZWG | B194: Zimbabwean Dollar | C194: 25.324496 | D194: 0.039487459

Sheet Validation
A1: Customer Label | B1: Region | C1: Region2 | D1: Account Manager | E1: BD
A2: Stylopay Pte. Ltd | B2: APAC | C2: APAC | D2: XiaoXiao | E2: NA
A3: PayQuicker LLC | B3: Americas | C3: Americas | D3: Terminated | E3: Kyle Reny
A4: Varni Tech Inc | B4: APAC | C4: APAC | D4: Terminated | E4: Gitesh Athavale
A5: aerapass pte. ltd | B5: APAC | C5: APAC | D5: Terminated | E5: Gitesh Athavale
A6: Knox Payments Ltd. | B6: Americas | C6: Americas | D6: Tanu Arora | E6: NA
A7: TClub Inc. | B7: Americas | C7: Americas | D7: Terminated | E7: NA
A8: Transwap Private Limited | B8: Shared Center | C8: Shared Center | D8: Mrinal | E8: Gitesh Athavale
A9: Widoph Remit | B9: Shared Center | C9: Shared Center | D9: NA | E9: Vinoth M
A10: MeshPay UK | B10: EU/UK | C10: UK | D10: Will Turner | E10: Gitesh Athavale
A11: MeshPay UK Ltd | B11: EU/UK | C11: UK | D11: Will Turner | E11: Gitesh Athavale
A12: SPROUT CORPORATE SERVICES PTE LTD | B12: APAC | C12: APAC | D12: Terminated | E12: Gitesh Athavale
... A14: Coda Payments | B14: Shared Center | C14: Shared Center | D14: Sanat Patakar | E14: NA
A15: Al Dhahery Money Exchange | B15: MEA | C15: =B15 -> MEA | D15: Jerome Coelho | E15: Rohit Bammi
A16: coda payments malaysia - aplikasi | B16: SME | C16: SME | D16: Leon Lim | E16: NA
A17: Cash In Asia Pte Ltd | B17: APAC | C17: APAC | D17: Terminated | E17: Gitesh Athavale
A18: Hedgewiz Pure Risk Management Solutions Ltd | B18: EU/UK | C18: EU | D18: Terminated | E18: NA
A19: Hedgewiz Pure Risk Management Solutions Ltd - EU | B19: EU/UK | C19: EU | D19: Terminated | E19: NA
A20: Hedgewiz Pure Risk Management Solutions Ltd -UK | B20: EU/UK | C20: EU | D20: Terminated | E20: NA
A21: Hedgewiz Pure Risk Management Solutions Ltd -US | B21: EU/UK | C21: EU | D21: Terminated | E21: NA
A22: MeshPay EU B.V. | B22: EU/UK | C22: EU | D22: Will Turner | E22: Gitesh Athavale
A23: Pay Set Limited | B23: EU/UK | C23: EU | D23: Terminated | E23: NA
A24: Photon Dance (HongKong) Limited | B24: APAC | C24: APAC | D24: Terminated | E24: Gitesh Athavale
A25: UTU Rewards S.R.L. | B25: APAC | C25: APAC | D25: Terminated | E25: Gitesh Athavale
A26: Yondr Money Pty Ltd | B26: APAC | C26: APAC | D26: Hao Nguyen | E26: NA
A27: Skrill Ltd | B27: EU/UK | C27: EU | D27: Will Turner | E27: NA
A28: Paysafe Financial Services Limited | B28: EU/UK | C28: EU | D28: Will Turner | E28: NA
A29: SAAD EXCHANGE | B29: MEA | C29: =B29 -> MEA | D29: Jerome Coelho | E29: Rohit Bammi
A30: Qolo Inc. | B30: Shared Center | C30: Shared Centre | D30: Sakshi Shanbhag | E30: Kyle Reny
A31: Azimo Limited. | B31: EU/UK | C31: UK | D31: Sachli Zare | E31: Gitesh Athavale
A32: Bud Infrastructure Limited | B32: Shared Center | C32: Shared Centre | D32: Terminated | E32: Michael Bermingham
A33: GET GLOBAL HOLDINGS PTE LTD | B33: APAC | C33: APAC | D33: Terminated | E33: Gitesh Athavale
A34: OWLPAY HOLDINGS PTE. LTD. | B34: Shared Center | C34: Shared Center | D34: Bhavani | E34: Gitesh Athavale
A35: Pelican General Limited | B35: APAC | C35: APAC | D35: Terminated | E35: Lisa Sung
A36: VOLOPAY.CO PTE. LTD. | B36: APAC | C36: APAC | D36: XiaoXiao | E36: Gitesh Athavale
A37: A.D. Financial (AUS) Pty Ltd | B37: Shared Center | C37: Shared center | D37: Sanat Patakar | E37: Vinoth M
A38: AFT HK Limited | B38: APAC | C38: APAC | D38: Shi Yin | E38: Gitesh Athavale
A39: Aspire FT Pte Ltd | B39: APAC | C39: APAC | D39: Shi Yin | E39: Gitesh Athavale
A40: Budgetly Pty Ltd | B40: APAC | C40: APAC | D40: Hao Nguyen | E40: Vinoth M
A41: CAMBIONET CORRETORA DE CAMBIO LTDA | B41: Americas | C41: Americas | D41: Terminated | E41: Lia Susin
A42: CQUR Bank LLC | B42: MEA | C42: =B42 -> MEA | D42: Jerome Coelho | E42: Ashraf Omran
A43: DEEL Inc. | B43: Americas | C43: Americas | D43: Lia Susin | E43: Gitesh Athavale
A44: Digital Services SG Five Pte Ltd | B44: APAC | C44: APAC | D44: XiaoXiao | E44: Gitesh Athavale
A45: East Africa Bank SA | B45: MEA | C45: =B45 -> MEA | D45: Jerome Coelho | E45: Winfred
A46: Franklin Technologies ApS | B46: EU/UK | C46: EU | D46: Will Turner | E46: Gagan Smara
A47: GET GLOBAL HOLDINGS PTE LTD | B47: APAC | C47: APAC | D47: Pat Sarisa | E47: Gitesh Athavale
A48: Global E-Payment Limited | B48: APAC | C48: APAC | D48: Pat Sarisa | E48: Gitesh Athavale
A49: Hong Leong Finance Limited | B49: APAC | C49: APAC | D49: Terminated | E49: Gitesh Athavale
A50: IAPPS Pte. Ltd. | B50: APAC | C50: APAC | D50: Shi Yin | E50: Gitesh Athavale
A51: iFast Financial Pte Ltd | B51: Shared Center | C51: Shared Center | D51: Sanat Patakar | E51: Gitesh Athavale
A52: KUWAIT INDIA INTERNATIONAL EXCHANGE COMPANY(W.L.L) | B52: MEA | C52: =B52 -> MEA | D52: Jerome Coelho | E52: Ashraf Omran
A53: LENDERWIZE LTD-UK | B53: EU/UK | C53: UK | D53: Terminated | E53: Danny May
A54: LianLian International Company Limited | B54: APAC | C54: APAC | D54: Pat Sarisa | E54: Gitesh Athavale
A55: Maritime Payment Solutions, LLC (ShipMoney) | B55: Americas | C55: Americas | D55: Tanu Arora | E55: Michael Bermingham
A56: MESHPAY AU PTY LTD | B56: EU/UK | C56: EU | D56: Will Turner | E56: Gitesh Athavale
A57: MeshPay EU B.V. | B57: EU/UK | C57: EU | D57: Will Turner | E57: Gitesh Athavale
A58: MESHPAY GBL PTE. LTD. | B58: EU/UK | C58: EU | D58: Will Turner | E58: Gitesh Athavale
A59: MESHPAY UK LTD | B59: EU/UK | C59: UK | D59: Will Turner | E59: Gitesh Athavale
A60: MP Payments UK Limited | B60: APAC | C60: APAC | D60: Terminated | E60: Rohit Bammi
A61: OWLPAY HOLDINGS PTE. LTD | B61: Shared Center | C61: Shared Center | D61: Bhavani | E61: Gitesh Athavale
A62: OWLPAY HOLDINGS PTE. LTD. | B62: Shared Center | C62: Shared Center | D62: Bhavani | E62: Gitesh Athavale
A63: Paysure Solutions Ltd | B63: EU/UK | C63: UK | D63: Will Turner | E63: Andrew Mere
A64: Pelican General Limited | B64: APAC | C64: APAC | D64: Terminated | E64: Lisa Sung
... A67: Remote Europe Holding B.V. | B67: Americas | C67: Americas | D67: Lia Susin | E67: Danny May
A68: SENDER ÖDEME HIZMETLERI ANONIM SIRKETI | B68: MEA | C68: =B68 -> MEA | D68: Jerome Coelho | E68: Ashraf Omran
A69: SingCash Pte Ltd | B69: APAC | C69: APAC | D69: Shi Yin | E69: Gitesh Athavale
A70: Sleek Tech Pte. Ltd. | B70: APAC | C70: APAC | D70: Pat Sarisa | E70: Gitesh Athavale
A71: SPROUT CORPORATE SERVICES PTE LTD | B71: APAC | C71: APAC | D71: Terminated | E71: Gitesh Athavale
A72: SWiM Pay Pty Ltd | B72: Shared Center | C72: Shared Center | D72: Simrn | E72: Vinoth M
A73: The New Money Company of San Francisco, Inc | B73: Shared Center | C73: Shared Center | D73: Mrinal | E73: MIchael Podrid
A74: Travel Ledger UK | B74: EU/UK | C74: UK | D74: Will Turner | E74: Danny May
A75: UQPAY PTE LTD | B75: Shared Center | C75: Shared Center | D75: Bhavani | E75: Gitesh Athavale
A76: WEEL HOLDINGS PTY LTD | B76: APAC | C76: APAC | D76: Hao Nguyen | E76: NA
A77: Yondr Money Pty Ltd | B77: APAC | C77: APAC | D77: Hao Nguyen | E77: NA
A78: Yorbis Inc. | B78: Shared Center | C78: Shared Centre | D78: Sakshi Shanbhag | E78: Andrew Gyenis
A79: EBURY PARTNERS UK LIMITED | B79: EU/UK | C79: UK | D79: Will Turner | E79: NA
A80: teledolar | B80: Americas | C80: Americas | D80: Terminated | E80: Michael Bermingham
... A93: Remofirst, Inc. | B93: EU/UK | C93: EU | D93: Will Turner | E93: Kyle Reny
A94: SAAD EXCHANGE | B94: MEA | C94: =B94 -> MEA | D94: Jerome Coelho | E94: Rohit Bammi
A95: Al Dhahery Money Exchange | B95: MEA | C95: =B95 -> MEA | D95: Jerome Coelho | E95: Rohit Bammi
A96: Corporate Alliance Payments Pty Ltd - NSP | B96: Shared Center | C96: Shared Center | D96: Simrn | E96: Vinoth M
A97: OZ CORRETORA DE CÂMBIO SA | B97: Americas | C97: Americas | D97: Terminated | E97: Christina Hutchinson
A98: AYP Staffing Pte Ltd | B98: APAC | C98: APAC | D98: Shi Yin | E98: Gitesh Athavale
A99: Payana Ltd. | B99: Americas | C99: Americas | D99: Terminated | E99: Kyle Reny
A100: Widoph Remit | B100: Shared Center | C100: Shared Center | D100: NA | E100: Vinoth M
A101: Rippling Payments Inc FI US | B101: Americas | C101: Americas | D101: Tanu Arora | E101: Oren Cohen
A102: TAURUS ONE PRIVATE LIMITED | B102: APAC | C102: APAC | D102: Terminated | E102: Gitesh Athavale
A103: Rippling Payments Inc FI SG | B103: Americas | C103: Americas | D103: Tanu Arora | E103: Oren Cohen
A104: Nuvei Limited | B104: APAC | C104: APAC | D104: XiaoXiao | E104: Rohit Bammi
A105: Butlr Ltd T/A Ryftpay | B105: EU/UK | C105: EU | D105: Terminated | E105: NA
A106: BEXS BANCO DE CAMBIO S.A. | B106: Americas | C106: Americas | D106: Lia Susin | E106: Christina Hutchinson
A107: Klasha Technologies Limited | B107: MEA | C107: =B107 -> MEA | D107: Jerome Coelho | E107: Rohit Bammi
A108: alchemy agps solutions ltd | B108: APAC | C108: APAC | D108: Terminated | E108: NA
A109: PT FLIPTECH LENTERA INSPIRASI PERTIWI | B109: APAC | C109: APAC | D109: Hao Nguyen | E109: NA
A110: BRQ LINK Payment Services Inc | B110: MEA | C110: =B110 -> MEA | D110: Jerome Coelho | E110: Rohit Bammi
A111: 4400 WE Technologies, Inc. | B111: Shared Center | C111: Shared Center | D111: Mrinal | E111: NA
A112: Supra Negocios SAS | B112: Shared Center | C112: Shared Center | D112: Sakshi Shanbhag | E112: NA
A113: Travel Easy Innovation GmbH | B113: APAC | C113: APAC | D113: NA | E113: Lisa Sung
A114: REMIT5 | B114: Shared Center | C114: Shared Center | D114: Sakshi Shanbhag | E114: Michael Bermingham
A115: BAAS Corporation | B115: Americas | C115: Americas | D115: Tanu Arora | E115: Michael Bermingham
...

Sheet RevOPs mapping
A1: Clients | B1: region | C1: Product | D1: AM | I1: Sr. No | J1: Client Name | K1: AM Name
A2: RIPPLING PAYMENTS INC | B2: AMERICAS | C2: Payouts | D2: Tanu Arora | I2: 1 | J2: ATLANTIC PARTNERS ASIA | K2: Sanat
A3: CURRENCY CLOUD | B3: APAC | C3: Payouts | D3: XiaoXiao | I3: 2 | J3: WAN GUO GROUP | K3: Sanat
A4: GLOBAL81 | B4: AMERICAS | C4: Payouts | D4: tulio lima | I4: 3 | J4: ORBIT MONEY | K4: Sakshi
A5: GUSTO US | B5: AMERICAS | C5: Payouts | D5: Tanu Arora | I5: 4 | J5: AD FINANCIAL | K5: Sanat
A6: WORLDPAY AP LTD | B6: EUROPE-Non Travel | C6: Payouts | D6: Sachli Zare | I6: 5 | J6: NIURAL | K6: Mrinal
A7: MASTERCARD TRANSACTION SERVICES (EUROPE) SA | B7: EUROPE-Non Travel | C7: Payouts | D7: Sachli Zare | I7: 6 | J7: TAZAPAY | K7: Sanat
A8: YOU TECHNOLOGIES GROUP (SINGAPORE) PTE. LTD | B8: APAC | C8: Payouts | D8: XiaoXiao | I8: 7 | J8: SBI REMIT | K8: Sanat
A9: OFX | B9: APAC | C9: Payouts | D9: Hao Nguyen | I9: 8 | J9: MULTIPLIER TECHNOLOGIES PTE LTD | K9: Sanat
A10: EBURY | B10: EUROPE-Non Travel | C10: Payouts | D10: Will Turner | I10: 9 | J10: HIRE BORDERLESS US | K10: Mrinal
A11: MASHREQ | B11: MEA | C11: Payouts | D11: Saikat Roy | I11: 10 | J11: GOLANCE | K11: Sakshi
A12: AL MULLA INTERNATIONAL EXCHANGE COMPANY,K.S.C.C. | B12: MEA | C12: Payouts | D12: Jerome Coelho | I12: 11 | J12: BENDIX EXCHANGE | K12: Mrinal
A13: KASIKORN BANK | B13: APAC | C13: Payouts | D13: Pat Sarisa | I13: 12 | J13: UQPAY PTE LTD PAYOUT | K13: Bhavani
... A99: EIB | B99: MEA | C99: Payouts | D99: Jerome Coelho | I99: 98 | J99: JUST WALLET INC | K99: Mrinal
A100: EPAY LIMITED | B100: APAC | C100: Payouts | D100: Pat Sarisa
A101: EVERPRO HOLDINGS LIMITED | B101: APAC | C101: Payouts | D101: Shared center
A102: EVOCABANK CJSC | B102: MEA | C102: Payouts | D102: Jerome Coelho
A103: EZ MONEY | B103: APAC | C103: Payouts | D103: Shared center
A104: FIFTH AMERICAN CORPORATION O/A REMIT5 | B104: AMERICAS | C104: Payouts | D104: Shared center
A105: TCLUB INC. | B105: AMERICAS | C105: Payouts | D105: Terminated
A106: UNSI US | B106: AMERICAS | C106: Payouts | D106: Unmanaged
A107: Aardua | B107: Americas | C107: Payouts | D107: Terminated
A108: PACIFIC BASIN SHIPPING (HK) LIMITED | B108: APAC | C108: Payouts | D108: Irene
A109: FUTUREPAY GLOBAL | B109: APAC | C109: Payouts | D109: Shared center
A110: GENIEUM | B110: APAC | C110: Payouts | D110: Shared center
A111: GET KOLLO INC. | B111: AMERICAS | C111: Payouts | D111: Lia Susin
... A234: JP Morgan | B234: EUROPE-Non Travel | C234: Verify | D234: Sachli Zare
