Workbook
Name Slicer_Account_Manager: #N/A
Name Slicer_Region: #N/A

Sheet Summary
B2: RECEIVABLE SUMMARY(In $)
B3: Sum of USD AMOUNT | C3: Column Labels
B4: Row Labels | C4: 0-30 days | D4: 31-60 days | E4: 61-90 days | F4: Over 90+ days | G4: Grand Total
B5: EU/UK | C5: -83810.971 | D5: 1355.448 | E5: 195.88066 | F5: 261.09528 | G5: -81998.547
B6: USA | C6: -20153.441 | D6: 3210.4103 | E6: 4528.72 | F6: 18506.89 | G6: 6092.579
B7: ME | C7: 44723 | D7: 2500 | E7: 2500 | F7: 9.49 | G7: 49732.49
B8: APAC | C8: 158652.4 | D8: -27282.831 | E8: 8582.483 | F8: 105756.51 | G8: 245708.57
B9: Shared Centre | C9: 12704.171 | D9: 19035.871 | E9: -96 | F9: -150 | G9: 31494.042
B10: Grand Total | C10: 112115.16 | D10: -1181.1019 | E10: 15711.084 | F10: 124383.99 | G10: 251029.13
B13: Regional Outstanding (In $)
B14: Region | C14: 0-30 days | D14: 31-60 days | E14: 61-90 days | F14: Over 90+ days | G14: Grand Total | H14: Region-wise contribution(%)
B15: EU/UK | C15: =GETPIVOTDATA("USD AMOUNT",$B$3,"Region","EU/UK","Ageing Tier","0-30 days") -> -83810.971 | D15: =GETPIVOTDATA("USD AMOUNT",$B$3,"Region","EU/UK","Ageing Tier","31-60 days") -> 1355.448 | E15: =GETPIVOTDATA("USD AMOUNT",$B$3,"Region","EU/UK","Ageing Tier","61-90 days") -> 195.88066 | F15: =GETPIVOTDATA("USD AMOUNT",$B$3,"Region","EU/UK","Ageing Tier","Over 90+ days") -> 261.09528 | G15: =SUM(C15:F15) -> -81998.547 | H15: =G15/G19 -> -0.37350998
B16: USA | C16: =GETPIVOTDATA("USD AMOUNT",$B$3,"Region","USA","Ageing Tier","0-30 days") -> -20153.441 | D16: =GETPIVOTDATA("USD AMOUNT",$B$3,"Region","USA","Ageing Tier","31-60 days") -> 3210.4103 | E16: =GETPIVOTDATA("USD AMOUNT",$B$3,"Region","USA","Ageing Tier","61-90 days") -> 4528.72 | F16: =GETPIVOTDATA("USD AMOUNT",$B$3,"Region","USA","Ageing Tier","Over 90+ days") -> 18506.89 | G16: =SUM(C16:F16) -> 6092.579 | H16: =G16/G19 -> 0.027752187
B17: ME | C17: =GETPIVOTDATA("USD AMOUNT",$B$3,"Region","ME","Ageing Tier","0-30 days") -> 44723 | D17: =GETPIVOTDATA("USD AMOUNT",$B$3,"Region","ME","Ageing Tier","31-60 days") -> 2500 | E17: =GETPIVOTDATA("USD AMOUNT",$B$3,"Region","ME","Ageing Tier","61-90 days") -> 2500 | F17: =GETPIVOTDATA("USD AMOUNT",$B$3,"Region","ME","Ageing Tier","Over 90+ days") -> 9.49 | G17: =SUM(C17:F17) -> 49732.49 | H17: =G17/G19 -> 0.22653549
B18: APAC | C18: =GETPIVOTDATA("USD AMOUNT",$B$3,"Region","APAC","Ageing Tier","0-30 days") -> 158652.4 | D18: =GETPIVOTDATA("USD AMOUNT",$B$3,"Region","APAC","Ageing Tier","31-60 days") -> -27282.831 | E18: =GETPIVOTDATA("USD AMOUNT",$B$3,"Region","APAC","Ageing Tier","61-90 days") -> 8582.483 | F18: =GETPIVOTDATA("USD AMOUNT",$B$3,"Region","APAC","Ageing Tier","Over 90+ days") -> 105756.51 | G18: =GETPIVOTDATA("USD AMOUNT",$B$3,"Region","APAC") -> 245708.57 | H18: =G18/G19 -> 1.1192223
B19: Grand Total | C19: =SUM(C15:C18) -> 99410.992 | D19: =SUM(D15:D18) -> -20216.973 | E19: =SUM(E15:E18) -> 15807.084 | F19: =SUM(F15:F18) -> 124533.99 | G19: =SUM(G15:G18) -> 219535.09 | H19: 1
B20: Ageing-wise contribution(%) | C20: =C19/G19 -> 0.45282507 | D20: =D19/G19 -> -0.092089938 | E20: =E19/G19 -> 0.072002538 | F20: =F19/G19 -> 0.56726233 | G20: 1
B22: Customer Label | C22: Account Manager | D22: BD | E22: Amount($)
B23: Al Muzaini Exchange | C23: Jerome Coelho | D23: Ashraf Omran | E23: -68
B24: SBI Remit Co., Ltd. | C24: Jerome Coelho | D24: Rohit Bammi | E24: -298
B25: VOLOPAY.CO PTE. LTD. | C25: XiaoXiao | D25: Gitesh Athavale | E25: -7908.3063
B26: Aspire FT Pte Ltd | C26: Shi Yin | D26: Gitesh Athavale | E26: -85143.008
B27: Loadpass LTDA | C27: Eduardo Avallone | D27: Christina Hutchinson | E27: -152.91
B28: borderless llc | C28: Lia Susin | D28: NA | E28: -105.02
B29: Grand Total | E29: -93675.244
B32: Client Name | C32: AM/BD | D32: Amount ($)
B33: Al Muzaini Exchange | C33: Ashraf Omran | D33: -68
B34: SBI Remit Co., Ltd. | C34: Rohit Bammi | D34: -298
B35: VOLOPAY.CO PTE. LTD. | C35: Gitesh Athavale | D35: -7908.3063
B36: Aspire FT Pte Ltd | C36: Shi Yin | D36: -85143.008
C37: Total | D37: =SUM(D33:D36) -> -93417.314

Sheet Governance
A3: Sum of USD AMOUNT | J3: Month
A4: Client Name | B4: Region | C4: Platform | D4: Settlement Type | E4: Client Status | F4: AR's Comments | G4: Account Manager | H4: BD | I4: Year | J4: Jan | K4: Feb | L4: Mar | M4: Apr | N4: Sep | O4: Oct | P4: Nov | Q4: Dec | R4: May | S4: Jul | T4: Aug | U4: Grand Total
A5: Aspire FT Pte Ltd | B5: APAC | C5: N1 | D5: Bank Transfer | E5: Active | F5: (blank) | G5: Shi Yin | H5: Gitesh Athavale | I5: 2026 | J5: -85143.008 | K5: -18657.244 | U5: -103800.25
A6: PT Midtrans | B6: APAC | C6: Masspay | D6: Bank Transfer | E6: Active | F6: No response from the client post reminder sent | G6: Hao Nguyen | H6: Hari Budiman | I6: 2026 | J6: 356.96163 | K6: 329.55542 | U6: 686.51705
A7: SWiM Pay Pty Ltd | B7: APAC | C7: N1 | D7: Bank Transfer | E7: Active | F7: client has made progress with their capital raise however not provided exact settlement date to clear all o/s | G7: NA | H7: Vinoth M | I7: 2024 | P7: 5500 | U7: 5500
A8: SWiM Pay Pty Ltd | B8: APAC | C8: N1 | D8: Bank Transfer | E8: Active | F8: client has made progress with their capital raise however not provided exact settlement date to clear all o/s | G8: NA | H8: Vinoth M | I8: 2025 | J8: 9930 | K8: 10000 | L8: 10000 | M8: 10000 | R8: 10000 | U8: 49930
A9: Yondr Money Pty Ltd | B9: APAC | C9: N1 | D9: Bank Transfer | E9: Active | F9: AM to provide an update if invoices needs to be written off as client is suspended | G9: Hao Nguyen | H9: NA | I9: 2025 | N9: 4495.6248 | O9: 4473.4152 | P9: 4586.6383 | Q9: 4550.0559 | S9: 1319.9063 | T9: 4600.2593 | U9: 24025.9
A10: Yondr Money Pty Ltd | B10: APAC | C10: N1 | D10: Bank Transfer | E10: Active | F10: AM to provide an update if invoices needs to be written off as client is suspended | G10: Hao Nguyen | H10: NA | I10: 2026 | J10: 4749.1389 | U10: 4749.1389
A11: CashD Pty Ltd | B11: APAC | C11: N1 | D11: Bank Transfer | E11: Active | F11: No response from the client post reminder sent | G11: NA | H11: Vinoth M | I11: 2026 | J11: 2105.4768 | K11: 2105.4768 | U11: 4210.9536
A12: Pelikin Ventures Pty Ltd | B12: APAC | C12: N1 | D12: Bank Transfer | E12: Active | F12: No response from the client post reminder sent | G12: Hao Nguyen | H12: Vinoth M | I12: 2025 | Q12: 137.82337 | U12: 137.82337
A13: Pelikin Ventures Pty Ltd | B13: APAC | C13: N1 | D13: Bank Transfer | E13: Active | F13: No response from the client post reminder sent | G13: Hao Nguyen | H13: Vinoth M | I13: 2026 | J13: 3439.8135 | U13: 3439.8135
A14: Global E-Payment Limited-SG | B14: APAC | C14: N1 | D14: Bank Transfer | E14: Active | F14: (blank) | G14: Pat Sarisa | H14: NA | I14: 2026 | K14: 10000 | U14: 10000
A15: Budgetly Pty Ltd | B15: APAC | C15: N1 | D15: Bank Transfer | E15: Active | F15: Card printing invoice pending | G15: Hao Nguyen | H15: Vinoth M | I15: 2025 | N15: 919.11259 | O15: 1730.6283 | P15: 1729.4969 | Q15: 2284.0828 | U15: 6663.3206
A16: Budgetly Pty Ltd | B16: APAC | C16: N1 | D16: Bank Transfer | E16: Active | F16: Card printing invoice pending | G16: Hao Nguyen | H16: Vinoth M | I16: 2026 | J16: 3603.6651 | K16: 2576.0278 | U16: 6179.6929
A17: PT PELITA TRANSFER NUSANTARA | B17: APAC | C17: Masspay | D17: Bank Transfer | E17: Active | F17: No response from the client post reminder sent | G17: Luciana | H17: NA | I17: 2025 | O17: 5.6508548 | Q17: 5.6508548 | U17: 11.30171
A18: MULTIPLIER TECHNOLOGIES PTE. LTD | B18: APAC | C18: N1 | D18: Bank Transfer | E18: Active | F18: No response from the client post reminder sent | G18: Shi Yin | H18: Vinoth M | I18: 2025 | O18: 2756.75 | P18: 2743 | Q18: 2034 | U18: 7533.75
A19: MULTIPLIER TECHNOLOGIES PTE. LTD | B19: APAC | C19: N1 | D19: Bank Transfer | E19: Active | F19: No response from the client post reminder sent | G19: Shi Yin | H19: Vinoth M | I19: 2026 | J19: 2965 | K19: 2963.5 | U19: 5928.5
A20: VOLOPAY.CO PTE. LTD. | B20: APAC | C20: N1 | D20: Bank Transfer | E20: Active | F20: Client is disputing on decline charges on blocked cards,awaiting further update from AM. | G20: XiaoXiao | H20: Gitesh Athavale | I20: 2025 | N20: 1430.625 | O20: -527.4851 | P20: -3888.0024 | Q20: -1738.4406 | T20: 25680.39 | U20: 20957.087
A21: VOLOPAY.CO PTE. LTD. | B21: APAC | C21: N1 | D21: Bank Transfer | E21: Active | F21: Client is disputing on decline charges on blocked cards,awaiting further update from AM. | G21: XiaoXiao | H21: Gitesh Athavale | I21: 2026 | J21: -1754.3782 | K21: 606.2657 | U21: -1148.1125
A22: Nuvei Limited | B22: APAC | C22: Masspay | D22: Bank Transfer | E22: Active | F22: (blank) | G22: XiaoXiao | H22: Rohit Bammi | I22: 2026 | K22: 22670 | U22: 22670
A23: PT UCE Global Utama | B23: APAC | C23: N1 | D23: Bank Transfer | E23: Active | F23: (blank) | G23: NA | H23: Hari Budiman | I23: 2026 | K23: 8.816835 | L23: 832.88505 | U23: 841.70188
A24: Everpro Holdings Limited | B24: APAC | C24: Masspay | D24: Bank Transfer | E24: Active | F24: No response from the client post reminder sent | G24: NA | H24: Lisa Sung | I24: 2026 | J24: 5000 | K24: 5000 | U24: 10000
A25: FIRSTKYC PTE. LTD. | B25: APAC | C25: N1 | D25: Bank Transfer | E25: Active | F25: Client will settle once lumpsum threshold achieved | G25: NA | H25: Denis Tan | I25: 2025 | Q25: 1.72 | U25: 1.72
A26: FIRSTKYC PTE. LTD. | B26: APAC | C26: N1 | D26: Bank Transfer | E26: Active | F26: Client will settle once lumpsum threshold achieved | G26: NA | H26: Denis Tan | I26: 2026 | J26: 14.19 | K26: 6.88 | U26: 21.07
A27: iPiD Europe B.V. | B27: APAC | C27: N1 | D27: Bank Transfer | E27: Active | F27: No response from the client post reminder sent | G27: NA | H27: Febriali Tan | I27: 2025 | Q27: 2000 | U27: 2000
A28: Corporate Alliance Payments Pty Ltd - NSP | B28: APAC | C28: Masspay | D28: Bank Transfer | E28: Active | F28: (blank) | G28: Hao Nguyen | H28: Vinoth M | I28: 2026 | K28: 1431.4899 | U28: 1431.4899
A29: PT Transwap Dunamis Indonesia | B29: APAC | C29: Masspay | D29: Wallet Debit | E29: Active | F29: (blank) | G29: NA | H29: Hari Budiman | I29: 2026 | K29: 109.34 | U29: 109.34
A30: The CurrencyCloud Limited | B30: APAC | C30: Masspay | D30: Bank Transfer | E30: Active | F30: (blank) | G30: XiaoXiao | H30: NA | I30: 2026 | K30: 54089.5 | U30: 54089.5
A31: Express Hub Services Pty Ltd | B31: APAC | C31: N1 | D31: Bank Transfer | E31: Active | F31: No response from the client post reminder sent | G31: NA | H31: Wendy zhai | I31: 2026 | J31: 6666.8032 | U31: 6666.8032
A32: Express Hub Services Pty Ltd | B32: APAC | C32: N1 | D32: Bank Transfer | E32: Active | F32: (blank) | G32: NA | H32: Wendy zhai | I32: 2026 | K32: 3319.6976 | U32: 3319.6976
A33: Genieum Services Pty Ltd | B33: APAC | C33: N1 | D33: Bank Transfer | E33: Active | F33: (blank) | G33: NA | H33: Vinoth M | I33: 2026 | K33: 1896.971 | U33: 1896.971
A34: SlideSG Pte. Ltd. | B34: APAC | C34: N1 | D34: Bank Transfer | E34: Active | F34: No response from the client post reminder sent | G34: Shi Yin | H34: Gitesh Athavale | I34: 2026 | J34: 30312.631 | U34: 30312.631
A35: WORLDFIRST (SINGAPORE) MERCHANT SERVICESPTE. LTD. | B35: APAC | C35: N1 | D35: Bank Transfer | E35: Active | F35: (blank) | G35: NA | H35: Lisa Sung | I35: 2026 | K35: 25075 | U35: 25075
A36: Ichange Pte Ltd | B36: APAC | C36: N1 | D36: Bank Transfer | E36: Active | F36: (blank) | G36: Shi Yin | H36: Gitesh Athavale | I36: 2026 | K36: 20255.21 | U36: 20255.21
A37: kasikorn bank | B37: APAC | C37: Masspay | D37: Bank Transfer | E37: Active | F37: (blank) | G37: Pat Sarisa | H37: NA | I37: 2026 | K37: 22012 | U37: 22012
A38: Grand Total | J38: -17753.706 | K38: 165798.49 | L38: 10832.885 | M38: 10000 | N38: 6845.3624 | O38: 8438.9592 | P38: 10671.133 | Q38: 9274.8923 | R38: 10000 | S38: 1319.9063 | T38: 30280.649 | U38: 245708.57

Sheet Sheet1
A1: Region | B1: APAC/ME
A2: Account Manager | B2: Hui Ting Hoe
A4: Sum of USD AMOUNT | B4: Column Labels
A5: Row Labels | B5: 0-30 days | C5: 31-60 days | D5: 61-90 days | E5: Over 90+ days | F5: Grand Total
A6: Hong Leong Finance Limited | B6: 8074.9534 | D6: 4652.5833 | F6: 12727.537
A7: iFast Financial Pte Ltd | B7: 3452.8545 | F7: 3452.8545
A8: Transwap Private Limited | B8: 4406.6802 | C8: 3236.5106 | D8: 3389.1551 | E8: 23791.203 | F8: 34823.549
A9: Grand Total | B9: 15934.488 | C9: 3236.5106 | D9: 8041.7385 | E9: 23791.203 | F9: 51003.94

Sheet Invoices
A1: Platform | B1: Customer Label | C1: Region | D1: Account Manager | E1: BD | F1: Client Status | G1: Year | H1: Settlement Type | I1: Currency | J1: USD AMOUNT | K1: Invoice Amount | L1: Billing Period | M1: Month | N1: Days | O1: Ageing Tier | P1: Fee Type | Q1: Invoice Date | R1: Due Date | S1: Invoice Status | T1: Invoice Number | U1: Reminder Sent | V1: LOD | W1: AR's Comments | X1: AM's Comments | Y1: =TODAY() -> 46106
A2: N1 | B2: SWiM Pay Pty Ltd | C2: =VLOOKUP(B2,Validation!A:B,2,0) -> APAC | D2: =VLOOKUP(B2,Validation!A:D,4,0) -> NA | E2: =VLOOKUP(B2,Validation!A:E,5,0) -> Vinoth M | F2: Active | G2: =YEAR(L2) -> 2024 | H2: Bank Transfer | I2: USD | J2: =VLOOKUP(I2,'XE rates'!A:D,4,0)*K2 -> 5500 | K2: 5500 | L2: 45597 | M2: =TEXT(L2,"mmm") -> Nov | N2: =$Y$1-R2 -> 469 | O2: =IF(N2<=30, "0-30 days", IF(N2<=60, "31-60 days", IF(N2<=90, "61-90 days", "Over 90+ days"))) -> Over 90+ days | P2: Monthly Billing | Q2: 45597 | R2: 45637 | S2: Outstanding | T2: INV-041224105640 | U2: Yes | V2: Yes | W2: client has made progress with their capital raise however not provided exact settlement date to clear all o/s | Y2: =VLOOKUP(T2,'[1]Query result'!$J:$K,2,0) -> 45637 | Z2: =VLOOKUP(T2,'[1]Query result'!$J:$W,14,0) -> 0 | AA2: =K2-Z2 -> 5500 | AB2: =VLOOKUP(T2,'[2]Query result'!$F:$G,2,0) -> Outstanding
A3: N1 | B3: SWiM Pay Pty Ltd | C3: =VLOOKUP(B3,Validation!A:B,2,0) -> APAC | D3: =VLOOKUP(B3,Validation!A:D,4,0) -> NA | E3: =VLOOKUP(B3,Validation!A:E,5,0) -> Vinoth M | F3: Active | G3: =YEAR(L3) -> 2025 | H3: Bank Transfer | I3: USD | J3: =VLOOKUP(I3,'XE rates'!A:D,4,0)*K3 -> 9930 | K3: 9930 | L3: 45658 | M3: =TEXT(L3,"mmm") -> Jan | N3: =$Y$1-R3 -> 406 | O3: =IF(N3<=30, "0-30 days", IF(N3<=60, "31-60 days", IF(N3<=90, "61-90 days", "Over 90+ days"))) -> Over 90+ days | P3: Monthly Billing | Q3: 45693 | R3: 45700 | S3: Outstanding | T3: INV-050225183406 | U3: Yes | V3: Yes | W3: client has made progress with their capital raise however not provided exact settlement date to clear all o/s | Y3: =VLOOKUP(T3,'[1]Query result'!$J:$K,2,0) -> 45700 | Z3: =VLOOKUP(T3,'[1]Query result'!$J:$W,14,0) -> 0 | AA3: =K3-Z3 -> 9930 | AB3: =VLOOKUP(T3,'[2]Query result'!$F:$G,2,0) -> Outstanding
A4: N1 | B4: SWiM Pay Pty Ltd | C4: =VLOOKUP(B4,Validation!A:B,2,0) -> APAC | D4: =VLOOKUP(B4,Validation!A:D,4,0) -> NA | E4: =VLOOKUP(B4,Validation!A:E,5,0) -> Vinoth M | F4: Active | G4: =YEAR(L4) -> 2025 | H4: Bank Transfer | I4: USD | J4: =VLOOKUP(I4,'XE rates'!A:D,4,0)*K4 -> 10000 | K4: 10000 | L4: 45689 | M4: =TEXT(L4,"mmm") -> Feb | N4: =$Y$1-R4 -> 378 | O4: =IF(N4<=30, "0-30 days", IF(N4<=60, "31-60 days", IF(N4<=90, "61-90 days", "Over 90+ days"))) -> Over 90+ days | P4: Monthly Billing | Q4: 45721 | R4: 45728 | S4: Outstanding | T4: INV-050325103203 | U4: Yes | V4: Yes | W4: client has made progress with their capital raise however not provided exact settlement date to clear all o/s | Y4: =VLOOKUP(T4,'[1]Query result'!$J:$K,2,0) -> 45728 | Z4: =VLOOKUP(T4,'[1]Query result'!$J:$W,14,0) -> 0 | AA4: =K4-Z4 -> 10000 | AB4: =VLOOKUP(T4,'[2]Query result'!$F:$G,2,0) -> Outstanding
A5: N1 | B5: SWiM Pay Pty Ltd | C5: =VLOOKUP(B5,Validation!A:B,2,0) -> APAC | D5: =VLOOKUP(B5,Validation!A:D,4,0) -> NA | E5: =VLOOKUP(B5,Validation!A:E,5,0) -> Vinoth M | F5: Active | G5: =YEAR(L5) -> 2025 | H5: Bank Transfer | I5: USD | J5: =VLOOKUP(I5,'XE rates'!A:D,4,0)*K5 -> 10000 | K5: 10000 | L5: 45717 | M5: =TEXT(L5,"mmm") -> Mar | N5: =$Y$1-R5 -> 350 | O5: =IF(N5<=30, "0-30 days", IF(N5<=60, "31-60 days", IF(N5<=90, "61-90 days", "Over 90+ days"))) -> Over 90+ days | P5: Monthly Billing | Q5: 45749 | R5: 45756 | S5: Outstanding | T5: INV-020425174717 | U5: Yes | V5: Yes | W5: client has made progress with their capital raise however not provided exact settlement date to clear all o/s | Y5: =VLOOKUP(T5,'[1]Query result'!$J:$K,2,0) -> 45756 | Z5: =VLOOKUP(T5,'[1]Query result'!$J:$W,14,0) -> 0 | AA5: =K5-Z5 -> 10000 | AB5: =VLOOKUP(T5,'[2]Query result'!$F:$G,2,0) -> Outstanding
A6: N1 | B6: SWiM Pay Pty Ltd | C6: =VLOOKUP(B6,Validation!A:B,2,0) -> APAC | D6: =VLOOKUP(B6,Validation!A:D,4,0) -> NA | E6: =VLOOKUP(B6,Validation!A:E,5,0) -> Vinoth M | F6: Active | G6: =YEAR(L6) -> 2025 | H6: Bank Transfer | I6: USD | J6: =VLOOKUP(I6,'XE rates'!A:D,4,0)*K6 -> 10000 | K6: 10000 | L6: 45748 | M6: =TEXT(L6,"mmm") -> Apr | N6: =$Y$1-R6 -> 317 | O6: =IF(N6<=30, "0-30 days", IF(N6<=60, "31-60 days", IF(N6<=90, "61-90 days", "Over 90+ days"))) -> Over 90+ days | P6: Monthly Billing | Q6: 45782 | R6: 45789 | S6: Outstanding | T6: INV-050525114818 | U6: Yes | V6: Yes | W6: client has made progress with their capital raise however not provided exact settlement date to clear all o/s | Y6: =VLOOKUP(T6,'[1]Query result'!$J:$K,2,0) -> 45789 | Z6: =VLOOKUP(T6,'[1]Query result'!$J:$W,14,0) -> 0 | AA6: =K6-Z6 -> 10000 | AB6: =VLOOKUP(T6,'[2]Query result'!$F:$G,2,0) -> Outstanding
A7: N1 | B7: SWiM Pay Pty Ltd | C7: =VLOOKUP(B7,Validation!A:B,2,0) -> APAC | D7: =VLOOKUP(B7,Validation!A:D,4,0) -> NA | E7: =VLOOKUP(B7,Validation!A:E,5,0) -> Vinoth M | F7: Active | G7: =YEAR(L7) -> 2025 | H7: Bank Transfer | I7: USD | J7: =VLOOKUP(I7,'XE rates'!A:D,4,0)*K7 -> 10000 | K7: 10000 | L7: 45778 | M7: =TEXT(L7,"mmm") -> May | N7: =$Y$1-R7 -> 287 | O7: =IF(N7<=30, "0-30 days", IF(N7<=60, "31-60 days", IF(N7<=90, "61-90 days", "Over 90+ days"))) -> Over 90+ days | P7: Monthly Billing | Q7: 45812 | R7: 45819 | S7: Outstanding | T7: INV-040625165635 | U7: Yes | V7: Yes | W7: client has made progress with their capital raise however not provided exact settlement date to clear all o/s | Y7: =VLOOKUP(T7,'[1]Query result'!$J:$K,2,0) -> 45819 | Z7: =VLOOKUP(T7,'[1]Query result'!$J:$W,14,0) -> 0 | AA7: =K7-Z7 -> 10000 | AB7: =VLOOKUP(T7,'[2]Query result'!$F:$G,2,0) -> Outstanding
A8: N1 | B8: Loadpass LTDA | C8: =VLOOKUP(B8,Validation!A:B,2,0) -> USA | D8: =VLOOKUP(B8,Validation!A:D,4,0) -> Eduardo Avallone | E8: =VLOOKUP(B8,Validation!A:E,5,0) -> Christina Hutchinson | F8: Active | G8: =YEAR(L8) -> 2025 | H8: Bank Transfer | I8: USD | J8: =VLOOKUP(I8,'XE rates'!A:D,4,0)*K8 -> 3495.5 | K8: 3495.5 | L8: 45839 | M8: =TEXT(L8,"mmm") -> Jul | N8: =$Y$1-R8 -> 225 | O8: =IF(N8<=30, "0-30 days", IF(N8<=60, "31-60 days", IF(N8<=90, "61-90 days", "Over 90+ days"))) -> Over 90+ days | P8: Monthly Billing | Q8: 45874 | R8: 45881 | S8: Outstanding | T8: INV-050825115818 | U8: Yes | V8: No | W8: AM is chasing the client to clear all o/s invoices | Y8: =VLOOKUP(T8,'[1]Query result'!$J:$K,2,0) -> 45881 | Z8: =VLOOKUP(T8,'[1]Query result'!$J:$W,14,0) -> 0 | AA8: =K8-Z8 -> 3495.5 | AB8: =VLOOKUP(T8,'[2]Query result'!$F:$G,2,0) -> Outstanding
A9: N1 | B9: Yondr Money Pty Ltd | C9: =VLOOKUP(B9,Validation!A:B,2,0) -> APAC | D9: =VLOOKUP(B9,Validation!A:D,4,0) -> Hao Nguyen | E9: =VLOOKUP(B9,Validation!A:E,5,0) -> NA | F9: Active | G9: =YEAR(L9) -> 2025 | H9: Bank Transfer | I9: AUD | J9: =VLOOKUP(I9,'XE rates'!A:D,4,0)*K9 -> 1319.9063 | K9: =6943.705-4972.13 -> 1971.575 | L9: 45839 | M9: =TEXT(L9,"mmm") -> Jul | N9: =$Y$1-R9 -> 225 | O9: =IF(N9<=30, "0-30 days", IF(N9<=60, "31-60 days", IF(N9<=90, "61-90 days", "Over 90+ days"))) -> Over 90+ days | P9: Monthly Billing | Q9: 45874 | R9: 45881 | S9: Partially Paid | T9: INV-050825195438 | U9: Yes | V9: Yes | W9: AM to provide an update if invoices needs to be written off as client is suspended | Y9: =VLOOKUP(T9,'[1]Query result'!$J:$K,2,0) -> 45881 | Z9: =VLOOKUP(T9,'[1]Query result'!$J:$W,14,0) -> 0 | AA9: =K9-Z9 -> 1971.575 | AB9: =VLOOKUP(T9,'[2]Query result'!$F:$G,2,0) -> Partially Paid
A10: N1 | B10: Loadpass LTDA | C10: =VLOOKUP(B10,Validation!A:B,2,0) -> USA | D10: =VLOOKUP(B10,Validation!A:D,4,0) -> Eduardo Avallone | E10: =VLOOKUP(B10,Validation!A:E,5,0) -> Christina Hutchinson | F10: Active | G10: =YEAR(L10) -> 2025 | H10: Bank Transfer | I10: USD | J10: =VLOOKUP(I10,'XE rates'!A:D,4,0)*K10 -> 3485 | K10: 3485 | L10: 45870 | M10: =TEXT(L10,"mmm") -> Aug | N10: =$Y$1-R10 -> 197 | O10: =IF(N10<=30, "0-30 days", IF(N10<=60, "31-60 days", IF(N10<=90, "61-90 days", "Over 90+ days"))) -> Over 90+ days | P10: Monthly Billing | Q10: 45902 | R10: 45909 | S10: Outstanding | T10: INV-020925171323 | U10: Yes | V10: No | W10: AM is chasing the client to clear all o/s invoices | Y10: =VLOOKUP(T10,'[1]Query result'!$J:$K,2,0) -> 45909 | Z10: =VLOOKUP(T10,'[1]Query result'!$J:$W,14,0) -> 0 | AA10: =K10-Z10 -> 3485 | AB10: =VLOOKUP(T10,'[2]Query result'!$F:$G,2,0) -> Outstanding
A11: N1 | B11: VOLOPAY.CO PTE. LTD. | C11: =VLOOKUP(B11,Validation!A:B,2,0) -> APAC | D11: =VLOOKUP(B11,Validation!A:D,4,0) -> XiaoXiao | E11: =VLOOKUP(B11,Validation!A:E,5,0) -> Gitesh Athavale | F11: Active | G11: =YEAR(L11) -> 2025 | H11: Bank Transfer | I11: USD | J11: =VLOOKUP(I11,'XE rates'!A:D,4,0)*K11 -> 25680.39 | K11: =34635.56-8955.17 -> 25680.39 | L11: 45870 | M11: =TEXT(L11,"mmm") -> Aug | N11: =$Y$1-R11 -> 195 | O11: =IF(N11<=30, "0-30 days", IF(N11<=60, "31-60 days", IF(N11<=90, "61-90 days", "Over 90+ days"))) -> Over 90+ days | P11: Monthly Billing | Q11: 45904 | R11: 45911 | S11: Partially Paid | T11: INV-040925095830 | U11: Yes | V11: No | W11: Client is disputing on decline charges on blocked cards,awaiting further update from AM. | Y11: =VLOOKUP(T11,'[1]Query result'!$J:$K,2,0) -> 45911 | Z11: =VLOOKUP(T11,'[1]Query result'!$J:$W,14,0) -> 0 | AA11: =K11-Z11 -> 25680.39 | AB11: =VLOOKUP(T11,'[2]Query result'!$F:$G,2,0) -> Partially Paid
A12: N1 | B12: Yondr Money Pty Ltd | C12: =VLOOKUP(B12,Validation!A:B,2,0) -> APAC | D12: =VLOOKUP(B12,Validation!A:D,4,0) -> Hao Nguyen | E12: =VLOOKUP(B12,Validation!A:E,5,0) -> NA | F12: Active | G12: =YEAR(L12) -> 2025 | H12: Bank Transfer | I12: AUD | J12: =VLOOKUP(I12,'XE rates'!A:D,4,0)*K12 -> 4600.2593 | K12: 6871.515 | L12: 45870 | M12: =TEXT(L12,"mmm") -> Aug | N12: =$Y$1-R12 -> 196 | O12: =IF(N12<=30, "0-30 days", IF(N12<=60, "31-60 days", IF(N12<=90, "61-90 days", "Over 90+ days"))) -> Over 90+ days | P12: Monthly Billing | Q12: 45903 | R12: 45910 | S12: Outstanding | T12: INV-030925145658 | U12: Yes | V12: Yes | W12: AM to provide an update if invoices needs to be written off as client is suspended | Y12: =VLOOKUP(T12,'[1]Query result'!$J:$K,2,0) -> 45910 | Z12: =VLOOKUP(T12,'[1]Query result'!$J:$W,14,0) -> 0 | AA12: =K12-Z12 -> 6871.515 | AB12: =VLOOKUP(T12,'[2]Query result'!$F:$G,2,0) -> Outstanding
A13: Masspay | B13: FTB HUB S.A.C | C13: =VLOOKUP(B13,Validation!A:B,2,0) -> USA | D13: =VLOOKUP(B13,Validation!A:D,4,0) -> Eduardo Avallone | E13: =VLOOKUP(B13,Validation!A:E,5,0) -> NA | F13: Active | G13: =YEAR(L13) -> 2025 | H13: Wallet Debit | I13: USD | J13: =VLOOKUP(I13,'XE rates'!A:D,4,0)*K13 -> 1020 | K13: 1020 | L13: 45901 | M13: =TEXT(L13,"mmm") -> Sep | N13: =$Y$1-R13 -> 169 | O13: =IF(N13<=30, "0-30 days", IF(N13<=60, "31-60 days", IF(N13<=90, "61-90 days", "Over 90+ days"))) -> Over 90+ days | P13: Monthly Billing | Q13: 45931 | R13: 45937 | S13: Force Settlement | T13: SG-FTBHUB-09/2025 | U13: Yes | V13: No | W13: wallet debited, insufficient funds | Y13: =VLOOKUP(T13,'[1]Query result'!$J:$K,2,0) -> 45937 | Z13: =VLOOKUP(T13,'[1]Query result'!$J:$W,14,0) -> 0 | AA13: =K13-Z13 -> 1020 | AB13: =VLOOKUP(T13,'[2]Query result'!$F:$G,2,0) -> Force Settlement
A14: N1 | B14: Loadpass LTDA | C14: =VLOOKUP(B14,Validation!A:B,2,0) -> USA | D14: =VLOOKUP(B14,Validation!A:D,4,0) -> Eduardo Avallone | E14: =VLOOKUP(B14,Validation!A:E,5,0) -> Christina Hutchinson | F14: Active | G14: =YEAR(L14) -> 2025 | H14: Bank Transfer | I14: USD | J14: =VLOOKUP(I14,'XE rates'!A:D,4,0)*K14 -> 3487.5 | K14: 3487.5 | L14: 45901 | M14: =TEXT(L14,"mmm") -> Sep | N14: =$Y$1-R14 -> 167 | O14: =IF(N14<=30, "0-30 days", IF(N14<=60, "31-60 days", IF(N14<=90, "61-90 days", "Over 90+ days"))) -> Over 90+ days | P14: Monthly Billing | Q14: 45932 | R14: 45939 | S14: Outstanding | T14: INV-021025184847 | U14: Yes | V14: No | W14: AM is chasing the client to clear all o/s invoices | Y14: =VLOOKUP(T14,'[1]Query result'!$J:$K,2,0) -> 45939 | Z14: =VLOOKUP(T14,'[1]Query result'!$J:$W,14,0) -> 0 | AA14: =K14-Z14 -> 3487.5 | AB14: =VLOOKUP(T14,'[2]Query result'!$F:$G,2,0) -> Outstanding
A15: N1 | B15: VOLOPAY.CO PTE. LTD. | C15: =VLOOKUP(B15,Validation!A:B,2,0) -> APAC | D15: =VLOOKUP(B15,Validation!A:D,4,0) -> XiaoXiao | E15: =VLOOKUP(B15,Validation!A:E,5,0) -> Gitesh Athavale | F15: Active | G15: =YEAR(L15) -> 2025 | H15: Bank Transfer | I15: USD | J15: =VLOOKUP(I15,'XE rates'!A:D,4,0)*K15 -> 1430.625 | K15: 1430.625 | L15: 45901 | M15: =TEXT(L15,"mmm") -> Sep | N15: =$Y$1-R15 -> 163 | O15: =IF(N15<=30, "0-30 days", IF(N15<=60, "31-60 days", IF(N15<=90, "61-90 days", "Over 90+ days"))) -> Over 90+ days | P15: Monthly Billing | Q15: 45936 | R15: 45943 | S15: Outstanding | T15: INV-061025143320 | U15: Yes | V15: No | W15: Client is disputing on decline charges on blocked cards,awaiting further update from AM. | Y15: =VLOOKUP(T15,'[1]Query result'!$J:$K,2,0) -> 45943 | Z15: =VLOOKUP(T15,'[1]Query result'!$J:$W,14,0) -> 0 | AA15: =K15-Z15 -> 1430.625 | AB15: =VLOOKUP(T15,'[2]Query result'!$F:$G,2,0) -> Outstanding
A16: N1 | B16: Yondr Money Pty Ltd | C16: =VLOOKUP(B16,Validation!A:B,2,0) -> APAC | D16: =VLOOKUP(B16,Validation!A:D,4,0) -> Hao Nguyen | E16: =VLOOKUP(B16,Validation!A:E,5,0) -> NA | F16: Active | G16: =YEAR(L16) -> 2025 | H16: Bank Transfer | I16: AUD | J16: =VLOOKUP(I16,'XE rates'!A:D,4,0)*K16 -> 4495.6248 | K16: 6715.22 | L16: 45901 | M16: =TEXT(L16,"mmm") -> Sep | N16: =$Y$1-R16 -> 163 | O16: =IF(N16<=30, "0-30 days", IF(N16<=60, "31-60 days", IF(N16<=90, "61-90 days", "Over 90+ days"))) -> Over 90+ days | P16: Monthly Billing | Q16: 45936 | R16: 45943 | S16: Outstanding | T16: INV-061025125629 | U16: Yes | V16: Yes | W16: AM to provide an update if invoices needs to be written off as client is suspended | Y16: =VLOOKUP(T16,'[1]Query result'!$J:$K,2,0) -> 45943 | Z16: =VLOOKUP(T16,'[1]Query result'!$J:$W,14,0) -> 0 | AA16: =K16-Z16 -> 6715.22 | AB16: =VLOOKUP(T16,'[2]Query result'!$F:$G,2,0) -> Outstanding
A17: Masspay | B17: FTB HUB S.A.C | C17: =VLOOKUP(B17,Validation!A:B,2,0) -> USA | D17: =VLOOKUP(B17,Validation!A:D,4,0) -> Eduardo Avallone | E17: =VLOOKUP(B17,Validation!A:E,5,0) -> NA | F17: Active | G17: =YEAR(L17) -> 2025 | H17: Wallet Debit | I17: USD | J17: =VLOOKUP(I17,'XE rates'!A:D,4,0)*K17 -> 1000 | K17: 1000 | L17: 45931 | M17: =TEXT(L17,"mmm") -> Oct | N17: =$Y$1-R17 -> 138 | O17: =IF(N17<=30, "0-30 days", IF(N17<=60, "31-60 days", IF(N17<=90, "61-90 days", "Over 90+ days"))) -> Over 90+ days | P17: Monthly Billing | Q17: 45962 | R17: 45968 | S17: Force Settlement | T17: SG-FTBHUB-10/2025 | U17: Yes | V17: No | W17: wallet debited, insufficient funds | Y17: =VLOOKUP(T17,'[1]Query result'!$J:$K,2,0) -> 45968 | Z17: =VLOOKUP(T17,'[1]Query result'!$J:$W,14,0) -> 0 | AA17: =K17-Z17 -> 1000 | AB17: =VLOOKUP(T17,'[2]Query result'!$F:$G,2,0) -> Force Settlement
A18: Masspay | B18: PT PELITA TRANSFER NUSANTARA | C18: =VLOOKUP(B18,Validation!A:B,2,0) -> APAC | D18: =VLOOKUP(B18,Validation!A:D,4,0) -> Luciana | E18: =VLOOKUP(B18,Validation!A:E,5,0) -> NA | F18: Active | G18: =YEAR(L18) -> 2025 | H18: Bank Transfer | I18: IDR | J18: =VLOOKUP(I18,'XE rates'!A:D,4,0)*K18 -> 5.6508548 | K18: 95444 | L18: 45931 | M18: =TEXT(L18,"mmm") -> Oct | N18: =$Y$1-R18 -> 127 | O18: =IF(N18<=30, "0-30 days", IF(N18<=60, "31-60 days", IF(N18<=90, "61-90 days", "Over 90+ days"))) -> Over 90+ days | P18: Monthly Billing | Q18: 45964 | R18: 45979 | S18: Overdue | T18: ID-ptpelita-10/2025 | U18: Yes | V18: No | W18: No response from the client post reminder sent | Y18: =VLOOKUP(T18,'[1]Query result'!$J:$K,2,0) -> 45979 | Z18: =VLOOKUP(T18,'[1]Query result'!$J:$W,14,0) -> 0 | AA18: =K18-Z18 -> 95444 | AB18: =VLOOKUP(T18,'[2]Query result'!$F:$G,2,0) -> Overdue
A19: N1 | B19: Azimo Limited. | C19: =VLOOKUP(B19,Validation!A:B,2,0) -> EU/UK | D19: =VLOOKUP(B19,Validation!A:D,4,0) -> Sachli Zare | E19: =VLOOKUP(B19,Validation!A:E,5,0) -> Gitesh Athavale | F19: Active | G19: =YEAR(L19) -> 2025 | H19: Bank Transfer | I19: GBP | J19: =VLOOKUP(I19,'XE rates'!A:D,4,0)*K19 -> 186.09528 | K19: 139.19 | L19: 45931 | M19: =TEXT(L19,"mmm") -> Oct | N19: =$Y$1-R19 -> 135 | O19: =IF(N19<=30, "0-30 days", IF(N19<=60, "31-60 days", IF(N19<=90, "61-90 days", "Over 90+ days"))) -> Over 90+ days | P19: Monthly Billing | Q19: 45964 | R19: 45971 | S19: Outstanding | T19: INV-031125184753 | U19: Yes | V19: No | W19: No response from the client post reminder sent | Y19: =VLOOKUP(T19,'[1]Query result'!$J:$K,2,0) -> 45971 | Z19: =VLOOKUP(T19,'[1]Query result'!$J:$W,14,0) -> 0 | AA19: =K19-Z19 -> 139.19 | AB19: =VLOOKUP(T19,'[2]Query result'!$F:$G,2,0) -> Outstanding
A20: N1 | B20: Budgetly Pty Ltd | C20: =VLOOKUP(B20,Validation!A:B,2,0) -> APAC | D20: =VLOOKUP(B20,Validation!A:D,4,0) -> Hao Nguyen | E20: =VLOOKUP(B20,Validation!A:E,5,0) -> Vinoth M | F20: Active | G20: =YEAR(L20) -> 2025 | H20: Bank Transfer | I20: AUD | J20: =VLOOKUP(I20,'XE rates'!A:D,4,0)*K20 -> 919.11259 | K20: 1372.9 | L20: 45901 | M20: =TEXT(L20,"mmm") -> Sep | N20: =$Y$1-R20 -> 117 | O20: =IF(N20<=30, "0-30 days", IF(N20<=60, "31-60 days", IF(N20<=90, "61-90 days", "Over 90+ days"))) -> Over 90+ days | P20: Card Printing and Delivery | Q20: 45958 | R20: 45989 | S20: Outstanding | T20: INV-281025170000 | U20: Yes | V20: No | W20: Card printing invoice pending | Y20: =VLOOKUP(T20,'[1]Query result'!$J:$K,2,0) -> 45989 | Z20: =VLOOKUP(T20,'[1]Query result'!$J:$W,14,0) -> 0 | AA20: =K20-Z20 -> 1372.9 | AB20: =VLOOKUP(T20,'[2]Query result'!$F:$G,2,0) -> Partially Paid
A21: N1 | B21: JPMORGAN CHASE BANK | C21: =VLOOKUP(B21,Validation!A:B,2,0) -> EU/UK | D21: =VLOOKUP(B21,Validation!A:D,4,0) -> Sachli Zare | E21: =VLOOKUP(B21,Validation!A:E,5,0) -> NA | F21: Active | G21: =YEAR(L21) -> 2025 | H21: Bank Transfer | I21: USD | J21: =VLOOKUP(I21,'XE rates'!A:D,4,0)*K21 -> 75 | K21: 75 | L21: 45931 | M21: =TEXT(L21,"mmm") -> Oct | N21: =$Y$1-R21 -> 133 | O21: =IF(N21<=30, "0-30 days", IF(N21<=60, "31-60 days", IF(N21<=90, "61-90 days", "Over 90+ days"))) -> Over 90+ days | P21: Monthly Billing | Q21: 45966 | R21: 45973 | S21: Partially Paid | T21: INV-051125174218 | U21: Yes | V21: No | W21: Partially settled by the client | Y21: =VLOOKUP(T21,'[1]Query result'!$J:$K,2,0) -> 45973 | Z21: =VLOOKUP(T21,'[1]Query result'!$J:$W,14,0) -> 0 | AA21: =K21-Z21 -> 75 | AB21: =VLOOKUP(T21,'[2]Query result'!$F:$G,2,0) -> Partially Paid
A22: N1 | B22: Loadpass LTDA | C22: =VLOOKUP(B22,Validation!A:B,2,0) -> USA | D22: =VLOOKUP(B22,Validation!A:D,4,0) -> Eduardo Avallone | E22: =VLOOKUP(B22,Validation!A:E,5,0) -> Christina Hutchinson | F22: Active | G22: =YEAR(L22) -> 2025 | H22: Bank Transfer | I22: USD | J22: =VLOOKUP(I22,'XE rates'!A:D,4,0)*K22 -> 2602.25 | K22: 2602.25 | L22: 45931 | M22: =TEXT(L22,"mmm") -> Oct | N22: =$Y$1-R22 -> 133 | O22: =IF(N22<=30, "0-30 days", IF(N22<=60, "31-60 days", IF(N22<=90, "61-90 days", "Over 90+ days"))) -> Over 90+ days | P22: Monthly Billing | Q22: 45966 | R22: 45973 | S22: Outstanding | T22: INV-051125173213 | U22: Yes | V22: No | W22: AM is chasing the client to clear all o/s invoices | Y22: =VLOOKUP(T22,'[1]Query result'!$J:$K,2,0) -> 45973 | Z22: =VLOOKUP(T22,'[1]Query result'!$J:$W,14,0) -> 0 | AA22: =K22-Z22 -> 2602.25 | AB22: =VLOOKUP(T22,'[2]Query result'!$F:$G,2,0) -> Outstanding
A23: N1 | B23: MULTIPLIER TECHNOLOGIES PTE. LTD | C23: =VLOOKUP(B23,Validation!A:B,2,0) -> APAC | D23: =VLOOKUP(B23,Validation!A:D,4,0) -> Shi Yin | E23: =VLOOKUP(B23,Validation!A:E,5,0) -> Vinoth M | F23: Active | G23: 2025 | H23: Bank Transfer | I23: USD | J23: =VLOOKUP(I23,'XE rates'!A:D,4,0)*K23 -> 2756.75 | K23: 2756.75 | L23: Sep & oct-2025 | M23: Oct | N23: =$Y$1-R23 -> 126 | O23: =IF(N23<=30, "0-30 days", IF(N23<=60, "31-60 days", IF(N23<=90, "61-90 days", "Over 90+ days"))) -> Over 90+ days | P23: Monthly Billing | Q23: 45966 | R23: 45980 | S23: Partially Paid | T23: INV-051125161416 | U23: Yes | V23: No | W23: No response from the client post reminder sent | Y23: =VLOOKUP(T23,'[1]Query result'!$J:$K,2,0) -> 45980 | Z23: =VLOOKUP(T23,'[1]Query result'!$J:$W,14,0) -> 0 | AA23: =K23-Z23 -> 2756.75 | AB23: =VLOOKUP(T23,'[2]Query result'!$F:$G,2,0) -> Partially Paid
A24: N1 | B24: Yondr Money Pty Ltd | C24: =VLOOKUP(B24,Validation!A:B,2,0) -> APAC | D24: =VLOOKUP(B24,Validation!A:D,4,0) -> Hao Nguyen | E24: =VLOOKUP(B24,Validation!A:E,5,0) -> NA | F24: Active | G24: =YEAR(L24) -> 2025 | H24: Bank Transfer | I24: AUD | J24: =VLOOKUP(I24,'XE rates'!A:D,4,0)*K24 -> 4473.4152 | K24: 6682.045 | L24: 45931 | M24: =TEXT(L24,"mmm") -> Oct | N24: =$Y$1-R24 -> 132 | O24: =IF(N24<=30, "0-30 days", IF(N24<=60, "31-60 days", IF(N24<=90, "61-90 days", "Over 90+ days"))) -> Over 90+ days | P24: Monthly Billing | Q24: 45967 | R24: 45974 | S24: Outstanding | T24: INV-061125104927 | U24: Yes | V24: Yes | W24: AM to provide an update if invoices needs to be written off as client is suspended | Y24: =VLOOKUP(T24,'[1]Query result'!$J:$K,2,0) -> 45974 | Z24: =VLOOKUP(T24,'[1]Query result'!$J:$W,14,0) -> 0 | AA24: =K24-Z24 -> 6682.045 | AB24: =VLOOKUP(T24,'[2]Query result'!$F:$G,2,0) -> Outstanding
A25: N1 | B25: Zeni, Inc. | C25: =VLOOKUP(B25,Validation!A:B,2,0) -> USA | D25: =VLOOKUP(B25,Validation!A:D,4,0) -> NA | E25: =VLOOKUP(B25,Validation!A:E,5,0) -> Tyler Reed | F25: Active | G25: =YEAR(L25) -> 2025 | H25: Bank Transfer | I25: USD | J25: =VLOOKUP(I25,'XE rates'!A:D,4,0)*K25 -> 0.5 | K25: 0.5 | L25: 45931 | M25: =TEXT(L25,"mmm") -> Oct | N25: =$Y$1-R25 -> 133 | O25: =IF(N25<=30, "0-30 days", IF(N25<=60, "31-60 days", IF(N25<=90, "61-90 days", "Over 90+ days"))) -> Over 90+ days | P25: Monthly Billing | Q25: 45966 | R25: 45973 | S25: Outstanding | T25: INV-041125182344 | U25: Yes | V25: No | W25: No response from the client post reminder sent | Y25: =VLOOKUP(T25,'[1]Query result'!$J:$K,2,0) -> 45973 | Z25: =VLOOKUP(T25,'[1]Query result'!$J:$W,14,0) -> 0 | AA25: =K25-Z25 -> 0.5 | AB25: =VLOOKUP(T25,'[2]Query result'!$F:$G,2,0) -> Outstanding
A26: N1 | B26: Budgetly Pty Ltd | C26: =VLOOKUP(B26,Validation!A:B,2,0) -> APAC | D26: =VLOOKUP(B26,Validation!A:D,4,0) -> Hao Nguyen | E26: =VLOOKUP(B26,Validation!A:E,5,0) -> Vinoth M | F26: Active | G26: =YEAR(L26) -> 2025 | H26: Bank Transfer | I26: AUD | J26: =VLOOKUP(I26,'XE rates'!A:D,4,0)*K26 -> 1730.6283 | K26: 2585.08 | L26: 45931 | M26: =TEXT(L26,"mmm") -> Oct | N26: =$Y$1-R26 -> 98 | O26: =IF(N26<=30, "0-30 days", IF(N26<=60, "31-60 days", IF(N26<=90, "61-90 days", "Over 90+ days"))) -> Over 90+ days | P26: Card Printing and Delivery | Q26: 45978 | R26: 46008 | S26: Outstanding | T26: INV-171125170000 | U26: No | V26: No | W26: Card printing invoice pending | Y26: =VLOOKUP(T26,'[1]Query result'!$J:$K,2,0) -> 46008 | Z26: =VLOOKUP(T26,'[1]Query result'!$J:$W,14,0) -> 0 | AA26: =K26-Z26 -> 2585.08 | AB26: =VLOOKUP(T26,'[2]Query result'!$F:$G,2,0) -> Outstanding
A27: Masspay | B27: FTB HUB S.A.C | C27: =VLOOKUP(B27,Validation!A:B,2,0) -> USA | D27: =VLOOKUP(B27,Validation!A:D,4,0) -> Eduardo Avallone | E27: =VLOOKUP(B27,Validation!A:E,5,0) -> NA | F27: Active | G27: =YEAR(L27) -> 2025 | H27: Wallet Debit | I27: USD | J27: =VLOOKUP(I27,'XE rates'!A:D,4,0)*K27 -> 1000 | K27: 1000 | L27: 45962 | M27: =TEXT(L27,"mmm") -> Nov | N27: =$Y$1-R27 -> 107 | O27: =IF(N27<=30, "0-30 days", IF(N27<=60, "31-60 days", IF(N27<=90, "61-90 days", "Over 90+ days"))) -> Over 90+ days | P27: Monthly Billing | Q27: 45992 | R27: 45999 | S27: Force Settlement | T27: SG-FTBHUB-11/2025 | U27: Yes | V27: No | W27: wallet debited, insufficient funds | Y27: =VLOOKUP(T27,'[1]Query result'!$J:$K,2,0) -> 45999 | Z27: =VLOOKUP(T27,'[1]Query result'!$J:$W,14,0) -> 0 | AA27: =K27-Z27 -> 1000 | AB27: =VLOOKUP(T27,'[2]Query result'!$F:$G,2,0) -> Force Settlement
A28: N1 | B28: Azimo Limited. | C28: =VLOOKUP(B28,Validation!A:B,2,0) -> EU/UK | D28: =VLOOKUP(B28,Validation!A:D,4,0) -> Sachli Zare | E28: =VLOOKUP(B28,Validation!A:E,5,0) -> Gitesh Athavale | F28: Active | G28: =YEAR(L28) -> 2025 | H28: Bank Transfer | I28: GBP | J28: =VLOOKUP(I28,'XE rates'!A:D,4,0)*K28 -> 127.08066 | K28: 95.05 | L28: 45962 | M28: =TEXT(L28,"mmm") -> Nov | N28: =$Y$1-R28 -> 83 | O28: =IF(N28<=30, "0-30 days", IF(N28<=60, "31-60 days", IF(N28<=90, "61-90 days", "Over 90+ days"))) -> 61-90 days | P28: Monthly Billing | Q28: 45993 | R28: 46023 | S28: Invoice Sent | T28: INV-021225130146 | U28: Yes | V28: No | W28: No response from the client post reminder sent | Y28: =VLOOKUP(T28,'[1]Query result'!$J:$K,2,0) -> 46023 | Z28: =VLOOKUP(T28,'[1]Query result'!$J:$W,14,0) -> 0 | AA28: =K28-Z28 -> 95.05 | AB28: =VLOOKUP(T28,'[2]Query result'!$F:$G,2,0) -> Outstanding
A29: N1 | B29: Budgetly Pty Ltd | C29: =VLOOKUP(B29,Validation!A:B,2,0) -> APAC | D29: =VLOOKUP(B29,Validation!A:D,4,0) -> Hao Nguyen | E29: =VLOOKUP(B29,Validation!A:E,5,0) -> Vinoth M | F29: Active | G29: =YEAR(L29) -> 2025 | H29: Bank Transfer | I29: AUD | J29: =VLOOKUP(I29,'XE rates'!A:D,4,0)*K29 -> 1729.4969 | K29: 2583.39 | L29: 45962 | M29: =TEXT(L29,"mmm") -> Nov | N29: =$Y$1-R29 -> 69 | O29: =IF(N29<=30, "0-30 days", IF(N29<=60, "31-60 days", IF(N29<=90, "61-90 days", "Over 90+ days"))) -> 61-90 days | P29: Card Printing and Delivery | Q29: 46006 | R29: 46037 | S29: Invoice Sent | T29: INV-151225170000 | U29: No | V29: No | W29: Card printing invoice pending | Y29: =VLOOKUP(T29,'[1]Query result'!$J:$K,2,0) -> 46037 | Z29: =VLOOKUP(T29,'[1]Query result'!$J:$W,14,0) -> 0 | AA29: =K29-Z29 -> 2583.39 | AB29: =VLOOKUP(T29,'[2]Query result'!$F:$G,2,0) -> Outstanding
A30: N1 | B30: goLance, Inc. | C30: =VLOOKUP(B30,Validation!A:B,2,0) -> USA | D30: =VLOOKUP(B30,Validation!A:D,4,0) -> Eduardo Avallone | E30: =VLOOKUP(B30,Validation!A:E,5,0) -> Greg McAllister | F30: Active | G30: =YEAR(L30) -> 2025 | H30: Bank Transfer | I30: USD | J30: =VLOOKUP(I30,'XE rates'!A:D,4,0)*K30 -> 130 | K30: 130 | L30: 45962 | M30: =TEXT(L30,"mmm") -> Nov | N30: =$Y$1-R30 -> 106 | O30: =IF(N30<=30, "0-30 days", IF(N30<=60, "31-60 days", IF(N30<=90, "61-90 days", "Over 90+ days"))) -> Over 90+ days | P30: Monthly Billing | Q30: 45993 | R30: 46000 | S30: Outstanding | T30: INV-021225154117 | U30: Yes | V30: No | W30: No response from the client post reminder sent | Y30: =VLOOKUP(T30,'[1]Query result'!$J:$K,2,0) -> 46000 | Z30: =VLOOKUP(T30,'[1]Query result'!$J:$W,14,0) -> 0 | AA30: =K30-Z30 -> 130 | AB30: =VLOOKUP(T30,'[2]Query result'!$F:$G,2,0) -> Outstanding
A31: N1 | B31: Istanbul Ödeme ve Elektronik Para A.S | C31: =VLOOKUP(B31,Validation!A:B,2,0) -> ME | D31: =VLOOKUP(B31,Validation!A:D,4,0) -> Jerome Coelho | E31: =VLOOKUP(B31,Validation!A:E,5,0) -> Ashraf Omran | F31: Active | G31: =YEAR(L31) -> 2025 | H31: Bank Transfer | I31: USD | J31: =VLOOKUP(I31,'XE rates'!A:D,4,0)*K31 -> 57.49 | K31: 57.49 | L31: 45962 | M31: =TEXT(L31,"mmm") -> Nov | N31: =$Y$1-R31 -> 106 | O31: =IF(N31<=30, "0-30 days", IF(N31<=60, "31-60 days", IF(N31<=90, "61-90 days", "Over 90+ days"))) -> Over 90+ days | P31: Monthly Billing | Q31: 45993 | R31: 46000 | S31: Partially Paid | T31: INV-021225185612 | U31: Yes | V31: No | W31: No response from the client post reminder sent | Y31: =VLOOKUP(T31,'[1]Query result'!$J:$K,2,0) -> 46000 | Z31: =VLOOKUP(T31,'[1]Query result'!$J:$W,14,0) -> 0 | AA31: =K31-Z31 -> 57.49 | AB31: =VLOOKUP(T31,'[2]Query result'!$F:$G,2,0) -> Partially Paid
A32: N1 | B32: Loadpass LTDA | C32: =VLOOKUP(B32,Validation!A:B,2,0) -> USA | D32: =VLOOKUP(B32,Validation!A:D,4,0) -> Eduardo Avallone | E32: =VLOOKUP(B32,Validation!A:E,5,0) -> Christina Hutchinson | F32: Active | G32: =YEAR(L32) -> 2025 | H32: Bank Transfer | I32: USD | J32: =VLOOKUP(I32,'XE rates'!A:D,4,0)*K32 -> 1786.14 | K32: 1786.14 | L32: 45962 | M32: =TEXT(L32,"mmm") -> Nov | N32: =$Y$1-R32 -> 106 | O32: =IF(N32<=30, "0-30 days", IF(N32<=60, "31-60 days", IF(N32<=90, "61-90 days", "Over 90+ days"))) -> Over 90+ days | P32: Monthly Billing | Q32: 45993 | R32: 46000 | S32: Outstanding | T32: INV-021225201549 | U32: Yes | V32: No | W32: AM is chasing the client to clear all o/s invoices | Y32: =VLOOKUP(T32,'[1]Query result'!$J:$K,2,0) -> 46000 | Z32: =VLOOKUP(T32,'[1]Query result'!$J:$W,14,0) -> 0 | AA32: =K32-Z32 -> 1786.14 | AB32: =VLOOKUP(T32,'[2]Query result'!$F:$G,2,0) -> Outstanding
A33: N1 | B33: MeshPay EU Ltd | C33: =VLOOKUP(B33,Validation!A:B,2,0) -> EU/UK | D33: =VLOOKUP(B33,Validation!A:D,4,0) -> Sachli Zare | E33: =VLOOKUP(B33,Validation!A:E,5,0) -> NA | F33: Active | G33: =YEAR(L33) -> 2025 | H33: Bank Transfer | I33: USD | J33: =VLOOKUP(I33,'XE rates'!A:D,4,0)*K33 -> 66.3 | K33: 66.3 | L33: 45962 | M33: =TEXT(L33,"mmm") -> Nov | N33: =$Y$1-R33 -> 69 | O33: =IF(N33<=30, "0-30 days", IF(N33<=60, "31-60 days", IF(N33<=90, "61-90 days", "Over 90+ days"))) -> 61-90 days | P33: Card Printing and Delivery | Q33: 46006 | R33: 46037 | S33: Invoice Sent | T33: INV2025-MSH-011 | U33: No | V33: No | W33: No response from the client post reminder sent | Y33: =VLOOKUP(T33,'[1]Query result'!$J:$K,2,0) -> 46037 | Z33: =VLOOKUP(T33,'[1]Query result'!$J:$W,14,0) -> 0 | AA33: =K33-Z33 -> 66.3 | AB33: =VLOOKUP(T33,'[2]Query result'!$F:$G,2,0) -> Outstanding
A34: N1 | B34: MULTIPLIER TECHNOLOGIES PTE. LTD | C34: =VLOOKUP(B34,Validation!A:B,2,0) -> APAC | D34: =VLOOKUP(B34,Validation!A:D,4,0) -> Shi Yin | E34: =VLOOKUP(B34,Validation!A:E,5,0) -> Vinoth M | F34: Active | G34: =YEAR(L34) -> 2025 | H34: Bank Transfer | I34: USD | J34: =VLOOKUP(I34,'XE rates'!A:D,4,0)*K34 -> 2743 | K34: 2743 | L34: 45962 | M34: =TEXT(L34,"mmm") -> Nov | N34: =$Y$1-R34 -> 97 | O34: =IF(N34<=30, "0-30 days", IF(N34<=60, "31-60 days", IF(N34<=90, "61-90 days", "Over 90+ days"))) -> Over 90+ days | P34: Monthly Billing | Q34: 45994 | R34: 46009 | S34: Invoice Sent | T34: INV-031225170417 | U34: Yes | V34: No | W34: No response from the client post reminder sent | Y34: =VLOOKUP(T34,'[1]Query result'!$J:$K,2,0) -> 46009 | Z34: =VLOOKUP(T34,'[1]Query result'!$J:$W,14,0) -> 0 | AA34: =K34-Z34 -> 2743 | AB34: =VLOOKUP(T34,'[2]Query result'!$F:$G,2,0) -> Outstanding
A35: N1 | B35: Yondr Money Pty Ltd | C35: =VLOOKUP(B35,Validation!A:B,2,0) -> APAC | D35: =VLOOKUP(B35,Validation!A:D,4,0) -> Hao Nguyen | E35: =VLOOKUP(B35,Validation!A:E,5,0) -> NA | F35: Active | G35: =YEAR(L35) -> 2025 | H35: Bank Transfer | I35: AUD | J35: =VLOOKUP(I35,'XE rates'!A:D,4,0)*K35 -> 4586.6383 | K35: 6851.169 | L35: 45962 | M35: =TEXT(L35,"mmm") -> Nov | N35: =$Y$1-R35 -> 104 | O35: =IF(N35<=30, "0-30 days", IF(N35<=60, "31-60 days", IF(N35<=90, "61-90 days", "Over 90+ days"))) -> Over 90+ days | P35: Monthly Billing | Q35: 45995 | R35: 46002 | S35: Outstanding | T35: INV-041225150054 | U35: Yes | V35: Yes | W35: AM to provide an update if invoices needs to be written off as client is suspended | Y35: =VLOOKUP(T35,'[1]Query result'!$J:$K,2,0) -> 46002 | Z35: =VLOOKUP(T35,'[1]Query result'!$J:$W,14,0) -> 0 | AA35: =K35-Z35 -> 6851.169 | AB35: =VLOOKUP(T35,'[2]Query result'!$F:$G,2,0) -> Outstanding
A36: N1 | B36: Zeni, Inc. | C36: =VLOOKUP(B36,Validation!A:B,2,0) -> USA | D36: =VLOOKUP(B36,Validation!A:D,4,0) -> NA | E36: =VLOOKUP(B36,Validation!A:E,5,0) -> Tyler Reed | F36: Active | G36: =YEAR(L36) -> 2025 | H36: Bank Transfer | I36: USD | J36: =VLOOKUP(I36,'XE rates'!A:D,4,0)*K36 -> 500 | K36: 500 | L36: 45962 | M36: =TEXT(L36,"mmm") -> Nov | N36: =$Y$1-R36 -> 105 | O36: =IF(N36<=30, "0-30 days", IF(N36<=60, "31-60 days", IF(N36<=90, "61-90 days", "Over 90+ days"))) -> Over 90+ days | P36: Monthly Billing | Q36: 45994 | R36: 46001 | S36: Outstanding | T36: INV-031225091936 | U36: Yes | V36: No | W36: No response from the client post reminder sent | Y36: =VLOOKUP(T36,'[1]Query result'!$J:$K,2,0) -> 46001 | Z36: =VLOOKUP(T36,'[1]Query result'!$J:$W,14,0) -> 0 | AA36: =K36-Z36 -> 500 | AB36: =VLOOKUP(T36,'[2]Query result'!$F:$G,2,0) -> Outstanding
A37: Masspay | B37: GLOBAL ROOTS INC | C37: =VLOOKUP(B37,Validation!A:B,2,0) -> USA | D37: =VLOOKUP(B37,Validation!A:D,4,0) -> Eduardo Avallone | E37: =VLOOKUP(B37,Validation!A:E,5,0) -> NA | F37: Active | G37: =YEAR(L37) -> 2025 | H37: Bank Transfer | I37: USD | J37: =VLOOKUP(I37,'XE rates'!A:D,4,0)*K37 -> 2217.6 | K37: 2217.6 | L37: 45992 | M37: =TEXT(L37,"mmm") -> Dec | N37: =$Y$1-R37 -> 67 | O37: =IF(N37<=30, "0-30 days", IF(N37<=60, "31-60 days", IF(N37<=90, "61-90 days", "Over 90+ days"))) -> 61-90 days | P37: Monthly Billing | Q37: 46024 | R37: 46039 | S37: Invoice Sent | T37: US-GLOBAL ROOTS INC-12/2025 | U37: Yes | V37: No | W37: No response from the client post reminder sent | Y37: =VLOOKUP(T37,'[1]Query result'!$J:$K,2,0) -> 46039 | AB37: =VLOOKUP(T37,'[2]Query result'!$F:$G,2,0) -> Overdue
A38: Masspay | B38: PT PELITA TRANSFER NUSANTARA | C38: =VLOOKUP(B38,Validation!A:B,2,0) -> APAC | D38: =VLOOKUP(B38,Validation!A:D,4,0) -> Luciana | E38: =VLOOKUP(B38,Validation!A:E,5,0) -> NA | F38: Active | G38: =YEAR(L38) -> 2025 | H38: Bank Transfer | I38: IDR | J38: =VLOOKUP(I38,'XE rates'!A:D,4,0)*K38 -> 5.6508548 | K38: 95444 | L38: 45992 | M38: =TEXT(L38,"mmm") -> Dec | N38: =$Y$1-R38 -> 67 | O38: =IF(N38<=30, "0-30 days", IF(N38<=60, "31-60 days", IF(N38<=90, "61-90 days", "Over 90+ days"))) -> 61-90 days | P38: Monthly Billing | Q38: 46024 | R38: 46039 | S38: Invoice Sent | T38: ID-ptpelita-12/2025 | U38: Yes | V38: No | W38: No response from the client post reminder sent | Y38: =VLOOKUP(T38,'[1]Query result'!$J:$K,2,0) -> 46039 | Z38: =VLOOKUP(T38,'[1]Query result'!$J:$W,14,0) -> 0 | AA38: =K38-Z38 -> 95444 | AB38: =VLOOKUP(T38,'[2]Query result'!$F:$G,2,0) -> Overdue
A39: Masspay | B39: TClub Inc. | C39: =VLOOKUP(B39,Validation!A:B,2,0) -> USA | D39: =VLOOKUP(B39,Validation!A:D,4,0) -> Tanu Arora | E39: =VLOOKUP(B39,Validation!A:E,5,0) -> NA | F39: Active | G39: =YEAR(L39) -> 2025 | H39: Bank Transfer | I39: USD | J39: =VLOOKUP(I39,'XE rates'!A:D,4,0)*K39 -> 1.5 | K39: 1.5 | L39: 45992 | M39: =TEXT(L39,"mmm") -> Dec | N39: =$Y$1-R39 -> 74 | O39: =IF(N39<=30, "0-30 days", IF(N39<=60, "31-60 days", IF(N39<=90, "61-90 days", "Over 90+ days"))) -> 61-90 days | P39: Monthly Billing | Q39: 46025 | R39: 46032 | S39: Overdue | T39: US-TClub Inc.-12/2025 | U39: Yes | V39: No | W39: No response from the client post reminder sent | Y39: =VLOOKUP(T39,'[1]Query result'!$J:$K,2,0) -> 46032 | Z39: =VLOOKUP(T39,'[1]Query result'!$J:$W,14,0) -> 0 | AA39: =K39-Z39 -> 1.5 | AB39: =VLOOKUP(T39,'[2]Query result'!$F:$G,2,0) -> Overdue
A40: N1 | B40: Azimo Limited. | C40: =VLOOKUP(B40,Validation!A:B,2,0) -> EU/UK | D40: =VLOOKUP(B40,Validation!A:D,4,0) -> Sachli Zare | E40: =VLOOKUP(B40,Validation!A:E,5,0) -> Gitesh Athavale | F40: Active | G40: =YEAR(L40) -> 2025 | H40: Bank Transfer | I40: GBP | J40: =VLOOKUP(I40,'XE rates'!A:D,4,0)*K40 -> 29.961888 | K40: 22.41 | L40: 45992 | M40: =TEXT(L40,"mmm") -> Dec | N40: =$Y$1-R40 -> 52 | O40: =IF(N40<=30, "0-30 days", IF(N40<=60, "31-60 days", IF(N40<=90, "61-90 days", "Over 90+ days"))) -> 31-60 days | P40: Monthly Billing | Q40: 46024 | R40: 46054 | S40: Invoice Sent | T40: INV-020126135021 | U40: Yes | V40: No | W40: No response from the client post reminder sent | Y40: =VLOOKUP(T40,'[1]Query result'!$J:$K,2,0) -> 46054 | Z40: =VLOOKUP(T40,'[1]Query result'!$J:$W,14,0) -> 0 | AA40: =K40-Z40 -> 22.41 | AB40: =VLOOKUP(T40,'[2]Query result'!$F:$G,2,0) -> Outstanding
A41: N1 | B41: Budgetly Pty Ltd | C41: =VLOOKUP(B41,Validation!A:B,2,0) -> APAC | D41: =VLOOKUP(B41,Validation!A:D,4,0) -> Hao Nguyen | E41: =VLOOKUP(B41,Validation!A:E,5,0) -> Vinoth M | F41: Active | G41: =YEAR(L41) -> 2025 | H41: Bank Transfer | I41: AUD | J41: =VLOOKUP(I41,'XE rates'!A:D,4,0)*K41 -> 795.00528 | K41: 1187.518 | L41: 45992 | M41: =TEXT(L41,"mmm") -> Dec | N41: =$Y$1-R41 -> 48 | O41: =IF(N41<=30, "0-30 days", IF(N41<=60, "31-60 days", IF(N41<=90, "61-90 days", "Over 90+ days"))) -> 31-60 days | P41: Monthly Billing | Q41: 46028 | R41: 46058 | S41: Invoice Sent | T41: INV-060126122618 | U41: Yes | V41: No | W41: Card printing invoice pending | Y41: =VLOOKUP(T41,'[1]Query result'!$J:$K,2,0) -> 46058 | Z41: =VLOOKUP(T41,'[1]Query result'!$J:$W,14,0) -> 0 | AA41: =K41-Z41 -> 1187.518 | AB41: =VLOOKUP(T41,'[2]Query result'!$F:$G,2,0) -> Outstanding
A42: N1 | B42: FIRSTKYC PTE. LTD. | C42: =VLOOKUP(B42,Validation!A:B,2,0) -> APAC | D42: =VLOOKUP(B42,Validation!A:D,4,0) -> NA | E42: =VLOOKUP(B42,Validation!A:E,5,0) -> Denis Tan | F42: Active | G42: =YEAR(L42) -> 2025 | H42: Bank Transfer | I42: USD | J42: =VLOOKUP(I42,'XE rates'!A:D,4,0)*K42 -> 1.72 | K42: 1.72 | L42: 45992 | M42: =TEXT(L42,"mmm") -> Dec | N42: =$Y$1-R42 -> 72 | O42: =IF(N42<=30, "0-30 days", IF(N42<=60, "31-60 days", IF(N42<=90, "61-90 days", "Over 90+ days"))) -> 61-90 days | P42: Monthly Billing | Q42: 46027 | R42: 46034 | S42: Outstanding | T42: INV-050126095427 | U42: Yes | V42: No | W42: Client will settle once lumpsum threshold achieved | Y42: =VLOOKUP(T42,'[1]Query result'!$J:$K,2,0) -> 46034 | Z42: =VLOOKUP(T42,'[1]Query result'!$J:$W,14,0) -> 0 | AA42: =K42-Z42 -> 1.72 | AB42: =VLOOKUP(T42,'[2]Query result'!$F:$G,2,0) -> Outstanding
A43: N1 | B43: goLance, Inc. | C43: =VLOOKUP(B43,Validation!A:B,2,0) -> USA | D43: =VLOOKUP(B43,Validation!A:D,4,0) -> Eduardo Avallone | E43: =VLOOKUP(B43,Validation!A:E,5,0) -> Greg McAllister | F43: Active | G43: =YEAR(L43) -> 2025 | H43: Bank Transfer | I43: USD | J43: =VLOOKUP(I43,'XE rates'!A:D,4,0)*K43 -> 100 | K43: 100 | L43: 45992 | M43: =TEXT(L43,"mmm") -> Dec | N43: =$Y$1-R43 -> 75 | O43: =IF(N43<=30, "0-30 days", IF(N43<=60, "31-60 days", IF(N43<=90, "61-90 days", "Over 90+ days"))) -> 61-90 days | P43: Monthly Billing | Q43: 46024 | R43: 46031 | S43: Outstanding | T43: INV-020126171358 | U43: Yes | V43: No | W43: No response from the client post reminder sent | Y43: =VLOOKUP(T43,'[1]Query result'!$J:$K,2,0) -> 46031 | Z43: =VLOOKUP(T43,'[1]Query result'!$J:$W,14,0) -> 0 | AA43: =K43-Z43 -> 100 | AB43: =VLOOKUP(T43,'[2]Query result'!$F:$G,2,0) -> Outstanding
A44: N1 | B44: iPiD Europe B.V. | C44: =VLOOKUP(B44,Validation!A:B,2,0) -> APAC | D44: =VLOOKUP(B44,Validation!A:D,4,0) -> NA | E44: =VLOOKUP(B44,Validation!A:E,5,0) -> Febriali Tan | F44: Active | G44: =YEAR(L44) -> 2025 | H44: Bank Transfer | I44: USD | J44: =VLOOKUP(I44,'XE rates'!A:D,4,0)*K44 -> 2000 | K44: 2000 | L44: 45992 | M44: =TEXT(L44,"mmm") -> Dec | N44: =$Y$1-R44 -> 71 | O44: =IF(N44<=30, "0-30 days", IF(N44<=60, "31-60 days", IF(N44<=90, "61-90 days", "Over 90+ days"))) -> 61-90 days | P44: Monthly Billing | Q44: 46028 | R44: 46035 | S44: Outstanding | T44: INV-060126114015 | U44: Yes | V44: No | W44: No response from the client post reminder sent | Y44: =VLOOKUP(T44,'[1]Query result'!$J:$K,2,0) -> 46035 | Z44: =VLOOKUP(T44,'[1]Query result'!$J:$W,14,0) -> 0 | AA44: =K44-Z44 -> 2000 | AB44: =VLOOKUP(T44,'[2]Query result'!$F:$G,2,0) -> Outstanding
A45: N1 | B45: Istanbul Ödeme ve Elektronik Para A.S | C45: =VLOOKUP(B45,Validation!A:B,2,0) -> ME | D45: =VLOOKUP(B45,Validation!A:D,4,0) -> Jerome Coelho | E45: =VLOOKUP(B45,Validation!A:E,5,0) -> Ashraf Omran | F45: Active | G45: =YEAR(L45) -> 2025 | H45: Bank Transfer | I45: USD | J45: =VLOOKUP(I45,'XE rates'!A:D,4,0)*K45 -> 2500 | K45: 2500 | L45: 45992 | M45: =TEXT(L45,"mmm") -> Dec | N45: =$Y$1-R45 -> 72 | O45: =IF(N45<=30, "0-30 days", IF(N45<=60, "31-60 days", IF(N45<=90, "61-90 days", "Over 90+ days"))) -> 61-90 days | P45: Monthly Billing | Q45: 46027 | R45: 46034 | S45: Force Settlement | T45: INV-050126150313 | U45: Yes | V45: No | W45: No response from the client post reminder sent | Y45: =VLOOKUP(T45,'[1]Query result'!$J:$K,2,0) -> 46034 | Z45: =VLOOKUP(T45,'[1]Query result'!$J:$W,14,0) -> 0 | AA45: =K45-Z45 -> 2500 | AB45: =VLOOKUP(T45,'[2]Query result'!$F:$G,2,0) -> Force Settlement
A46: N1 | B46: JPMORGAN CHASE BANK | C46: =VLOOKUP(B46,Validation!A:B,2,0) -> EU/UK | D46: =VLOOKUP(B46,Validation!A:D,4,0) -> Sachli Zare | E46: =VLOOKUP(B46,Validation!A:E,5,0) -> NA | F46: Active | G46: =YEAR(L46) -> 2025 | H46: Bank Transfer | I46: USD | J46: =VLOOKUP(I46,'XE rates'!A:D,4,0)*K46 -> 2.5 | K46: 2.5 | L46: 45992 | M46: =TEXT(L46,"mmm") -> Dec | N46: =$Y$1-R46 -> 72 | O46: =IF(N46<=30, "0-30 days", IF(N46<=60, "31-60 days", IF(N46<=90, "61-90 days", "Over 90+ days"))) -> 61-90 days | P46: Monthly Billing | Q46: 46027 | R46: 46034 | S46: Outstanding | T46: INV-050126184308 | U46: Yes | V46: No | W46: Partially settled by the client | Y46: =VLOOKUP(T46,'[1]Query result'!$J:$K,2,0) -> 46034 | Z46: =VLOOKUP(T46,'[1]Query result'!$J:$W,14,0) -> 0 | AA46: =K46-Z46 -> 2.5 | AB46: =VLOOKUP(T46,'[2]Query result'!$F:$G,2,0) -> Outstanding
A47: N1 | B47: Loadpass LTDA | C47: =VLOOKUP(B47,Validation!A:B,2,0) -> USA | D47: =VLOOKUP(B47,Validation!A:D,4,0) -> Eduardo Avallone | E47: =VLOOKUP(B47,Validation!A:E,5,0) -> Christina Hutchinson | F47: Active | G47: =YEAR(L47) -> 2025 | H47: Bank Transfer | I47: USD | J47: =VLOOKUP(I47,'XE rates'!A:D,4,0)*K47 -> 1659.62 | K47: 1659.62 | L47: 45992 | M47: =TEXT(L47,"mmm") -> Dec | N47: =$Y$1-R47 -> 72 | O47: =IF(N47<=30, "0-30 days", IF(N47<=60, "31-60 days", IF(N47<=90, "61-90 days", "Over 90+ days"))) -> 61-90 days | P47: Monthly Billing | Q47: 46027 | R47: 46034 | S47: Outstanding | T47: INV-050126153219 | U47: Yes | V47: No | W47: AM is chasing the client to clear all o/s invoices | Y47: =VLOOKUP(T47,'[1]Query result'!$J:$K,2,0) -> 46034 | Z47: =VLOOKUP(T47,'[1]Query result'!$J:$W,14,0) -> 0 | AA47: =K47-Z47 -> 1659.62 | AB47: =VLOOKUP(T47,'[2]Query result'!$F:$G,2,0) -> Outstanding
A48: N1 | B48: MULTIPLIER TECHNOLOGIES PTE. LTD | C48: =VLOOKUP(B48,Validation!A:B,2,0) -> APAC | D48: =VLOOKUP(B48,Validation!A:D,4,0) -> Shi Yin | E48: =VLOOKUP(B48,Validation!A:E,5,0) -> Vinoth M | F48: Active | G48: =YEAR(L48) -> 2025 | H48: Bank Transfer | I48: USD | J48: =VLOOKUP(I48,'XE rates'!A:D,4,0)*K48 -> 2034 | K48: 2034 | L48: 45992 | M48: =TEXT(L48,"mmm") -> Dec | N48: =$Y$1-R48 -> 72 | O48: =IF(N48<=30, "0-30 days", IF(N48<=60, "31-60 days", IF(N48<=90, "61-90 days", "Over 90+ days"))) -> 61-90 days | P48: Monthly Billing | Q48: 46027 | R48: 46034 | S48: Outstanding | T48: INV-050126154823 | U48: Yes | V48: No | W48: No response from the client post reminder sent | Y48: =VLOOKUP(T48,'[1]Query result'!$J:$K,2,0) -> 46034 | Z48: =VLOOKUP(T48,'[1]Query result'!$J:$W,14,0) -> 0 | AA48: =K48-Z48 -> 2034 | AB48: =VLOOKUP(T48,'[2]Query result'!$F:$G,2,0) -> Outstanding
A49: N1 | B49: Yondr Money Pty Ltd | C49: =VLOOKUP(B49,Validation!A:B,2,0) -> APAC | D49: =VLOOKUP(B49,Validation!A:D,4,0) -> Hao Nguyen | E49: =VLOOKUP(B49,Validation!A:E,5,0) -> NA | F49: Active | G49: =YEAR(L49) -> 2025 | H49: Bank Transfer | I49: AUD | J49: =VLOOKUP(I49,'XE rates'!A:D,4,0)*K49 -> 4550.0559 | K49: 6796.525 | L49: 45992 | M49: =TEXT(L49,"mmm") -> Dec | N49: =$Y$1-R49 -> 71 | O49: =IF(N49<=30, "0-30 days", IF(N49<=60, "31-60 days", IF(N49<=90, "61-90 days", "Over 90+ days"))) -> 61-90 days | P49: Monthly Billing | Q49: 46028 | R49: 46035 | S49: Outstanding | T49: INV-060126181825 | U49: Yes | V49: Yes | W49: AM to provide an update if invoices needs to be written off as client is suspended | Y49: =VLOOKUP(T49,'[1]Query result'!$J:$K,2,0) -> 46035 | Z49: =VLOOKUP(T49,'[1]Query result'!$J:$W,14,0) -> 0 | AA49: =K49-Z49 -> 6796.525 | AB49: =VLOOKUP(T49,'[2]Query result'!$F:$G,2,0) -> Outstanding
A50: N1 | B50: Zeni, Inc. | C50: =VLOOKUP(B50,Validation!A:B,2,0) -> USA | D50: =VLOOKUP(B50,Validation!A:D,4,0) -> NA | E50: =VLOOKUP(B50,Validation!A:E,5,0) -> Tyler Reed | F50: Active | G50: =YEAR(L50) -> 2025 | H50: Bank Transfer | I50: USD | J50: =VLOOKUP(I50,'XE rates'!A:D,4,0)*K50 -> 550 | K50: 550 | L50: 45992 | M50: =TEXT(L50,"mmm") -> Dec | N50: =$Y$1-R50 -> 74 | O50: =IF(N50<=30, "0-30 days", IF(N50<=60, "31-60 days", IF(N50<=90, "61-90 days", "Over 90+ days"))) -> 61-90 days | P50: Monthly Billing | Q50: 46025 | R50: 46032 | S50: Outstanding | T50: INV-030126111809 | U50: Yes | V50: No | W50: No response from the client post reminder sent | Y50: =VLOOKUP(T50,'[1]Query result'!$J:$K,2,0) -> 46032 | Z50: =VLOOKUP(T50,'[1]Query result'!$J:$W,14,0) -> 0 | AA50: =K50-Z50 -> 550 | AB50: =VLOOKUP(T50,'[2]Query result'!$F:$G,2,0) -> Outstanding
A51: N1 | B51: Budgetly Pty Ltd | C51: =VLOOKUP(B51,Validation!A:B,2,0) -> APAC | D51: =VLOOKUP(B51,Validation!A:D,4,0) -> Hao Nguyen | E51: =VLOOKUP(B51,Validation!A:E,5,0) -> Vinoth M | F51: Active | G51: =YEAR(L51) -> 2025 | H51: Bank Transfer | I51: AUD | J51: =VLOOKUP(I51,'XE rates'!A:D,4,0)*K51 -> 1489.0775 | K51: 2224.27 | L51: 45992 | M51: =TEXT(L51,"mmm") -> Dec | N51: =$Y$1-R51 -> 30 | O51: =IF(N51<=30, "0-30 days", IF(N51<=60, "31-60 days", IF(N51<=90, "61-90 days", "Over 90+ days"))) -> 0-30 days | P51: Card Printing and Delivery | Q51: 46045 | R51: 46076 | S51: Invoice Sent | T51: INV-230126170000 | U51: Yes | V51: No | W51: Card printing invoice pending | AB51: =VLOOKUP(T51,'[2]Query result'!$F:$G,2,0) -> Outstanding
A52: N1 | B52: Pelikin Ventures Pty Ltd | C52: =VLOOKUP(B52,Validation!A:B,2,0) -> APAC | D52: =VLOOKUP(B52,Validation!A:D,4,0) -> Hao Nguyen | E52: =VLOOKUP(B52,Validation!A:E,5,0) -> Vinoth M | F52: Active | G52: =YEAR(L52) -> 2025 | H52: Bank Transfer | I52: AUD | J52: =VLOOKUP(I52,'XE rates'!A:D,4,0)*K52 -> 137.82337 | K52: 205.87 | L52: 45992 | M52: =TEXT(L52,"mmm") -> Dec | N52: =$Y$1-R52 -> 30 | O52: =IF(N52<=30, "0-30 days", IF(N52<=60, "31-60 days", IF(N52<=90, "61-90 days", "Over 90+ days"))) -> 0-30 days | P52: Card Printing and Delivery | Q52: 46045 | R52: 46076 | S52: Invoice Sent | T52: INV-230126143000 | U52: No | V52: No | W52: No response from the client post reminder sent | AB52: =VLOOKUP(T52,'[2]Query result'!$F:$G,2,0) -> Outstanding
A53: Masspay | B53: Everpro Holdings Limited | C53: =VLOOKUP(B53,Validation!A:B,2,0) -> APAC | D53: =VLOOKUP(B53,Validation!A:D,4,0) -> NA | E53: =VLOOKUP(B53,Validation!A:E,5,0) -> Lisa Sung | F53: Active | G53: =YEAR(L53) -> 2026 | H53: Bank Transfer | I53: USD | J53: =VLOOKUP(I53,'XE rates'!A:D,4,0)*K53 -> 5000 | K53: 5000 | L53: 46023 | M53: =TEXT(L53,"mmm") -> Jan | N53: =$Y$1-R53 -> 44 | O53: =IF(N53<=30, "0-30 days", IF(N53<=60, "31-60 days", IF(N53<=90, "61-90 days", "Over 90+ days"))) -> 31-60 days | P53: Monthly Billing | Q53: 46055 | R53: 46062 | S53: Overdue | T53: HK-Everpro-01/2026 | U53: Yes | V53: No | W53: No response from the client post reminder sent | AB53: =VLOOKUP(T53,'[2]Query result'!$F:$G,2,0) -> Overdue
A54: Masspay | B54: GLOBAL ROOTS INC | C54: =VLOOKUP(B54,Validation!A:B,2,0) -> USA | D54: =VLOOKUP(B54,Validation!A:D,4,0) -> Eduardo Avallone | E54: =VLOOKUP(B54,Validation!A:E,5,0) -> NA | F54: Active | G54: =YEAR(L54) -> 2026 | H54: Bank Transfer | I54: USD | J54: =VLOOKUP(I54,'XE rates'!A:D,4,0)*K54 -> 1371.03 | K54: 1371.03 | L54: 46023 | M54: =TEXT(L54,"mmm") -> Jan | N54: =$Y$1-R54 -> 36 | O54: =IF(N54<=30, "0-30 days", IF(N54<=60, "31-60 days", IF(N54<=90, "61-90 days", "Over 90+ days"))) -> 31-60 days | P54: Monthly Billing | Q54: 46055 | R54: 46070 | S54: Overdue | T54: US-GLOBAL ROOTS INC-01/2026 | U54: Yes | V54: No | W54: No response from the client post reminder sent | AB54: =VLOOKUP(T54,'[2]Query result'!$F:$G,2,0) -> Overdue
A55: Masspay | B55: lemonway | C55: =VLOOKUP(B55,Validation!A:B,2,0) -> EU/UK | D55: =VLOOKUP(B55,Validation!A:D,4,0) -> Unmanaged - Harshita or saloni | E55: =VLOOKUP(B55,Validation!A:E,5,0) -> NA | F55: Active | G55: =YEAR(L55) -> 2026 | H55: Bank Transfer | I55: EUR | J55: =VLOOKUP(I55,'XE rates'!A:D,4,0)*K55 -> 1325.4862 | K55: 1144.33 | L55: 46023 | M55: =TEXT(L55,"mmm") -> Jan | N55: =$Y$1-R55 -> 46 | O55: =IF(N55<=30, "0-30 days", IF(N55<=60, "31-60 days", IF(N55<=90, "61-90 days", "Over 90+ days"))) -> 31-60 days | P55: Monthly Billing | Q55: 46056 | R55: 46060 | S55: Overdue | T55: SG-Lemonway-01/2026 | U55: Yes | V55: No | W55: No response from the client post reminder sent | AB55: =VLOOKUP(T55,'[2]Query result'!$F:$G,2,0) -> Overdue
A56: Masspay | B56: PT Midtrans | C56: =VLOOKUP(B56,Validation!A:B,2,0) -> APAC | D56: =VLOOKUP(B56,Validation!A:D,4,0) -> Hao Nguyen | E56: =VLOOKUP(B56,Validation!A:E,5,0) -> Hari Budiman | F56: Active | G56: =YEAR(L56) -> 2026 | H56: Bank Transfer | I56: IDR | J56: =VLOOKUP(I56,'XE rates'!A:D,4,0)*K56 -> 356.96163 | K56: 6029149 | L56: 46023 | M56: =TEXT(L56,"mmm") -> Jan | N56: =$Y$1-R56 -> 21 | O56: =IF(N56<=30, "0-30 days", IF(N56<=60, "31-60 days", IF(N56<=90, "61-90 days", "Over 90+ days"))) -> 0-30 days | P56: Monthly Billing | Q56: 46055 | R56: 46085 | S56: Invoice Sent | T56: ID-PT Midtrans-01/2026 | U56: Yes | V56: No | W56: No response from the client post reminder sent | AB56: =VLOOKUP(T56,'[2]Query result'!$F:$G,2,0) -> Overdue
A57: Masspay | B57: TClub Inc. | C57: =VLOOKUP(B57,Validation!A:B,2,0) -> USA | D57: =VLOOKUP(B57,Validation!A:D,4,0) -> Tanu Arora | E57: =VLOOKUP(B57,Validation!A:E,5,0) -> NA | F57: Active | G57: =YEAR(L57) -> 2026 | H57: Bank Transfer | I57: USD | J57: =VLOOKUP(I57,'XE rates'!A:D,4,0)*K57 -> 5.5 | K57: 5.5 | L57: 46023 | M57: =TEXT(L57,"mmm") -> Jan | N57: =$Y$1-R57 -> 46 | O57: =IF(N57<=30, "0-30 days", IF(N57<=60, "31-60 days", IF(N57<=90, "61-90 days", "Over 90+ days"))) -> 31-60 days | P57: Monthly Billing | Q57: 46055 | R57: 46060 | S57: Overdue | T57: US-TClub Inc.-01/2026 | U57: Yes | V57: No | W57: No response from the client post reminder sent | AB57: =VLOOKUP(T57,'[2]Query result'!$F:$G,2,0) -> Overdue
A58: N1 | B58: Azimo Limited. | C58: =VLOOKUP(B58,Validation!A:B,2,0) -> EU/UK | D58: =VLOOKUP(B58,Validation!A:D,4,0) -> Sachli Zare | E58: =VLOOKUP(B58,Validation!A:E,5,0) -> Gitesh Athavale | F58: Active | G58: =YEAR(L58) -> 2026 | H58: Bank Transfer | I58: GBP | J58: =VLOOKUP(I58,'XE rates'!A:D,4,0)*K58 -> 117.30728 | K58: 87.74 | L58: 46023 | M58: =TEXT(L58,"mmm") -> Jan | N58: =$Y$1-R58 -> 23 | O58: =IF(N58<=30, "0-30 days", IF(N58<=60, "31-60 days", IF(N58<=90, "61-90 days", "Over 90+ days"))) -> 0-30 days | P58: Monthly Billing | Q58: 46055 | R58: 46083 | S58: Invoice Sent | T58: INV-020226153711 | U58: Yes | V58: No | W58: No response from the client post reminder sent | AB58: =VLOOKUP(T58,'[2]Query result'!$F:$G,2,0) -> Outstanding
A59: N1 | B59: Budgetly Pty Ltd | C59: =VLOOKUP(B59,Validation!A:B,2,0) -> APAC | D59: =VLOOKUP(B59,Validation!A:D,4,0) -> Hao Nguyen | E59: =VLOOKUP(B59,Validation!A:E,5,0) -> Vinoth M | F59: Active | G59: =YEAR(L59) -> 2026 | H59: Bank Transfer | I59: AUD | J59: =VLOOKUP(I59,'XE rates'!A:D,4,0)*K59 -> 3566.4963 | K59: 5327.359 | L59: 46023 | M59: =TEXT(L59,"mmm") -> Jan | N59: =$Y$1-R59 -> 39 | O59: =IF(N59<=30, "0-30 days", IF(N59<=60, "31-60 days", IF(N59<=90, "61-90 days", "Over 90+ days"))) -> 31-60 days | P59: Monthly Billing | Q59: 46060 | R59: 46067 | S59: Outstanding | T59: INV-070226133026 | U59: Yes | V59: No | W59: Card printing invoice pending | AB59: =VLOOKUP(T59,'[2]Query result'!$F:$G,2,0) -> Outstanding
A60: N1 | B60: CashD Pty Ltd | C60: =VLOOKUP(B60,Validation!A:B,2,0) -> APAC | D60: =VLOOKUP(B60,Validation!A:D,4,0) -> NA | E60: =VLOOKUP(B60,Validation!A:E,5,0) -> Vinoth M | F60: Active | G60: =YEAR(L60) -> 2026 | H60: Bank Transfer | I60: AUD | J60: =VLOOKUP(I60,'XE rates'!A:D,4,0)*K60 -> 2105.4768 | K60: 3145 | L60: 46023 | M60: =TEXT(L60,"mmm") -> Jan | N60: =$Y$1-R60 -> 42 | O60: =IF(N60<=30, "0-30 days", IF(N60<=60, "31-60 days", IF(N60<=90, "61-90 days", "Over 90+ days"))) -> 31-60 days | P60: Monthly Billing | Q60: 46057 | R60: 46064 | S60: Outstanding | T60: INV-040226191953 | U60: Yes | V60: No | W60: No response from the client post reminder sent | AB60: =VLOOKUP(T60,'[2]Query result'!$F:$G,2,0) -> Outstanding
A61: N1 | B61: Express Hub Services Pty Ltd | C61: =VLOOKUP(B61,Validation!A:B,2,0) -> APAC | D61: =VLOOKUP(B61,Validation!A:D,4,0) -> NA | E61: =VLOOKUP(B61,Validation!A:E,5,0) -> Wendy zhai | F61: Active | G61: =YEAR(L61) -> 2026 | H61: Bank Transfer | I61: AUD | J61: =VLOOKUP(I61,'XE rates'!A:D,4,0)*K61 -> 6666.8032 | K61: 9958.36 | L61: 46023 | M61: =TEXT(L61,"mmm") -> Jan | N61: =$Y$1-R61 -> 40 | O61: =IF(N61<=30, "0-30 days", IF(N61<=60, "31-60 days", IF(N61<=90, "61-90 days", "Over 90+ days"))) -> 31-60 days | P61: Monthly Billing | Q61: 46059 | R61: 46066 | S61: Outstanding | T61: INV-060226135736 | U61: Yes | V61: No | W61: No response from the client post reminder sent | AB61: =VLOOKUP(T61,'[2]Query result'!$F:$G,2,0) -> Outstanding
A62: N1 | B62: FIRSTKYC PTE. LTD. | C62: =VLOOKUP(B62,Validation!A:B,2,0) -> APAC | D62: =VLOOKUP(B62,Validation!A:D,4,0) -> NA | E62: =VLOOKUP(B62,Validation!A:E,5,0) -> Denis Tan | F62: Active | G62: =YEAR(L62) -> 2026 | H62: Bank Transfer | I62: USD | J62: =VLOOKUP(I62,'XE rates'!A:D,4,0)*K62 -> 14.19 | K62: 14.19 | L62: 46023 | M62: =TEXT(L62,"mmm") -> Jan | N62: =$Y$1-R62 -> 40 | O62: =IF(N62<=30, "0-30 days", IF(N62<=60, "31-60 days", IF(N62<=90, "61-90 days", "Over 90+ days"))) -> 31-60 days | P62: Monthly Billing | Q62: 46059 | R62: 46066 | S62: Outstanding | T62: INV-060226120820 | U62: Yes | V62: No | W62: Client will settle once lumpsum threshold achieved | AB62: =VLOOKUP(T62,'[2]Query result'!$F:$G,2,0) -> Outstanding
... A75: N1 | B75: Budgetly Pty Ltd | C75: =VLOOKUP(B75,Validation!A:B,2,0) -> APAC | D75: =VLOOKUP(B75,Validation!A:D,4,0) -> Hao Nguyen | E75: =VLOOKUP(B75,Validation!A:E,5,0) -> Vinoth M | F75: Active | G75: =YEAR(L75) -> 2026 | H75: Bank Transfer | I75: AUD | J75: =VLOOKUP(I75,'XE rates'!A:D,4,0)*K75 -> 37.168862 | K75: 55.52 | L75: 46023 | M75: =TEXT(L75,"mmm") -> Jan | N75: =$Y$1-R75 -> 5 | O75: =IF(N75<=30, "0-30 days", IF(N75<=60, "31-60 days", IF(N75<=90, "61-90 days", "Over 90+ days"))) -> 0-30 days | P75: Card Printing and Delivery | Q75: 46073 | R75: 46101 | S75: Invoice Sent | T75: INV-200226170000 | U75: Yes | V75: No | W75: Card printing invoice pending | AB75: =VLOOKUP(T75,'[2]Query result'!$F:$G,2,0) -> Outstanding
A76: Masspay | B76: Banco Topazio (Beetech) | C76: =VLOOKUP(B76,Validation!A:B,2,0) -> USA | D76: =VLOOKUP(B76,Validation!A:D,4,0) -> Eduardo Avallone | E76: =VLOOKUP(B76,Validation!A:E,5,0) -> NA | F76: Active | G76: =YEAR(L76) -> 2026 | H76: Bank Transfer | I76: USD | J76: =VLOOKUP(I76,'XE rates'!A:D,4,0)*K76 -> 8074.55 | K76: 8074.55 | L76: Feb/2026 | M76: =TEXT(L76,"mmm") -> Feb | N76: =$Y$1-R76 -> 16 | O76: =IF(N76<=30, "0-30 days", IF(N76<=60, "31-60 days", IF(N76<=90, "61-90 days", "Over 90+ days"))) -> 0-30 days | P76: Monthly Billing | Q76: 46083 | R76: 46090 | S76: Overdue | T76: SG-Banco Topazio-02/2026 | AB76: =VLOOKUP(T76,'[2]Query result'!$F:$G,2,0) -> Overdue
A77: Masspay | B77: borderless llc | C77: =VLOOKUP(B77,Validation!A:B,2,0) -> USA | D77: =VLOOKUP(B77,Validation!A:D,4,0) -> Lia Susin | E77: =VLOOKUP(B77,Validation!A:E,5,0) -> NA | F77: Active | G77: =YEAR(L77) -> 2026 | H77: Bank Transfer | I77: USD | J77: =VLOOKUP(I77,'XE rates'!A:D,4,0)*K77 -> -322.54 | K77: -322.54 | L77: Feb-2026 | M77: =TEXT(L77,"mmm") -> Feb | N77: =$Y$1-R77 -> 6 | O77: =IF(N77<=30, "0-30 days", IF(N77<=60, "31-60 days", IF(N77<=90, "61-90 days", "Over 90+ days"))) -> 0-30 days | P77: Credit Note-Rebate | Q77: 46093 | R77: 46100 | S77: Invoice Sent | T77: US-CN-Borderless-02-2026 | AB77: =VLOOKUP(T77,'[2]Query result'!$F:$G,2,0) -> Invoice Sent
A78: Masspay | B78: Corporate Alliance Payments Pty Ltd - NSP | C78: =VLOOKUP(B78,Validation!A:B,2,0) -> APAC | D78: =VLOOKUP(B78,Validation!A:D,4,0) -> Hao Nguyen | E78: =VLOOKUP(B78,Validation!A:E,5,0) -> Vinoth M | F78: Active | G78: =YEAR(L78) -> 2026 | H78: Bank Transfer | I78: AUD | J78: =VLOOKUP(I78,'XE rates'!A:D,4,0)*K78 -> 1431.4899 | K78: 2138.25 | L78: Feb/2026 | M78: =TEXT(L78,"mmm") -> Feb | N78: =$Y$1-R78 -> 15 | O78: =IF(N78<=30, "0-30 days", IF(N78<=60, "31-60 days", IF(N78<=90, "61-90 days", "Over 90+ days"))) -> 0-30 days | P78: Monthly Billing | Q78: 46084 | R78: 46091 | S78: Overdue | T78: AU-CorporateAlliance-02/2026 | AB78: =VLOOKUP(T78,'[2]Query result'!$F:$G,2,0) -> Overdue
A79: Masspay | B79: ebury mass payments | C79: =VLOOKUP(B79,Validation!A:B,2,0) -> EU/UK | D79: =VLOOKUP(B79,Validation!A:D,4,0) -> Margarita | E79: =VLOOKUP(B79,Validation!A:E,5,0) -> NA | F79: Active | G79: =YEAR(L79) -> 2026 | H79: Bank Transfer | I79: USD | J79: =VLOOKUP(I79,'XE rates'!A:D,4,0)*K79 -> 689 | K79: 689 | L79: Feb/2026 | M79: =TEXT(L79,"mmm") -> Feb | N79: =$Y$1-R79 -> 18 | O79: =IF(N79<=30, "0-30 days", IF(N79<=60, "31-60 days", IF(N79<=90, "61-90 days", "Over 90+ days"))) -> 0-30 days | P79: Monthly Billing | Q79: 46083 | R79: 46088 | S79: Overdue | T79: SG-eburymass-02/2026 | AB79: =VLOOKUP(T79,'[2]Query result'!$F:$G,2,0) -> Overdue
A80: Masspay | B80: EBURY PARTNERS UK LIMITED | C80: =VLOOKUP(B80,Validation!A:B,2,0) -> EU/UK | D80: =VLOOKUP(B80,Validation!A:D,4,0) -> Margarita | E80: =VLOOKUP(B80,Validation!A:E,5,0) -> NA | F80: Active | G80: =YEAR(L80) -> 2026 | H80: Bank Transfer | I80: USD | J80: =VLOOKUP(I80,'XE rates'!A:D,4,0)*K80 -> -7567.54 | K80: -7567.54 | L80: Feb-2026 | M80: =TEXT(L80,"mmm") -> Feb | N80: =$Y$1-R80 -> 15 | O80: =IF(N80<=30, "0-30 days", IF(N80<=60, "31-60 days", IF(N80<=90, "61-90 days", "Over 90+ days"))) -> 0-30 days | P80: Credit Note-Rebate | Q80: 46084 | R80: 46091 | S80: Overdue | T80: SG-CN-EburyPartUKLtd-02-2026 | U80: Yes | AB80: =VLOOKUP(T80,'[2]Query result'!$F:$G,2,0) -> Overdue
A81: Masspay | B81: EBURY PARTNERS UK LIMITED | C81: =VLOOKUP(B81,Validation!A:B,2,0) -> EU/UK | D81: =VLOOKUP(B81,Validation!A:D,4,0) -> Margarita | E81: =VLOOKUP(B81,Validation!A:E,5,0) -> NA | F81: Active | G81: =YEAR(L81) -> 2026 | H81: Bank Transfer | I81: USD | J81: =VLOOKUP(I81,'XE rates'!A:D,4,0)*K81 -> 2317.74 | K81: 2317.74 | L81: Feb/2026 | M81: =TEXT(L81,"mmm") -> Feb | N81: =$Y$1-R81 -> 18 | O81: =IF(N81<=30, "0-30 days", IF(N81<=60, "31-60 days", IF(N81<=90, "61-90 days", "Over 90+ days"))) -> 0-30 days | P81: Monthly Billing | Q81: 46084 | R81: 46088 | S81: Overdue | T81: SG-EburyPartUKLtd-02/2026 | U81: Yes | AB81: =VLOOKUP(T81,'[2]Query result'!$F:$G,2,0) -> Overdue
A82: Masspay | B82: Everpro Holdings Limited | C82: =VLOOKUP(B82,Validation!A:B,2,0) -> APAC | D82: =VLOOKUP(B82,Validation!A:D,4,0) -> NA | E82: =VLOOKUP(B82,Validation!A:E,5,0) -> Lisa Sung | F82: Active | G82: =YEAR(L82) -> 2026 | H82: Bank Transfer | I82: USD | J82: =VLOOKUP(I82,'XE rates'!A:D,4,0)*K82 -> 5000 | K82: 5000 | L82: Feb/2026 | M82: =TEXT(L82,"mmm") -> Feb | N82: =$Y$1-R82 -> 16 | O82: =IF(N82<=30, "0-30 days", IF(N82<=60, "31-60 days", IF(N82<=90, "61-90 days", "Over 90+ days"))) -> 0-30 days | P82: Monthly Billing | Q82: 46083 | R82: 46090 | S82: Overdue | T82: HK-Everpro-02/2026 | U82: Yes | V82: No | W82: No response from the client post reminder sent | AB82: =VLOOKUP(T82,'[2]Query result'!$F:$G,2,0) -> Overdue
A83: Masspay | B83: GLOBAL ROOTS INC | C83: =VLOOKUP(B83,Validation!A:B,2,0) -> USA | D83: =VLOOKUP(B83,Validation!A:D,4,0) -> Eduardo Avallone | E83: =VLOOKUP(B83,Validation!A:E,5,0) -> NA | F83: Active | G83: =YEAR(L83) -> 2026 | H83: Bank Transfer | I83: USD | J83: =VLOOKUP(I83,'XE rates'!A:D,4,0)*K83 -> 1408.4 | K83: 1408.4 | L83: Feb/2026 | M83: =TEXT(L83,"mmm") -> Feb | N83: =$Y$1-R83 -> 7 | O83: =IF(N83<=30, "0-30 days", IF(N83<=60, "31-60 days", IF(N83<=90, "61-90 days", "Over 90+ days"))) -> 0-30 days | P83: Monthly Billing | Q83: 46084 | R83: 46099 | S83: Invoice Sent | T83: US-GLOBAL ROOTS INC-02/2026 | U83: Yes | V83: No | W83: No response from the client post reminder sent | AB83: =VLOOKUP(T83,'[2]Query result'!$F:$G,2,0) -> Overdue
A84: Masspay | B84: kasikorn bank | C84: =VLOOKUP(B84,Validation!A:B,2,0) -> APAC | D84: =VLOOKUP(B84,Validation!A:D,4,0) -> Pat Sarisa | E84: =VLOOKUP(B84,Validation!A:E,5,0) -> NA | F84: Active | G84: =YEAR(L84) -> 2026 | H84: Bank Transfer | I84: USD | J84: =VLOOKUP(I84,'XE rates'!A:D,4,0)*K84 -> 22012 | K84: 22012 | L84: Feb/2026 | M84: =TEXT(L84,"mmm") -> Feb | N84: =$Y$1-R84 -> 15 | O84: =IF(N84<=30, "0-30 days", IF(N84<=60, "31-60 days", IF(N84<=90, "61-90 days", "Over 90+ days"))) -> 0-30 days | P84: Monthly Billing | Q84: 46084 | R84: 46091 | S84: Overdue | T84: SG-KasikornBank-02/2026 | AB84: =VLOOKUP(T84,'[2]Query result'!$F:$G,2,0) -> Overdue
A85: Masspay | B85: lemonway | C85: =VLOOKUP(B85,Validation!A:B,2,0) -> EU/UK | D85: =VLOOKUP(B85,Validation!A:D,4,0) -> Unmanaged - Harshita or saloni | E85: =VLOOKUP(B85,Validation!A:E,5,0) -> NA | F85: Active | G85: =YEAR(L85) -> 2026 | H85: Bank Transfer | I85: EUR | J85: =VLOOKUP(I85,'XE rates'!A:D,4,0)*K85 -> 2001.266 | K85: 1727.75 | L85: Feb/2026 | M85: =TEXT(L85,"mmm") -> Feb | N85: =$Y$1-R85 -> 18 | O85: =IF(N85<=30, "0-30 days", IF(N85<=60, "31-60 days", IF(N85<=90, "61-90 days", "Over 90+ days"))) -> 0-30 days | P85: Monthly Billing | Q85: 46083 | R85: 46088 | S85: Overdue | T85: SG-Lemonway-02/2026 | U85: Yes | V85: No | W85: No response from the client post reminder sent | AB85: =VLOOKUP(T85,'[2]Query result'!$F:$G,2,0) -> Overdue
A86: Masspay | B86: Nuvei Limited | C86: =VLOOKUP(B86,Validation!A:B,2,0) -> APAC | D86: =VLOOKUP(B86,Validation!A:D,4,0) -> XiaoXiao | E86: =VLOOKUP(B86,Validation!A:E,5,0) -> Rohit Bammi | F86: Active | G86: =YEAR(L86) -> 2026 | H86: Bank Transfer | I86: USD | J86: =VLOOKUP(I86,'XE rates'!A:D,4,0)*K86 -> 22670 | K86: 22670 | L86: Feb/2026 | M86: =TEXT(L86,"mmm") -> Feb | N86: =$Y$1-R86 -> 15 | O86: =IF(N86<=30, "0-30 days", IF(N86<=60, "31-60 days", IF(N86<=90, "61-90 days", "Over 90+ days"))) -> 0-30 days | P86: Monthly Billing | Q86: 46084 | R86: 46091 | S86: Overdue | T86: SG-Nuvei-02/2026 | AB86: =VLOOKUP(T86,'[2]Query result'!$F:$G,2,0) -> Overdue
A87: Masspay | B87: PT Harsya Remitindo | C87: =VLOOKUP(B87,Validation!A:B,2,0) -> Shared Centre | D87: =VLOOKUP(B87,Validation!A:D,4,0) -> Sanat Patakar | E87: =VLOOKUP(B87,Validation!A:E,5,0) -> Hari Budiman | F87: Active | G87: =YEAR(L87) -> 2026 | H87: Bank Transfer | I87: USD | J87: =VLOOKUP(I87,'XE rates'!A:D,4,0)*K87 -> 2344.32 | K87: 2344.32 | L87: Feb-2026 | M87: =TEXT(L87,"mmm") -> Feb | N87: =$Y$1-R87 -> 1 | O87: =IF(N87<=30, "0-30 days", IF(N87<=60, "31-60 days", IF(N87<=90, "61-90 days", "Over 90+ days"))) -> 0-30 days | P87: Monthly Billing | Q87: 46084 | R87: 46105 | S87: Invoice Sent | T87: ID-Harsya Remitindo-02/2026 | AB87: =VLOOKUP(T87,'[2]Query result'!$F:$G,2,0) -> Overdue
A88: Masspay | B88: PT Midtrans | C88: =VLOOKUP(B88,Validation!A:B,2,0) -> APAC | D88: =VLOOKUP(B88,Validation!A:D,4,0) -> Hao Nguyen | E88: =VLOOKUP(B88,Validation!A:E,5,0) -> Hari Budiman | F88: Active | G88: =YEAR(L88) -> 2026 | H88: Bank Transfer | I88: IDR | J88: =VLOOKUP(I88,'XE rates'!A:D,4,0)*K88 -> 329.55542 | K88: 5566253 | L88: Feb/2026 | M88: =TEXT(L88,"mmm") -> Feb | N88: =$Y$1-R88 -> -8 | O88: =IF(N88<=30, "0-30 days", IF(N88<=60, "31-60 days", IF(N88<=90, "61-90 days", "Over 90+ days"))) -> 0-30 days | P88: Monthly Billing | Q88: 46084 | R88: 46114 | S88: Invoice Sent | T88: ID-PT Midtrans-02/2026 | U88: No | V88: No | W88: No response from the client post reminder sent | AB88: =VLOOKUP(T88,'[2]Query result'!$F:$G,2,0) -> Invoice Sent
A89: Masspay | B89: PT Transwap Dunamis Indonesia | C89: =VLOOKUP(B89,Validation!A:B,2,0) -> APAC | D89: =VLOOKUP(B89,Validation!A:D,4,0) -> NA | E89: =VLOOKUP(B89,Validation!A:E,5,0) -> Hari Budiman | F89: Active | G89: =YEAR(L89) -> 2026 | H89: Wallet Debit | I89: USD | J89: =VLOOKUP(I89,'XE rates'!A:D,4,0)*K89 -> 109.34 | K89: 109.34 | L89: Feb-2026 | M89: =TEXT(L89,"mmm") -> Feb | N89: =$Y$1-R89 -> 1 | O89: =IF(N89<=30, "0-30 days", IF(N89<=60, "31-60 days", IF(N89<=90, "61-90 days", "Over 90+ days"))) -> 0-30 days | P89: Monthly Billing | Q89: 46084 | R89: 46105 | S89: Invoice Sent | T89: ID-PT Transwap-02/2026 | AB89: =VLOOKUP(T89,'[2]Query result'!$F:$G,2,0) -> Force Settlement
A90: Masspay | B90: The CurrencyCloud Limited | C90: =VLOOKUP(B90,Validation!A:B,2,0) -> APAC | D90: =VLOOKUP(B90,Validation!A:D,4,0) -> XiaoXiao | E90: =VLOOKUP(B90,Validation!A:E,5,0) -> NA | F90: Active | G90: =YEAR(L90) -> 2026 | H90: Bank Transfer | I90: USD | J90: =VLOOKUP(I90,'XE rates'!A:D,4,0)*K90 -> 54089.5 | K90: 54089.5 | L90: Feb/2026 | M90: =TEXT(L90,"mmm") -> Feb | N90: =$Y$1-R90 -> 9 | O90: =IF(N90<=30, "0-30 days", IF(N90<=60, "31-60 days", IF(N90<=90, "61-90 days", "Over 90+ days"))) -> 0-30 days | P90: Monthly Billing | Q90: 46084 | R90: 46097 | S90: Invoice Sent | T90: SG-Currency Cloud-02/2026 | AB90: =VLOOKUP(T90,'[2]Query result'!$F:$G,2,0) -> Overdue
A91: N1 | B91: Abu Sheikha Exchange | C91: =VLOOKUP(B91,Validation!A:B,2,0) -> ME | D91: =VLOOKUP(B91,Validation!A:D,4,0) -> Jerome Coelho | E91: =VLOOKUP(B91,Validation!A:E,5,0) -> Ashraf Omran | F91: Active | G91: =YEAR(L91) -> 2026 | H91: Bank Transfer | I91: USD | J91: =VLOOKUP(I91,'XE rates'!A:D,4,0)*K91 -> 10 | K91: 10 | L91: 2026-02-01 | M91: =TEXT(L91,"mmm") -> Feb | N91: =$Y$1-R91 -> 15 | O91: =IF(N91<=30, "0-30 days", IF(N91<=60, "31-60 days", IF(N91<=90, "61-90 days", "Over 90+ days"))) -> 0-30 days | P91: Monthly Billing | Q91: 46084 | R91: 46091 | S91: Outstanding | T91: INV-030326143016 | AB91: =VLOOKUP(T91,'[2]Query result'!$F:$G,2,0) -> Outstanding
A92: N1 | B92: Al Muzaini Exchange | C92: =VLOOKUP(B92,Validation!A:B,2,0) -> ME | D92: =VLOOKUP(B92,Validation!A:D,4,0) -> Jerome Coelho | E92: =VLOOKUP(B92,Validation!A:E,5,0) -> Ashraf Omran | F92: Active | G92: =YEAR(L92) -> 2025 | H92: Bank Transfer | I92: USD | J92: =VLOOKUP(I92,'XE rates'!A:D,4,0)*K92 -> -48 | K92: =-68+20 -> -48 | L92: 01-08-2025 | M92: =TEXT(L92,"mmm") -> Aug | N92: =$Y$1-R92 -> 196 | O92: =IF(N92<=30, "0-30 days", IF(N92<=60, "31-60 days", IF(N92<=90, "61-90 days", "Over 90+ days"))) -> Over 90+ days | P92: Credit Note-Waive off | Q92: 45903 | R92: 45910 | S92: Outstanding | T92: CN-INV-030925182457 | U92: No | V92: No | W92: credit note will be settled against future invoices | AB92: =VLOOKUP(T92,'[2]Query result'!$F:$G,2,0) -> Partially Paid
A93: N1 | B93: Aspire FT Pte Ltd | C93: =VLOOKUP(B93,Validation!A:B,2,0) -> APAC | D93: =VLOOKUP(B93,Validation!A:D,4,0) -> Shi Yin | E93: =VLOOKUP(B93,Validation!A:E,5,0) -> Gitesh Athavale | F93: Active | G93: =YEAR(L93) -> 2026 | H93: Bank Transfer | I93: SGD | J93: =VLOOKUP(I93,'XE rates'!A:D,4,0)*K93 -> -85143.008 | K93: -109615.32 | L93: 01-01-2026 | M93: =TEXT(L93,"mmm") -> Jan | N93: =$Y$1-R93 -> 39 | O93: =IF(N93<=30, "0-30 days", IF(N93<=60, "31-60 days", IF(N93<=90, "61-90 days", "Over 90+ days"))) -> 31-60 days | P93: Monthly Billing | Q93: 46060 | R93: 46067 | S93: Outstanding | T93: INV-070226172013 | AB93: =VLOOKUP(T93,'[2]Query result'!$F:$G,2,0) -> Outstanding
A94: N1 | B94: Aspire FT Pte Ltd | C94: =VLOOKUP(B94,Validation!A:B,2,0) -> APAC | D94: =VLOOKUP(B94,Validation!A:D,4,0) -> Shi Yin | E94: =VLOOKUP(B94,Validation!A:E,5,0) -> Gitesh Athavale | F94: Active | G94: =YEAR(L94) -> 2026 | H94: Bank Transfer | I94: SGD | J94: =VLOOKUP(I94,'XE rates'!A:D,4,0)*K94 -> -18657.244 | K94: -24019.821 | L94: 01-02-2026 | M94: =TEXT(L94,"mmm") -> Feb | N94: =$Y$1-R94 -> -9 | O94: =IF(N94<=30, "0-30 days", IF(N94<=60, "31-60 days", IF(N94<=90, "61-90 days", "Over 90+ days"))) -> 0-30 days | P94: Monthly Billing | Q94: 46085 | R94: 46115 | S94: Invoice Sent | T94: INV-040326135331 | AB94: =VLOOKUP(T94,'[2]Query result'!$F:$G,2,0) -> Invoice Sent
A95: N1 | B95: Azimo Limited. | C95: =VLOOKUP(B95,Validation!A:B,2,0) -> EU/UK | D95: =VLOOKUP(B95,Validation!A:D,4,0) -> Sachli Zare | E95: =VLOOKUP(B95,Validation!A:E,5,0) -> Gitesh Athavale | F95: Active | G95: =YEAR(L95) -> 2026 | H95: Bank Transfer | I95: GBP | J95: =VLOOKUP(I95,'XE rates'!A:D,4,0)*K95 -> 88.775966 | K95: 66.4 | L95: 01-02-2026 | M95: =TEXT(L95,"mmm") -> Feb | N95: =$Y$1-R95 -> -8 | O95: =IF(N95<=30, "0-30 days", IF(N95<=60, "31-60 days", IF(N95<=90, "61-90 days", "Over 90+ days"))) -> 0-30 days | P95: Monthly Billing | Q95: 46084 | R95: 46114 | S95: Invoice Sent | T95: INV-030326093301 | U95: No | V95: No | W95: No response from the client post reminder sent | AB95: =VLOOKUP(T95,'[2]Query result'!$F:$G,2,0) -> Invoice Sent
A96: N1 | B96: Banque Patronus | C96: =VLOOKUP(B96,Validation!A:B,2,0) -> ME | D96: =VLOOKUP(B96,Validation!A:D,4,0) -> Jerome Coelho | E96: =VLOOKUP(B96,Validation!A:E,5,0) -> Saikat Roy | F96: Active | G96: =YEAR(L96) -> 2026 | H96: Bank Transfer | I96: USD | J96: =VLOOKUP(I96,'XE rates'!A:D,4,0)*K96 -> 3000 | K96: 3000 | L96: 2026-02-01 | M96: =TEXT(L96,"mmm") -> Feb | N96: =$Y$1-R96 -> 15 | O96: =IF(N96<=30, "0-30 days", IF(N96<=60, "31-60 days", IF(N96<=90, "61-90 days", "Over 90+ days"))) -> 0-30 days | P96: Monthly Billing | Q96: 46084 | R96: 46091 | S96: Outstanding | T96: INV-030326005231 | AB96: =VLOOKUP(T96,'[2]Query result'!$F:$G,2,0) -> Outstanding
A97: N1 | B97: Budgetly Pty Ltd | C97: =VLOOKUP(B97,Validation!A:B,2,0) -> APAC | D97: =VLOOKUP(B97,Validation!A:D,4,0) -> Hao Nguyen | E97: =VLOOKUP(B97,Validation!A:E,5,0) -> Vinoth M | F97: Active | G97: =YEAR(L97) -> 2026 | H97: Bank Transfer | I97: AUD | J97: =VLOOKUP(I97,'XE rates'!A:D,4,0)*K97 -> 2576.0278 | K97: 3847.873 | L97: 01-02-2026 | M97: =TEXT(L97,"mmm") -> Feb | N97: =$Y$1-R97 -> -9 | O97: =IF(N97<=30, "0-30 days", IF(N97<=60, "31-60 days", IF(N97<=90, "61-90 days", "Over 90+ days"))) -> 0-30 days | P97: Monthly Billing | Q97: 46085 | R97: 46115 | S97: Invoice Sent | T97: INV-040326125850 | U97: Yes | V97: No | W97: Card printing invoice pending | AB97: =VLOOKUP(T97,'[2]Query result'!$F:$G,2,0) -> Invoice Sent
A98: N1 | B98: CashD Pty Ltd | C98: =VLOOKUP(B98,Validation!A:B,2,0) -> APAC | D98: =VLOOKUP(B98,Validation!A:D,4,0) -> NA | E98: =VLOOKUP(B98,Validation!A:E,5,0) -> Vinoth M | F98: Active | G98: =YEAR(L98) -> 2026 | H98: Bank Transfer | I98: AUD | J98: =VLOOKUP(I98,'XE rates'!A:D,4,0)*K98 -> 2105.4768 | K98: 3145 | L98: 01-02-2026 | M98: =TEXT(L98,"mmm") -> Feb | N98: =$Y$1-R98 -> 15 | O98: =IF(N98<=30, "0-30 days", IF(N98<=60, "31-60 days", IF(N98<=90, "61-90 days", "Over 90+ days"))) -> 0-30 days | P98: Monthly Billing | Q98: 46084 | R98: 46091 | S98: Outstanding | T98: INV-030326191331 | U98: Yes | V98: No | W98: No response from the client post reminder sent | AB98: =VLOOKUP(T98,'[2]Query result'!$F:$G,2,0) -> Outstanding
A99: N1 | B99: DK Limited | C99: =VLOOKUP(B99,Validation!A:B,2,0) -> Shared Centre | D99: =VLOOKUP(B99,Validation!A:D,4,0) -> Sanat Patakar | E99: =VLOOKUP(B99,Validation!A:E,5,0) -> Gitesh Athavale | F99: Active | G99: =YEAR(L99) -> 2026 | H99: Bank Transfer | I99: USD | J99: =VLOOKUP(I99,'XE rates'!A:D,4,0)*K99 -> 2971 | K99: 2971 | L99: 01-02-2026 | M99: =TEXT(L99,"mmm") -> Feb | N99: =$Y$1-R99 -> 15 | O99: =IF(N99<=30, "0-30 days", IF(N99<=60, "31-60 days", IF(N99<=90, "61-90 days", "Over 90+ days"))) -> 0-30 days | P99: Monthly Billing | Q99: 46084 | R99: 46091 | S99: Outstanding | T99: INV-030326185225 | AB99: =VLOOKUP(T99,'[2]Query result'!$F:$G,2,0) -> Outstanding
A100: N1 | B100: EBURY PARTNERS UK LIMITED | C100: =VLOOKUP(B100,Validation!A:B,2,0) -> EU/UK | D100: =VLOOKUP(B100,Validation!A:D,4,0) -> Margarita | E100: =VLOOKUP(B100,Validation!A:E,5,0) -> NA | F100: Active | G100: =YEAR(L100) -> 2026 | H100: Bank Transfer | I100: USD | J100: =VLOOKUP(I100,'XE rates'!A:D,4,0)*K100 -> 187.42 | K100: 187.42 | L100: 01-02-2026 | M100: =TEXT(L100,"mmm") -> Feb | N100: =$Y$1-R100 -> 12 | O100: =IF(N100<=30, "0-30 days", IF(N100<=60, "31-60 days", IF(N100<=90, "61-90 days", "Over 90+ days"))) -> 0-30 days | P100: Monthly Billing | Q100: 46087 | R100: 46094 | S100: Invoice Sent | T100: INV-060326152527 | U100: Yes | AB100: =VLOOKUP(T100,'[2]Query result'!$F:$G,2,0) -> Outstanding
A101: N1 | B101: Emirates Islamic Bank PJSC | C101: =VLOOKUP(B101,Validation!A:B,2,0) -> ME | D101: =VLOOKUP(B101,Validation!A:D,4,0) -> Jerome Coelho | E101: =VLOOKUP(B101,Validation!A:E,5,0) -> Rohit Bammi | F101: Active | G101: =YEAR(L101) -> 2026 | H101: Bank Transfer | I101: USD | J101: =VLOOKUP(I101,'XE rates'!A:D,4,0)*K101 -> 3284.5 | K101: 3284.5 | L101: 01-02-2026 | M101: =TEXT(L101,"mmm") -> Feb | N101: =$Y$1-R101 -> 14 | O101: =IF(N101<=30, "0-30 days", IF(N101<=60, "31-60 days", IF(N101<=90, "61-90 days", "Over 90+ days"))) -> 0-30 days | P101: Monthly Billing | Q101: 46085 | R101: 46092 | S101: Outstanding | T101: INV-040326135554 | AB101: =VLOOKUP(T101,'[2]Query result'!$F:$G,2,0) -> Outstanding
A102: N1 | B102: Emirates NBD Bank PJSC | C102: =VLOOKUP(B102,Validation!A:B,2,0) -> ME | D102: =VLOOKUP(B102,Validation!A:D,4,0) -> Jerome Coelho | E102: =VLOOKUP(B102,Validation!A:E,5,0) -> Rohit Bammi | F102: Active | G102: =YEAR(L102) -> 2026 | H102: Bank Transfer | I102: USD | J102: =VLOOKUP(I102,'XE rates'!A:D,4,0)*K102 -> 35903.5 | K102: 35903.5 | L102: 01-02-2026 | M102: =TEXT(L102,"mmm") -> Feb | N102: =$Y$1-R102 -> 14 | O102: =IF(N102<=30, "0-30 days", IF(N102<=60, "31-60 days", IF(N102<=90, "61-90 days", "Over 90+ days"))) -> 0-30 days | P102: Monthly Billing | Q102: 46085 | R102: 46092 | S102: Outstanding | T102: INV-040326162658 | AB102: =VLOOKUP(T102,'[2]Query result'!$F:$G,2,0) -> Outstanding
A103: N1 | B103: Express Hub Services Pty Ltd | C103: =VLOOKUP(B103,Validation!A:B,2,0) -> APAC | D103: =VLOOKUP(B103,Validation!A:D,4,0) -> NA | E103: =VLOOKUP(B103,Validation!A:E,5,0) -> Wendy zhai | F103: Active | G103: =YEAR(L103) -> 2026 | H103: Bank Transfer | I103: AUD | J103: =VLOOKUP(I103,'XE rates'!A:D,4,0)*K103 -> 3319.6976 | K103: 4958.71 | L103: 01-02-2026 | M103: =TEXT(L103,"mmm") -> Feb | N103: =$Y$1-R103 -> 15 | O103: =IF(N103<=30, "0-30 days", IF(N103<=60, "31-60 days", IF(N103<=90, "61-90 days", "Over 90+ days"))) -> 0-30 days | P103: Monthly Billing | Q103: 46084 | R103: 46091 | S103: Outstanding | T103: INV-030326151733 | AB103: =VLOOKUP(T103,'[2]Query result'!$F:$G,2,0) -> Outstanding
A104: N1 | B104: Finofo Inc | C104: =VLOOKUP(B104,Validation!A:B,2,0) -> USA | D104: =VLOOKUP(B104,Validation!A:D,4,0) -> NA | E104: =VLOOKUP(B104,Validation!A:E,5,0) -> Michael Bermingham | F104: Active | G104: =YEAR(L104) -> 2026 | H104: Bank Transfer | I104: USD | J104: =VLOOKUP(I104,'XE rates'!A:D,4,0)*K104 -> 610 | K104: 610 | L104: 01-02-2026 | M104: =TEXT(L104,"mmm") -> Feb | N104: =$Y$1-R104 -> 12 | O104: =IF(N104<=30, "0-30 days", IF(N104<=60, "31-60 days", IF(N104<=90, "61-90 days", "Over 90+ days"))) -> 0-30 days | P104: Monthly Billing | Q104: 46087 | R104: 46094 | S104: Invoice Sent | T104: INV-060326111243 | AB104: =VLOOKUP(T104,'[2]Query result'!$F:$G,2,0) -> Partially Paid
A105: N1 | B105: FIRSTKYC PTE. LTD. | C105: =VLOOKUP(B105,Validation!A:B,2,0) -> APAC | D105: =VLOOKUP(B105,Validation!A:D,4,0) -> NA | E105: =VLOOKUP(B105,Validation!A:E,5,0) -> Denis Tan | F105: Active | G105: =YEAR(L105) -> 2026 | H105: Bank Transfer | I105: USD | J105: =VLOOKUP(I105,'XE rates'!A:D,4,0)*K105 -> 6.88 | K105: 6.88 | L105: 01-02-2026 | M105: =TEXT(L105,"mmm") -> Feb | N105: =$Y$1-R105 -> 14 | O105: =IF(N105<=30, "0-30 days", IF(N105<=60, "31-60 days", IF(N105<=90, "61-90 days", "Over 90+ days"))) -> 0-30 days | P105: Monthly Billing | Q105: 46085 | R105: 46092 | S105: Outstanding | T105: INV-040326132912 | U105: Yes | V105: No | W105: Client will settle once lumpsum threshold achieved | AB105: =VLOOKUP(T105,'[2]Query result'!$F:$G,2,0) -> Outstanding
A106: N1 | B106: Franklin Technologies ApS | C106: =VLOOKUP(B106,Validation!A:B,2,0) -> EU/UK | D106: =VLOOKUP(B106,Validation!A:D,4,0) -> Sachli Zare | E106: =VLOOKUP(B106,Validation!A:E,5,0) -> Gagan Smara | F106: Active | G106: =YEAR(L106) -> 2026 | H106: Bank Transfer | I106: EUR | J106: =VLOOKUP(I106,'XE rates'!A:D,4,0)*K106 -> -91021.736 | K106: -78581.66 | L106: 01-02-2026 | M106: =TEXT(L106,"mmm") -> Feb | N106: =$Y$1-R106 -> 6 | O106: =IF(N106<=30, "0-30 days", IF(N106<=60, "31-60 days", IF(N106<=90, "61-90 days", "Over 90+ days"))) -> 0-30 days | P106: Monthly Billing | Q106: 46086 | R106: 46100 | S106: Invoice Sent | T106: INV-050326163610 | AB106: =VLOOKUP(T106,'[2]Query result'!$F:$G,2,0) -> Outstanding
A107: N1 | B107: Genieum Services Pty Ltd | C107: =VLOOKUP(B107,Validation!A:B,2,0) -> APAC | D107: =VLOOKUP(B107,Validation!A:D,4,0) -> NA | E107: =VLOOKUP(B107,Validation!A:E,5,0) -> Vinoth M | F107: Active | G107: =YEAR(L107) -> 2026 | H107: Bank Transfer | I107: AUD | J107: =VLOOKUP(I107,'XE rates'!A:D,4,0)*K107 -> 1896.971 | K107: 2833.55 | L107: 01-02-2026 | M107: =TEXT(L107,"mmm") -> Feb | N107: =$Y$1-R107 -> 15 | O107: =IF(N107<=30, "0-30 days", IF(N107<=60, "31-60 days", IF(N107<=90, "61-90 days", "Over 90+ days"))) -> 0-30 days | P107: Monthly Billing | Q107: 46084 | R107: 46091 | S107: Outstanding | T107: INV-030326161558 | AB107: =VLOOKUP(T107,'[2]Query result'!$F:$G,2,0) -> Outstanding
A108: N1 | B108: Global E-Payment Limited-SG | C108: =VLOOKUP(B108,Validation!A:B,2,0) -> APAC | D108: =VLOOKUP(B108,Validation!A:D,4,0) -> Pat Sarisa | E108: =VLOOKUP(B108,Validation!A:E,5,0) -> NA | F108: Active | G108: =YEAR(L108) -> 2026 | H108: Bank Transfer | I108: USD | J108: =VLOOKUP(I108,'XE rates'!A:D,4,0)*K108 -> 10000 | K108: 10000 | L108: 01-02-2026 | M108: =TEXT(L108,"mmm") -> Feb | N108: =$Y$1-R108 -> 13 | O108: =IF(N108<=30, "0-30 days", IF(N108<=60, "31-60 days", IF(N108<=90, "61-90 days", "Over 90+ days"))) -> 0-30 days | P108: Monthly Billing | Q108: 46086 | R108: 46093 | S108: Outstanding | T108: INV-050326103533 | AB108: =VLOOKUP(T108,'[2]Query result'!$F:$G,2,0) -> Outstanding
A109: N1 | B109: goLance, Inc. | C109: =VLOOKUP(B109,Validation!A:B,2,0) -> USA | D109: =VLOOKUP(B109,Validation!A:D,4,0) -> Eduardo Avallone | E109: =VLOOKUP(B109,Validation!A:E,5,0) -> Greg McAllister | F109: Active | G109: =YEAR(L109) -> 2026 | H109: Bank Transfer | I109: USD | J109: =VLOOKUP(I109,'XE rates'!A:D,4,0)*K109 -> 40 | K109: 40 | L109: 2026-02-01 | M109: =TEXT(L109,"mmm") -> Feb | N109: =$Y$1-R109 -> 16 | O109: =IF(N109<=30, "0-30 days", IF(N109<=60, "31-60 days", IF(N109<=90, "61-90 days", "Over 90+ days"))) -> 0-30 days | P109: Monthly Billing | Q109: 46083 | R109: 46090 | S109: Outstanding | T109: INV-020326192002 | U109: Yes | V109: No | W109: No response from the client post reminder sent | AB109: =VLOOKUP(T109,'[2]Query result'!$F:$G,2,0) -> Outstanding
A110: N1 | B110: Ichange Pte Ltd | C110: =VLOOKUP(B110,Validation!A:B,2,0) -> APAC | D110: =VLOOKUP(B110,Validation!A:D,4,0) -> Shi Yin | E110: =VLOOKUP(B110,Validation!A:E,5,0) -> Gitesh Athavale | F110: Active | G110: =YEAR(L110) -> 2026 | H110: Bank Transfer | I110: SGD | J110: =VLOOKUP(I110,'XE rates'!A:D,4,0)*K110 -> 20255.21 | K110: 26077.085 | L110: 01-02-2026 | M110: =TEXT(L110,"mmm") -> Feb | N110: =$Y$1-R110 -> 12 | O110: =IF(N110<=30, "0-30 days", IF(N110<=60, "31-60 days", IF(N110<=90, "61-90 days", "Over 90+ days"))) -> 0-30 days | P110: Monthly Billing | Q110: 46087 | R110: 46094 | S110: Invoice Sent | T110: INV-060326112524 | AB110: =VLOOKUP(T110,'[2]Query result'!$F:$G,2,0) -> Outstanding
A111: N1 | B111: Istanbul Ödeme ve Elektronik Para A.S | C111: =VLOOKUP(B111,Validation!A:B,2,0) -> ME | D111: =VLOOKUP(B111,Validation!A:D,4,0) -> Jerome Coelho | E111: =VLOOKUP(B111,Validation!A:E,5,0) -> Ashraf Omran | F111: Active | G111: =YEAR(L111) -> 2026 | H111: Bank Transfer | I111: USD | J111: =VLOOKUP(I111,'XE rates'!A:D,4,0)*K111 -> 2500 | K111: 2500 | L111: 2026-02-01 | M111: =TEXT(L111,"mmm") -> Feb | N111: =$Y$1-R111 -> 16 | O111: =IF(N111<=30, "0-30 days", IF(N111<=60, "31-60 days", IF(N111<=90, "61-90 days", "Over 90+ days"))) -> 0-30 days | P111: Monthly Billing | Q111: 46083 | R111: 46090 | S111: Force Settlement | T111: INV-020326191014 | U111: Yes | V111: No | W111: No response from the client post reminder sent | AB111: =VLOOKUP(T111,'[2]Query result'!$F:$G,2,0) -> Force Settlement
A112: N1 | B112: JPMORGAN CHASE BANK | C112: =VLOOKUP(B112,Validation!A:B,2,0) -> EU/UK | D112: =VLOOKUP(B112,Validation!A:D,4,0) -> Sachli Zare | E112: =VLOOKUP(B112,Validation!A:E,5,0) -> NA | F112: Active | G112: =YEAR(L112) -> 2026 | H112: Bank Transfer | I112: USD | J112: =VLOOKUP(I112,'XE rates'!A:D,4,0)*K112 -> 105.1 | K112: 105.1 | L112: 01-02-2026 | M112: =TEXT(L112,"mmm") -> Feb | N112: =$Y$1-R112 -> 14 | O112: =IF(N112<=30, "0-30 days", IF(N112<=60, "31-60 days", IF(N112<=90, "61-90 days", "Over 90+ days"))) -> 0-30 days | P112: Monthly Billing | Q112: 46085 | R112: 46092 | S112: Outstanding | T112: INV-040326132449 | U112: Yes | V112: No | W112: Partially settled by the client | AB112: =VLOOKUP(T112,'[2]Query result'!$F:$G,2,0) -> Outstanding
...

Sheet Rebates
A1: Platform | B1: Customer Label | C1: Region | D1: Account Manager | E1: BD | F1: Client Status | G1: Year | H1: Settlement Type | I1: Currency | J1: USD AMOUNT | K1: Invoice Amount | L1: Billing Period | M1: Month | N1: Days | O1: Ageing Tier | P1: Fee Type | Q1: Invoice Date | R1: Due Date | S1: Invoice Status | T1: Invoice Number | U1: Reminder Sent | V1: LOD | W1: AR's Comments | X1: AM's Comments
A2: N1 | B2: Al Muzaini Exchange | C2: ME | D2: Jerome Coelho | E2: Ashraf Omran | F2: Active | G2: 2025 | H2: Bank Transfer | I2: USD | J2: -68 | K2: -68 | L2: 45870 | M2: Aug | N2: 170 | O2: Over 90+ days | P2: Credit Note-Waive off | Q2: 45903 | R2: 45910 | S2: Outstanding | T2: CN-INV-030925182457 | U2: No | V2: No | W2: credit note will be settled against future invoices
A3: N1 | B3: SBI Remit Co., Ltd. | C3: ME | D3: Jerome Coelho | E3: Rohit Bammi | F3: Active | G3: 2025 | H3: Bank Transfer | I3: USD | J3: -10 | K3: -10 | L3: 45901 | M3: Sep | N3: 137 | O3: Over 90+ days | P3: Credit Note-Rebate | Q3: 45936 | R3: 45943 | S3: Outstanding | T3: CN-INV-061025093259 | U3: No | V3: No | W3: credit note will be settled against future invoices
A4: N1 | B4: SBI Remit Co., Ltd. | C4: ME | D4: Jerome Coelho | E4: Rohit Bammi | F4: Active | G4: 2025 | H4: Bank Transfer | I4: USD | J4: -25 | K4: -25 | L4: 45931 | M4: Oct | N4: 107 | O4: Over 90+ days | P4: Credit Note-Rebate | Q4: 45966 | R4: 45973 | S4: Outstanding | T4: CN-INV-051125105233 | U4: No | V4: No | W4: credit note will be settled against future invoices
A5: N1 | B5: SBI Remit Co., Ltd. | C5: ME | D5: Jerome Coelho | E5: Rohit Bammi | F5: Active | G5: 2025 | H5: Bank Transfer | I5: USD | J5: -115 | K5: -115 | L5: 45962 | M5: Nov | N5: 79 | O5: 61-90 days | P5: Credit Note-Rebate | Q5: 45994 | R5: 46001 | S5: Outstanding | T5: CN-INV-031225192101 | U5: No | V5: No | W5: credit note will be settled against future invoices
A6: N1 | B6: SBI Remit Co., Ltd. | C6: ME | D6: Jerome Coelho | E6: Rohit Bammi | F6: Active | G6: 2025 | H6: Bank Transfer | I6: USD | J6: -96 | K6: -96 | L6: 45992 | M6: Dec | N6: 46 | O6: 31-60 days | P6: Credit Note-Rebate | Q6: 46027 | R6: 46034 | S6: Outstanding | T6: CN-INV-050126163126 | U6: Yes | V6: No | W6: credit note will be settled against future invoices
A7: N1 | B7: VOLOPAY.CO PTE. LTD. | C7: APAC | D7: XiaoXiao | E7: Gitesh Athavale | F7: Active | G7: 2025 | H7: Bank Transfer | I7: USD | J7: -527.4851 | K7: -527.4851 | L7: 45931 | M7: Oct | N7: 106 | O7: Over 90+ days | P7: Monthly Billing | Q7: 45967 | R7: 45974 | S7: Outstanding | T7: INV-061125120844 | U7: Yes | V7: No | W7: credit will be settled against future invoices
A8: N1 | B8: VOLOPAY.CO PTE. LTD. | C8: APAC | D8: XiaoXiao | E8: Gitesh Athavale | F8: Active | G8: 2025 | H8: Bank Transfer | I8: USD | J8: -3888.0024 | K8: -3888.0024 | L8: 45962 | M8: Nov | N8: 78 | O8: 61-90 days | P8: Monthly Billing | Q8: 45995 | R8: 46002 | S8: Outstanding | T8: INV-041225180916 | U8: Yes | V8: No | W8: credit will be settled against future invoices
A9: N1 | B9: VOLOPAY.CO PTE. LTD. | C9: APAC | D9: XiaoXiao | E9: Gitesh Athavale | F9: Active | G9: 2025 | H9: Bank Transfer | I9: USD | J9: -1738.4406 | K9: -1738.4406 | L9: 45992 | M9: Dec | N9: 45 | O9: 31-60 days | P9: Monthly Billing | Q9: 46028 | R9: 46035 | S9: Outstanding | T9: INV-060126133501 | U9: Yes | V9: No | W9: credit will be settled against future invoices
A10: N1 | B10: Aspire FT Pte Ltd | C10: APAC | D10: Shi Yin | E10: Gitesh Athavale | F10: Active | G10: 2026 | H10: Bank Transfer | I10: SGD | J10: -85143.008 | K10: -109615.32 | L10: 46023 | M10: Jan | N10: 13 | O10: 0-30 days | P10: Monthly Billing | Q10: 46060 | R10: 46067 | S10: Outstanding | T10: INV-070226172013 | U10: Yes | V10: No | W10: No response from the client post reminder sent
A11: N1 | B11: Loadpass LTDA | C11: USA | D11: Eduardo Avallone | E11: Christina Hutchinson | F11: Active | G11: 2026 | H11: Bank Transfer | I11: USD | J11: -152.91 | K11: -152.91 | L11: 46023 | M11: Jan | N11: 17 | O11: 0-30 days | P11: Monthly Billing | Q11: 46056 | R11: 46063 | S11: Outstanding | T11: INV-030226233006 | U11: Yes | V11: No | W11: No response from the client post reminder sent
A12: N1 | B12: SBI Remit Co., Ltd. | C12: ME | D12: Jerome Coelho | E12: Rohit Bammi | F12: Active | G12: 2026 | H12: Bank Transfer | I12: USD | J12: -52 | K12: -52 | L12: 46023 | M12: Jan | N12: 14 | O12: 0-30 days | P12: Credit Note-Rebate | Q12: 46059 | R12: 46066 | S12: Outstanding | T12: INV-060226200521 | U12: Yes | V12: No | W12: No response from the client post reminder sent
A13: N1 | B13: VOLOPAY.CO PTE. LTD. | C13: APAC | D13: XiaoXiao | E13: Gitesh Athavale | F13: Active | G13: 2026 | H13: Bank Transfer | I13: USD | J13: -1754.3782 | K13: -1754.3782 | L13: 46023 | M13: Jan | N13: 13 | O13: 0-30 days | P13: Monthly Billing | Q13: 46060 | R13: 46067 | S13: Outstanding | T13: INV-070226184910 | U13: Yes | V13: No | W13: credit will be settled against future invoices
A14: Masspay | B14: borderless llc | C14: USA | D14: Lia Susin | E14: NA | F14: Active | G14: 2026 | H14: Wallet Debit | I14: USD | J14: -105.02 | K14: -105.02 | L14: 46023 | M14: Jan | N14: -27 | O14: 0-30 days | P14: Credit Note-Rebate | Q14: 46079 | R14: 46107 | S14: Invoice Sent | T14: US-CN-Borderless-01-2026 | U14: No | V14: No | W14: credit note will be settled against future invoices
I15: Total | J15: =SUM(J2:J14) -> -93675.244

Sheet XE rates
A1: Currency | B1: Name | C1: Units per USD | D1: USD per unit
A2: USD | B2: US Dollar | C2: 1 | D2: 1
A3: EUR | B3: Euro | C3: 0.86332852 | D3: 1.1583076
A4: GBP | B4: British Pound | C4: 0.74795019 | D4: 1.3369874
A5: INR | B5: Indian Rupee | C5: 90.72556 | D5: 0.011022252
A6: AUD | B6: Australian Dollar | C6: 1.4937234 | D6: 0.66946798
A7: CAD | B7: Canadian Dollar | C7: 1.3917133 | D7: 0.7185388
A8: SGD | B8: Singapore Dollar | C8: 1.287426 | D8: 0.77674366
A9: CHF | B9: Swiss Franc | C9: 0.80260194 | D9: 1.2459476
A10: MYR | B10: Malaysian Ringgit | C10: 4.0571159 | D10: 0.24648051
A11: JPY | B11: Japanese Yen | C11: 158.30924 | D11: 0.0063167506
A12: CNY | B12: Chinese Yuan Renminbi | C12: 6.9689281 | D12: 0.14349409
A13: NZD | B13: New Zealand Dollar | C13: 1.7386016 | D13: 0.57517489
... A189: ZWG | B189: Zimbabwean Dollar | C189: 25.67768 | D189: 0.038944329

Sheet Validation
A2: Customer Label | B2: Region | C2: Region2 | D2: Account Manager | E2: BD
A3: Stylopay Pte. Ltd | B3: APAC | C3: APAC | D3: XiaoXiao | E3: NA
A4: PayQuicker LLC | B4: USA | C4: USA | D4: Eduardo Avallone | E4: Kyle Reny
A5: Varni Tech Inc | B5: APAC | C5: APAC | D5: Jerome Coelho | E5: Gitesh Athavale
A6: aerapass pte. ltd | B6: APAC | C6: APAC | D6: Jerome Coelho | E6: Gitesh Athavale
A7: Knox Payments Ltd. | B7: USA | C7: USA | D7: Tanu Arora | E7: NA
A8: TClub Inc. | B8: USA | C8: USA | D8: Tanu Arora | E8: NA
A9: Transwap Private Limited | B9: APAC | C9: APAC | D9: Jerome Coelho | E9: Gitesh Athavale
A10: Widoph Remit | B10: APAC | C10: APAC | D10: NA | E10: Vinoth M
A11: MeshPay UK | B11: EU/UK | C11: UK | D11: Sachli Zare | E11: Gitesh Athavale
A12: MeshPay UK Ltd | B12: EU/UK | C12: UK | D12: Sachli Zare | E12: Gitesh Athavale
A13: SPROUT CORPORATE SERVICES PTE LTD | B13: APAC | C13: APAC | D13: Shi Yin | E13: Gitesh Athavale
... A141: ASIABILL COMPANY LIMITED | B141: APAC | C141: APAC | D141: NA | E141: Edward Li
A142: DK Limited | B142: Shared Centre | C142: =B142 -> Shared Centre | D142: Sanat Patakar | E142: Gitesh Athavale
A143: Pelikin Holdings Limited | B143: APAC | C143: APAC | D143: Hao Nguyen | E143: Vinoth M
A144: PT PELITA TRANSFER NUSANTARA | B144: APAC | C144: APAC | D144: Luciana | E144: NA
A145: pesapeer incorporated | B145: USA | C145: USA | D145: Eduardo Avallone | E145: NA
A146: PT Dhanapatra Loka Abadi | B146: APAC | C146: APAC | D146: Hari Budiman | E146: Hari Budiman
A147: CADANA INC | B147: USA | C147: USA | D147: Tanu Arora | E147: NA
A148: KappaPayCameroonS.A.(KPC) | B148: USA | C148: USA | D148: NA | E148: Michael Podrid
A149: Nala Inc | B149: USA | C149: USA | D149: NA | E149: Michael Bermingham
A150: Nala Payments Canada | B150: USA | C150: USA | D150: NA | E150: Michael Bermingham
A151: Red Owl Pty Ltd | B151: APAC | C151: APAC | D151: NA | E151: Vinoth M
A152: Yariex Group Corp | B152: USA | C152: USA | D152: NA | E152: Michael Podrid
A153: SIAM COMMERCIAL BANK PUBLIC COMPANY LIMITED | B153: APAC | C153: APAC | D153: Pat Sarisa | E153: NA
A154: tiagn i inc. dba libertypay | B154: USA | C154: USA | D154: NA | E154: NA
... A159: PT Reyhan Putra Mandiri | B159: APAC | C159: APAC | D159: Hari Budiman | E159: NA
A160: PT Harsya Remitindo | B160: Shared Centre | C160: =B160 -> Shared Centre | D160: Sanat Patakar | E160: Hari Budiman
A161: 6G Digital Remittance Limited | B161: USA | C161: USA | D161: NA | E161: Greg McAllister
A162: PT Midtrans | B162: APAC | C162: APAC | D162: Hao Nguyen | E162: Hari Budiman
A163: DRUO, Inc. | B163: USA | C163: USA | D163: NA | E163: Michael Podrid
A164: Nowports, Inc. | B164: USA | C164: USA | D164: NA | E164: Greg McAllister
A165: Taram Inc., | B165: USA | C165: USA | D165: NA | E165: Michael Podrid
A166: Wingspan Networks Inc | B166: USA | C166: USA | D166: Tanu Arora | E166: Tyler Reed
A167: City International Exchange Co. wll | B167: APAC | C167: APAC | D167: NA | E167: Ashraf Omran
A168: goLance, Inc. | B168: USA | C168: USA | D168: Eduardo Avallone | E168: Greg McAllister
A169: Spreadfun Pte. Ltd. | B169: APAC | C169: APAC | D169: Shi Yin | E169: NA
A170: Unified Signal, Inc. | B170: USA | C170: USA | D170: NA | E170: Michael Bermingham
A171: Glide APAC Pte. Ltd. | B171: APAC | C171: APAC | D171: NA | E171: Gitesh Athavale
A172: Rank Wyre pay Inc | B172: USA | C172: USA | D172: NA | E172: Winfred
... A209: Ibanera Private Limited | B209: USA | C209: USA | D209: Eduardo Avallone | E209: Michael Bermingham
A210: nsKnox Technologies Ltd | B210: Shared Centre | C210: =B210 -> Shared Centre | D210: Bhavani | E210: NA
A211: rewire | B211: EU/UK | C211: EU | D211: NA | E211: NA
A212: Depiteq, Inc. | B212: USA | C212: USA | D212: NA | E212: Greg McAllister
A213: Genieum Services Pty Ltd | B213: APAC | C213: APAC | D213: NA | E213: Vinoth M
A214: OZIN INTERNATIONAL PTY LTD | B214: APAC | C214: APAC | D214: NA | E214: Vinoth M
A215: Payease Technology (Hong Kong) Limited | B215: APAC | C215: APAC | D215: Pat Sarisa | E215: Edward Li
A216: Pelikin Ventures Pty Ltd | B216: APAC | C216: APAC | D216: Hao Nguyen | E216: Vinoth M
A217: WAN GUO GROUP HOLDING LIMITED | B217: Shared Centre | C217: =B217 -> Shared Centre | D217: Sanat Patakar | E217: Gitesh Athavale
A218: AL FUAD EXCHANGE | B218: ME | C218: ME | D218: Jerome Coelho | E218: Saikat Roy
A219: AVENIDA VESSEL | B219: USA | C219: USA | D219: NA | E219: Christina Hutchinson
A220: EPAY LIMITED | B220: APAC | C220: APAC | D220: Pat Sarisa | E220: Gitesh Athavale
A221: Jillion Group International Trading Limited | B221: APAC | C221: APAC | D221: NA | E221: Edward Li
A222: Zeni, Inc. | B222: USA | C222: USA | D222: NA | E222: Tyler Reed
A223: Mizzen Digital DMCC | B223: ME | C223: ME | D223: Jerome Coelho | E223: Rohit Bammi
A224: Cimb Speedsend | B224: APAC | C224: APAC | D224: Pat Sarisa | E224: NA
A225: Cimb Speedsend-EUR Corridor | B225: APAC | C225: APAC | D225: Pat Sarisa | E225: NA
A226: Cimb Speedsend-GBP Corridor | B226: APAC | C226: APAC | D226: Pat Sarisa | E226: NA
A227: Cimb Speedsend-SGD Corridor | B227: APAC | C227: APAC | D227: Pat Sarisa | E227: NA
A228: AL DAR FOR EXCHANGE WORKS | B228: ME | C228: ME | D228: Jerome Coelho | E228: NA
A229: Emirates Islamic Bank PJSC | B229: ME | C229: ME | D229: Jerome Coelho | E229: Rohit Bammi
... A231: KOHO Financial Inc.-Verify | B231: USA | C231: USA | D231: Eduardo Avallone | E231: Vinoth M
A232: SBI Remit Co., Ltd. | B232: Shared Centre | C232: =B232 -> Shared Centre | D232: Sanat Patakar | E232: Rohit Bammi
A233: Tensec Payments, Inc. | B233: USA | C233: USA | D233: NA | E233: Greg McAllister
A234: cohortgo | B234: APAC | C234: APAC | D234: Hao Nguyen | E234: NA
A235: Alipay Merchant Services Pte. Ltd. | B235: APAC | C235: APAC | D235: NA | E235: Lisa Sung
A236: DK Limited-Verify | B236: Shared Centre | C236: =B236 -> Shared Centre | D236: Sanat Patakar | E236: NA
A237: PT UCE Global Utama | B237: APAC | C237: APAC | D237: NA | E237: Hari Budiman
A238: VECTOR HOLDINGS PTY LTD | B238: Shared Centre | C238: =B238 -> Shared Centre | D238: Sanat Patakar | E238: NA
A239: Nomba Financial Services Ltd | B239: ME | C239: ME | D239: Jerome Coelho | E239: Winfred
A240: bank of ayudhya public company | B240: APAC | C240: APAC | D240: Pat Sarisa | E240: NA
A241: Qatar National Bank (Q.P.S.C.) | B241: ME | C241: ME | D241: Jerome Coelho | E241: Rohit Bammi
A242: Ardua Solutions Corp | B242: USA | C242: USA | D242: NA | E242: Christina Hutchinson
A243: BANCO BS2 S/A | B243: USA | C243: USA | D243: NA | E243: Christina Hutchinson
A244: Banco Ourinvest S.A. | B244: USA | C244: USA | D244: Eduardo Avallone | E244: NA
A245: Hitpay Payment Solutions Pte. Ltd. | B245: Shared Centre | C245: =B245 -> Shared Centre | D245: Sanat Patakar | E245: Febriali Tan
A246: International Payments Identity Pte. Ltd. | B246: APAC | C246: APAC | D246: NA | E246: Febriali Tan
A247: PIPO (SG) Pte. Ltd. | B247: APAC | C247: APAC | D247: NA | E247: Lisa Sung
A248: kina bank | B248: APAC | C248: APAC | D248: Hao Nguyen | E248: NA
A249: PT Kredigram Pembayaran Elektronis | B249: APAC | C249: APAC | D249: NA | E249: Hari Budiman
A250: Al Muzaini Exchange | B250: ME | C250: ME | D250: Jerome Coelho | E250: Ashraf Omran
A251: Bank of Ayudhya Public Company Limited | B251: APAC | C251: APAC | D251: Pat Sarisa | E251: NA
A252: Commercial Bank of Kuwait KPSC | B252: ME | C252: ME | D252: Jerome Coelho | E252: Ashraf Omran
A253: FIRSTKYC PTE. LTD. | B253: APAC | C253: APAC | D253: NA | E253: Denis Tan
A254: Global E-Payment Limited-SG | B254: APAC | C254: APAC | D254: Pat Sarisa | E254: NA
A255: Utransfer US LLC | B255: APAC | C255: APAC | D255: Joon Young Kim | E255: NA
A256: WORLDFIRST (SINGAPORE) MERCHANT SERVICES PTE. LTD. | B256: APAC | C256: APAC | D256: NA | E256: Lisa Sung
A257: MeshPay EU Ltd | B257: EU/UK | C257: EU | D257: Sachli Zare | E257: NA
... A266: 33 Remittance Company Limited | B266: APAC | C266: APAC | D266: Pat Sarisa | E266: NA
A267: al mulla international exchange company,k.s.c.c. | B267: ME | C267: =B267 -> ME | D267: Jerome Coelho | E267: NA
A268: Al Rostamani International Exchange LLC | B268: ME | C268: =B268 -> ME | D268: Jerome Coelho | E268: NA
A269: ample Transfer | B269: SME | C269: =B269 -> SME | D269: NA | E269: NA
A270: ample Transfer | B270: SME | C270: =B270 -> SME | D270: NA | E270: NA
A271: currency bird | B271: USA | C271: =B271 -> USA | D271: Eduardo Avallone | E271: NA
A272: global exchange uk | B272: EU/UK | C272: =B272 -> EU/UK | D272: Sachli Zare | E272: NA
A273: Global81 | B273: USA | C273: =B273 -> USA | D273: Lia Susin | E273: NA
A274: mashreq | B274: ME | C274: =B274 -> ME | D274: Jerome Coelho | E274: NA
A275: modern exchange co llc | B275: ME | C275: =B275 -> ME | D275: Jerome Coelho | E275: NA
A276: moin 2 | B276: APAC | C276: =B276 -> APAC | D276: Hao Nguyen | E276: NA
A277: moin inc | B277: APAC | C277: =B277 -> APAC | D277: Hao Nguyen | E277: NA
...
